Workbook

Sheet BALANCE SHEET 
A4: Powered by Clearbit
A5: NVIDIA Corp (NMS: NVDA)
A6: Standardized Annual Balance Sheet | B6: 2015 | C6: 2016 | D6: 2017 | E6: 2018 | F6: 2019 | G6: 2020 | H6: 2021 | I6: 2022 | J6: 2023 | K6: 2024
A7: Report Date | B7: 01/25/2015 | C7: 01/31/2016 | D7: 01/29/2017 | E7: 01/28/2018 | F7: 01/27/2019 | G7: 01/26/2020 | H7: 01/31/2021 | I7: 01/30/2022 | J7: 01/29/2023 | K7: 01/28/2024
A8: Currency | B8: USD | C8: USD | D8: USD | E8: USD | F8: USD | G8: USD | H8: USD | I8: USD | J8: USD | K8: USD
A9: Consolidated | B9: Yes | C9: Yes | D9: Yes | E9: Yes | F9: Yes | G9: Yes | H9: Yes | I9: Yes | J9: Yes | K9: Yes
A10: Scale | B10: Thousands | C10: Thousands | D10: Thousands | E10: Thousands | F10: Thousands | G10: Thousands | H10: Thousands | I10: Thousands | J10: Thousands | K10: Thousands
A11: Cash & Equivalents | B11: 496654 | C11: 596000 | D11: 1766000 | E11: 4002000 | F11: 782000 | G11: 10896000 | H11: 847000 | I11: 1990000 | J11: 3389000 | K11: 7280000
A12: Short Term Investments | B12: 4126685 | C12: 4441000 | D12: 5032000 | E12: 3106000 | F12: 6640000 | G12: 1000 | H12: 10714000 | I12: 19218000 | J12: 9907000 | K12: 18704000
A13: Cash & Equivs & ST Investments | B13: 4623339 | C13: 5037000 | D13: 6798000 | E13: 7108000 | F13: 7422000 | G13: 10897000 | H13: 11561000 | I13: 21208000 | J13: 13296000 | K13: 25984000
A14: Receivables (ST) | B14: 473637 | C14: 505000 | D14: 826000 | E14: 1265000 | F14: 1424000 | G14: 1657000 | H14: 2429000 | I14: 4650000 | J14: 3827000 | K14: 9999000
A15: Inventories | B15: 482893 | C15: 418000 | D15: 794000 | E15: 796000 | F15: 1575000 | G15: 979000 | H15: 1826000 | I15: 2605000 | J15: 5159000 | K15: 5282000
A16: Other Current Assets | B16: 70174 | C16: 93000 | D16: 118000 | E16: 86000 | F16: 136000 | G16: 157000 | H16: 239000 | I16: 366000 | J16: 791000 | K16: 3080000
A17: Total Current Assets | B17: 5713297 | C17: 6053000 | D17: 8536000 | E17: 9255000 | F17: 10557000 | G17: 13690000 | H17: 16055000 | I17: 28829000 | J17: 23073000 | K17: 44345000
A18: Gross Property Plant & Equip | B18: 1179257 | C18: 1100000 | D18: 1191000 | E18: 1737000 | F18: 2171000 | G18: 2685000 | H18: 3557000 | I18: 4681000 | J18: 6501000 | K18: 7423000
A19: Accumulated Depreciation | B19: 621975 | C19: 634000 | D19: 670000 | E19: 740000 | F19: 767000 | G19: 1011000 | H19: 1408000 | I19: 1903000 | J19: 2694000 | K19: 3509000
A20: Net Property Plant & Equip | B20: 557282 | C20: 466000 | D20: 521000 | E20: 997000 | F20: 1404000 | G20: 1674000 | H20: 2149000 | I20: 2778000 | J20: 3807000 | K20: 3914000
A21: Intangible Assets | B21: 839893 | C21: 784000 | D21: 722000 | E21: 670000 | F21: 663000 | G21: 667000 | H21: 6930000 | I21: 6688000 | J21: 6048000 | K21: 5542000
A22: Other Assets | B22: 90896 | C22: 67000 | D22: 62000 | E22: 319000 | F22: 668000 | G22: 736000 | H22: 2851000 | I22: 2248000 | J22: 1183000 | K22: 5846000
... A40: Total Liabilities & Equity | B40: 7201368 | C40: 7370000 | D40: 9841000 | E40: 11241000 | F40: 13292000 | G40: 17315000 | H40: 28791000 | I40: 44187000 | J40: 41182000 | K40: 65728000
A44: =

Sheet Percentage Balance sheet
A1: Standardized Annual Balance Sheet | B1: 2015 | C1: 2016 | D1: 2017 | E1: 2018 | F1: 2019 | G1: 2020 | H1: 2021 | I1: 2022 | J1: 2023 | K1: 2024
A2: Report Date | B2: 01/25/2015 | C2: 01/31/2016 | D2: 01/29/2017 | E2: 01/28/2018 | F2: 01/27/2019 | G2: 01/26/2020 | H2: 01/31/2021 | I2: 01/30/2022 | J2: 01/29/2023 | K2: 01/28/2024
A3: Currency | B3: USD | C3: USD | D3: USD | E3: USD | F3: USD | G3: USD | H3: USD | I3: USD | J3: USD | K3: USD
A4: Consolidated | B4: Yes | C4: Yes | D4: Yes | E4: Yes | F4: Yes | G4: Yes | H4: Yes | I4: Yes | J4: Yes | K4: Yes
A5: Scale | B5: Thousands | C5: Thousands | D5: Thousands | E5: Thousands | F5: Thousands | G5: Thousands | H5: Thousands | I5: Thousands | J5: Thousands | K5: Thousands
A6: Cash & Equivalents | B6: ='BALANCE SHEET '!B11/'BALANCE SHEET '!$B$23 -> 0.068966619 | C6: ='BALANCE SHEET '!C11/'BALANCE SHEET '!$C$23 -> 0.080868385 | D6: ='BALANCE SHEET '!D11/'BALANCE SHEET '!$D$23 -> 0.17945331 | E6: ='BALANCE SHEET '!E11/'BALANCE SHEET '!$E$23 -> 0.35601815 | F6: ='BALANCE SHEET '!F11/'BALANCE SHEET '!$F$23 -> 0.05883238 | G6: ='BALANCE SHEET '!G11/'BALANCE SHEET '!$G$23 -> 0.62928097 | H6: ='BALANCE SHEET '!H11/'BALANCE SHEET '!$H$23 -> 0.029418916 | I6: ='BALANCE SHEET '!I11/'BALANCE SHEET '!$I$23 -> 0.04503587 | J6: ='BALANCE SHEET '!J11/'BALANCE SHEET '!$J$23 -> 0.082293235 | K6: ='BALANCE SHEET '!K11/'BALANCE SHEET '!$K$23 -> 0.11075949
A7: Short Term Investments | B7: ='BALANCE SHEET '!B12/'BALANCE SHEET '!$B$23 -> 0.57304182 | C7: ='BALANCE SHEET '!C12/'BALANCE SHEET '!$C$23 -> 0.60257802 | D7: ='BALANCE SHEET '!D12/'BALANCE SHEET '!$D$23 -> 0.51133015 | E7: ='BALANCE SHEET '!E12/'BALANCE SHEET '!$E$23 -> 0.27630994 | F7: ='BALANCE SHEET '!F12/'BALANCE SHEET '!$F$23 -> 0.4995486 | G7: ='BALANCE SHEET '!G12/'BALANCE SHEET '!$G$23 -> 5.7753393e-05 | H7: ='BALANCE SHEET '!H12/'BALANCE SHEET '!$H$23 -> 0.37213018 | I7: ='BALANCE SHEET '!I12/'BALANCE SHEET '!$I$23 -> 0.4349243 | J7: ='BALANCE SHEET '!J12/'BALANCE SHEET '!$J$23 -> 0.24056627 | K7: ='BALANCE SHEET '!K12/'BALANCE SHEET '!$K$23 -> 0.2845667
A8: Cash & Equivs & ST Investments | B8: ='BALANCE SHEET '!B13/'BALANCE SHEET '!$B$23 -> 0.64200844 | C8: ='BALANCE SHEET '!C13/'BALANCE SHEET '!$C$23 -> 0.6834464 | D8: ='BALANCE SHEET '!D13/'BALANCE SHEET '!$D$23 -> 0.69078346 | E8: ='BALANCE SHEET '!E13/'BALANCE SHEET '!$E$23 -> 0.63232808 | F8: ='BALANCE SHEET '!F13/'BALANCE SHEET '!$F$23 -> 0.55838098 | G8: ='BALANCE SHEET '!G13/'BALANCE SHEET '!$G$23 -> 0.62933872 | H8: ='BALANCE SHEET '!H13/'BALANCE SHEET '!$H$23 -> 0.4015491 | I8: ='BALANCE SHEET '!I13/'BALANCE SHEET '!$I$23 -> 0.47996017 | J8: ='BALANCE SHEET '!J13/'BALANCE SHEET '!$J$23 -> 0.3228595 | K8: ='BALANCE SHEET '!K13/'BALANCE SHEET '!$K$23 -> 0.39532619
A9: Receivables (ST) | B9: ='BALANCE SHEET '!B14/'BALANCE SHEET '!$B$23 -> 0.06577042 | C9: ='BALANCE SHEET '!C14/'BALANCE SHEET '!$C$23 -> 0.068521031 | D9: ='BALANCE SHEET '!D14/'BALANCE SHEET '!$D$23 -> 0.083934559 | E9: ='BALANCE SHEET '!E14/'BALANCE SHEET '!$E$23 -> 0.11253447 | F9: ='BALANCE SHEET '!F14/'BALANCE SHEET '!$F$23 -> 0.10713211 | G9: ='BALANCE SHEET '!G14/'BALANCE SHEET '!$G$23 -> 0.095697372 | H9: ='BALANCE SHEET '!H14/'BALANCE SHEET '!$H$23 -> 0.084366642 | I9: ='BALANCE SHEET '!I14/'BALANCE SHEET '!$I$23 -> 0.10523457 | J9: ='BALANCE SHEET '!J14/'BALANCE SHEET '!$J$23 -> 0.09292895 | K9: ='BALANCE SHEET '!K14/'BALANCE SHEET '!$K$23 -> 0.15212695
A10: Inventories | B10: ='BALANCE SHEET '!B15/'BALANCE SHEET '!$B$23 -> 0.067055732 | C10: ='BALANCE SHEET '!C15/'BALANCE SHEET '!$C$23 -> 0.056716418 | D10: ='BALANCE SHEET '!D15/'BALANCE SHEET '!$D$23 -> 0.080682857 | E10: ='BALANCE SHEET '!E15/'BALANCE SHEET '!$E$23 -> 0.070812205 | F10: ='BALANCE SHEET '!F15/'BALANCE SHEET '!$F$23 -> 0.11849233 | G10: ='BALANCE SHEET '!G15/'BALANCE SHEET '!$G$23 -> 0.056540572 | H10: ='BALANCE SHEET '!H15/'BALANCE SHEET '!$H$23 -> 0.063422597 | I10: ='BALANCE SHEET '!I15/'BALANCE SHEET '!$I$23 -> 0.058953991 | J10: ='BALANCE SHEET '!J15/'BALANCE SHEET '!$J$23 -> 0.12527318 | K10: ='BALANCE SHEET '!K15/'BALANCE SHEET '!$K$23 -> 0.08036149
A11: Other Current Assets | B11: ='BALANCE SHEET '!B16/'BALANCE SHEET '!$B$23 -> 0.0097445374 | C11: ='BALANCE SHEET '!C16/'BALANCE SHEET '!$C$23 -> 0.012618725 | D11: ='BALANCE SHEET '!D16/'BALANCE SHEET '!$D$23 -> 0.011990651 | E11: ='BALANCE SHEET '!E16/'BALANCE SHEET '!$E$23 -> 0.0076505649 | F11: ='BALANCE SHEET '!F16/'BALANCE SHEET '!$F$23 -> 0.010231718 | G11: ='BALANCE SHEET '!G16/'BALANCE SHEET '!$G$23 -> 0.0090672827 | H11: ='BALANCE SHEET '!H16/'BALANCE SHEET '!$H$23 -> 0.0083012052 | I11: ='BALANCE SHEET '!I16/'BALANCE SHEET '!$I$23 -> 0.0082829792 | J11: ='BALANCE SHEET '!J16/'BALANCE SHEET '!$J$23 -> 0.019207421 | K11: ='BALANCE SHEET '!K16/'BALANCE SHEET '!$K$23 -> 0.046859786
A12: Total Current Assets | B12: ='BALANCE SHEET '!B17/'BALANCE SHEET '!$B$23 -> 0.79336273 | C12: ='BALANCE SHEET '!C17/'BALANCE SHEET '!$C$23 -> 0.82130258 | D12: ='BALANCE SHEET '!D17/'BALANCE SHEET '!$D$23 -> 0.86739153 | E12: ='BALANCE SHEET '!E17/'BALANCE SHEET '!$E$23 -> 0.82332533 | F12: ='BALANCE SHEET '!F17/'BALANCE SHEET '!$F$23 -> 0.79423714 | G12: ='BALANCE SHEET '!G17/'BALANCE SHEET '!$G$23 -> 0.79064395 | H12: ='BALANCE SHEET '!H17/'BALANCE SHEET '!$H$23 -> 0.55763954 | I12: ='BALANCE SHEET '!I17/'BALANCE SHEET '!$I$23 -> 0.65243171 | J12: ='BALANCE SHEET '!J17/'BALANCE SHEET '!$J$23 -> 0.56026905 | K12: ='BALANCE SHEET '!K17/'BALANCE SHEET '!$K$23 -> 0.67467442
A13: Gross Property Plant & Equip | B13: ='BALANCE SHEET '!B18/'BALANCE SHEET '!$B$23 -> 0.16375458 | C13: ='BALANCE SHEET '!C18/'BALANCE SHEET '!$C$23 -> 0.14925373 | D13: ='BALANCE SHEET '!D18/'BALANCE SHEET '!$D$23 -> 0.12102429 | E13: ='BALANCE SHEET '!E18/'BALANCE SHEET '!$E$23 -> 0.15452362 | F13: ='BALANCE SHEET '!F18/'BALANCE SHEET '!$F$23 -> 0.16333133 | G13: ='BALANCE SHEET '!G18/'BALANCE SHEET '!$G$23 -> 0.15506786 | H13: ='BALANCE SHEET '!H18/'BALANCE SHEET '!$H$23 -> 0.12354555 | I13: ='BALANCE SHEET '!I18/'BALANCE SHEET '!$I$23 -> 0.10593614 | J13: ='BALANCE SHEET '!J18/'BALANCE SHEET '!$J$23 -> 0.15786023 | K13: ='BALANCE SHEET '!K18/'BALANCE SHEET '!$K$23 -> 0.11293513
A14: Accumulated Depreciation | B14: ='BALANCE SHEET '!B19/'BALANCE SHEET '!$B$23 -> 0.086369007 | C14: ='BALANCE SHEET '!C19/'BALANCE SHEET '!$C$23 -> 0.086024423 | D14: ='BALANCE SHEET '!D19/'BALANCE SHEET '!$D$23 -> 0.068082512 | E14: ='BALANCE SHEET '!E19/'BALANCE SHEET '!$E$23 -> 0.065830442 | F14: ='BALANCE SHEET '!F19/'BALANCE SHEET '!$F$23 -> 0.057703882 | G14: ='BALANCE SHEET '!G19/'BALANCE SHEET '!$G$23 -> 0.05838868 | H14: ='BALANCE SHEET '!H19/'BALANCE SHEET '!$H$23 -> 0.048904171 | I14: ='BALANCE SHEET '!I19/'BALANCE SHEET '!$I$23 -> 0.043066965 | J14: ='BALANCE SHEET '!J19/'BALANCE SHEET '!$J$23 -> 0.06541693 | K14: ='BALANCE SHEET '!K19/'BALANCE SHEET '!$K$23 -> 0.053386685
A15: Net Property Plant & Equip | B15: ='BALANCE SHEET '!B20/'BALANCE SHEET '!$B$23 -> 0.077385575 | C15: ='BALANCE SHEET '!C20/'BALANCE SHEET '!$C$23 -> 0.063229308 | D15: ='BALANCE SHEET '!D20/'BALANCE SHEET '!$D$23 -> 0.052941774 | E15: ='BALANCE SHEET '!E20/'BALANCE SHEET '!$E$23 -> 0.088693177 | F15: ='BALANCE SHEET '!F20/'BALANCE SHEET '!$F$23 -> 0.10562745 | G15: ='BALANCE SHEET '!G20/'BALANCE SHEET '!$G$23 -> 0.09667918 | H15: ='BALANCE SHEET '!H20/'BALANCE SHEET '!$H$23 -> 0.074641381 | I15: ='BALANCE SHEET '!I20/'BALANCE SHEET '!$I$23 -> 0.06286917 | J15: ='BALANCE SHEET '!J20/'BALANCE SHEET '!$J$23 -> 0.0924433 | K15: ='BALANCE SHEET '!K20/'BALANCE SHEET '!$K$23 -> 0.059548442
A16: Intangible Assets | B16: ='BALANCE SHEET '!B21/'BALANCE SHEET '!$B$23 -> 0.11662965 | C16: ='BALANCE SHEET '!C21/'BALANCE SHEET '!$C$23 -> 0.1063772 | D16: ='BALANCE SHEET '!D21/'BALANCE SHEET '!$D$23 -> 0.073366528 | E16: ='BALANCE SHEET '!E21/'BALANCE SHEET '!$E$23 -> 0.059603238 | F16: ='BALANCE SHEET '!F21/'BALANCE SHEET '!$F$23 -> 0.049879627 | G16: ='BALANCE SHEET '!G21/'BALANCE SHEET '!$G$23 -> 0.038521513 | H16: ='BALANCE SHEET '!H21/'BALANCE SHEET '!$H$23 -> 0.24070022 | I16: ='BALANCE SHEET '!I21/'BALANCE SHEET '!$I$23 -> 0.15135673 | J16: ='BALANCE SHEET '!J21/'BALANCE SHEET '!$J$23 -> 0.14686028 | K16: ='BALANCE SHEET '!K21/'BALANCE SHEET '!$K$23 -> 0.084317186
A17: Other Assets | B17: ='BALANCE SHEET '!B22/'BALANCE SHEET '!$B$23 -> 0.012622046 | C17: ='BALANCE SHEET '!C22/'BALANCE SHEET '!$C$23 -> 0.0090909091 | D17: ='BALANCE SHEET '!D22/'BALANCE SHEET '!$D$23 -> 0.0063001727 | E17: ='BALANCE SHEET '!E22/'BALANCE SHEET '!$E$23 -> 0.028378258 | F17: ='BALANCE SHEET '!F22/'BALANCE SHEET '!$F$23 -> 0.050255793 | G17: ='BALANCE SHEET '!G22/'BALANCE SHEET '!$G$23 -> 0.042506497 | H17: ='BALANCE SHEET '!H22/'BALANCE SHEET '!$H$23 -> 0.099024001 | I17: ='BALANCE SHEET '!I22/'BALANCE SHEET '!$I$23 -> 0.050874692 | J17: ='BALANCE SHEET '!J22/'BALANCE SHEET '!$J$23 -> 0.028726142 | K17: ='BALANCE SHEET '!K22/'BALANCE SHEET '!$K$23 -> 0.088942308
... A35: Total Liabilities & Equity | B35: ='BALANCE SHEET '!B40/'BALANCE SHEET '!$B$23 -> 1 | C35: ='BALANCE SHEET '!C40/'BALANCE SHEET '!$C$23 -> 1 | D35: ='BALANCE SHEET '!D40/'BALANCE SHEET '!$D$23 -> 1 | E35: ='BALANCE SHEET '!E40/'BALANCE SHEET '!$E$23 -> 1 | F35: ='BALANCE SHEET '!F40/'BALANCE SHEET '!$F$23 -> 1 | G35: ='BALANCE SHEET '!G40/'BALANCE SHEET '!$G$23 -> 1 | H35: ='BALANCE SHEET '!H40/'BALANCE SHEET '!$H$23 -> 1 | I35: ='BALANCE SHEET '!I40/'BALANCE SHEET '!$I$23 -> 1 | J35: ='BALANCE SHEET '!J40/'BALANCE SHEET '!$J$23 -> 1 | K35: ='BALANCE SHEET '!K40/'BALANCE SHEET '!$K$23 -> 1

Sheet INCOME STATEMENT
A4: Powered by Clearbit
A5: NVIDIA Corp (NMS: NVDA)
A6: year | B6: 2015 | C6: 2016 | D6: 2017 | E6: 2018 | F6: 2019 | G6: 2020 | H6: 2021 | I6: 2022 | J6: 2023 | K6: 2024
A7: Report Date | B7: 01/25/2015 | C7: 01/31/2016 | D7: 01/29/2017 | E7: 01/28/2018 | F7: 01/27/2019 | G7: 01/26/2020 | H7: 01/31/2021 | I7: 01/30/2022 | J7: 01/29/2023 | K7: 01/28/2024
A8: Currency | B8: USD | C8: USD | D8: USD | E8: USD | F8: USD | G8: USD | H8: USD | I8: USD | J8: USD | K8: USD
A11: Audit Status | B11: Not Qualified | C11: Not Qualified | D11: Not Qualified | E11: Not Qualified | F11: Not Qualified | G11: Not Qualified | H11: Not Qualified | I11: Not Qualified | J11: Not Qualified | K11: Not Qualified | L11: average growth | M11: ST.d
A12: Standardized Annual Income Statement | C12: =(C17-B17)/B17 -> 0.070168217 | D12: =(D17-C17)/C17 -> 0.37924152 | E12: =(E17-D17)/D17 -> 0.40578871 | F12: =(F17-E17)/E17 -> 0.2060943 | G12: =(G17-F17)/F17 -> -0.068111984 | H12: =(H17-G17)/G17 -> 0.52729438 | I12: =(I17-H17)/H17 -> 0.61403298 | J12: =(J17-I17)/I17 -> 0.002229323 | K12: =(K17-J17)/J17 -> 1.2585453 | L12: =AVERAGE(C12:K12) -> 0.37725363 | M12: =_xlfn.STDEV.S(C12:K12) -> 0.40599578
A14: Consolidated | B14: Yes | C14: Yes | D14: Yes | E14: Yes | F14: Yes | G14: Yes | H14: Yes | I14: Yes | J14: Yes | K14: Yes
A15: Scale | B15: Thousands | C15: Thousands | D15: Thousands | E15: Thousands | F15: Thousands | G15: Thousands | H15: Thousands | I15: Thousands | J15: Thousands | K15: Thousands
A16: Sales Revenue | B16: - | C16: - | D16: - | E16: - | F16: - | G16: - | H16: - | I16: - | J16: - | K16: 60922000
A17: Total Revenue | B17: 4681507 | C17: 5010000 | D17: 6910000 | E17: 9714000 | F17: 11716000 | G17: 10918000 | H17: 16675000 | I17: 26914000 | J17: 26974000 | K17: 60922000
A18: Direct Costs | B18: 2082030 | C18: 2199000 | D18: 2847000 | E18: 3892000 | F18: 4545000 | G18: 4150000 | H18: 6279000 | I18: 9439000 | J18: 11618000 | K18: 16621000
A19: Gross Profit | B19: 2599477 | C19: 2811000 | D19: 4063000 | E19: 5822000 | F19: 7171000 | G19: 6768000 | H19: 10396000 | I19: 17475000 | J19: 15356000 | K19: 44301000
A20: Selling General & Admin | B20: 480763 | C20: 602000 | D20: 663000 | E20: 815000 | F20: 991000 | G20: 1093000 | H20: 1940000 | I20: 2166000 | J20: 2440000 | K20: 2654000
A21: Research & Development | B21: 1359725 | C21: 1331000 | D21: 1463000 | E21: 1797000 | F21: 2376000 | G21: 2829000 | H21: 3924000 | I21: 5268000 | J21: 7339000 | K21: 8675000
A22: Total Indirect Operating Costs | B22: 1840488 | C22: 2064000 | D22: 2129000 | E22: 2612000 | F22: 3367000 | G22: 3922000 | H22: 5864000 | I22: 7434000 | J22: 11132000 | K22: 11329000
A23: Operating Income(EBIT) | B23: 758989 | C23: 747000 | D23: 1934000 | E23: 3210000 | F23: 3804000 | G23: 2846000 | H23: 4532000 | I23: 10041000 | J23: 4224000 | K23: 32972000
A24: Interest Income | B24: -18043 | C24: -8000 | D24: -4000 | E24: 8000 | F24: 78000 | G24: 126000 | H24: -127000 | I24: -207000 | J24: 5000 | K24: 609000
A25: Other Non-Operating Income | B25: 13890 | C25: 4000 | D25: -25000 | E25: -22000 | F25: 14000 | G25: -2000 | H25: 4000 | I25: 107000 | J25: -48000 | K25: 237000
A26: Total Non-Operating Income | B26: -4153 | C26: -4000 | D26: -29000 | E26: -14000 | F26: 92000 | G26: 124000 | H26: -123000 | I26: -100000 | J26: -43000 | K26: 846000
A27: Earnings Before Tax(EBT) | B27: 754836 | C27: 743000 | D27: 1905000 | E27: 3196000 | F27: 3896000 | G27: 2970000 | H27: 4409000 | I27: 9941000 | J27: 4181000 | K27: 33818000
A28: Taxation | B28: 124249 | C28: 129000 | D28: 239000 | E28: 149000 | F28: -245000 | G28: 174000 | H28: 77000 | I28: 189000 | J28: -187000 | K28: 4058000
... A39: avg stock price | B39: 0.575 | C39: 1.3218 | D39: 3.7025 | E39: 5.7588 | F39: 4.3386 | G39: 9.8599 | H39: 19.4838 | I39: 18.5445 | J39: 36.5525 | K39: 107.8096
A40: Market capitilization | B40: =B39*B37 -> 12532999 | C40: =C39*C37 -> 28498008 | D40: =D39*D37 -> 86638500 | E40: =E39*E37 -> 139593312 | F40: =F39*F37 -> 1.0516766e+08 | G40: =G39*G37 -> 241370352 | H40: =H39*H37 -> 4.8319824e+08 | I40: =I39*I37 -> 464725170 | ... K40: =K39*K37 -> 2656428544
A41: Cash Flow
A43: operating cash flow | B43: =B23+('BALANCE SHEET '!B19-'BALANCE SHEET '!A19)-'INCOME STATEMENT'!B28 -> #VALUE! | C43: =C23+('BALANCE SHEET '!C19-'BALANCE SHEET '!B19)-'INCOME STATEMENT'!C28 -> 630025 | D43: =D23+('BALANCE SHEET '!D19-'BALANCE SHEET '!C19)-'INCOME STATEMENT'!D28 -> 1731000 | E43: =E23+('BALANCE SHEET '!E19-'BALANCE SHEET '!D19)-'INCOME STATEMENT'!E28 -> 3131000 | F43: =F23+('BALANCE SHEET '!F19-'BALANCE SHEET '!E19)-'INCOME STATEMENT'!F28 -> 4076000 | G43: =G23+('BALANCE SHEET '!G19-'BALANCE SHEET '!F19)-'INCOME STATEMENT'!G28 -> 2916000 | H43: =H23+('BALANCE SHEET '!H19-'BALANCE SHEET '!G19)-'INCOME STATEMENT'!H28 -> 4852000 | I43: =I23+('BALANCE SHEET '!I19-'BALANCE SHEET '!H19)-'INCOME STATEMENT'!I28 -> 10347000 | ... K43: =K23+('BALANCE SHEET '!K19-'BALANCE SHEET '!J19)-'INCOME STATEMENT'!K28 -> 29729000
A44: change CAPEX | B44: ='BALANCE SHEET '!B18-'BALANCE SHEET '!A18 -> #VALUE! | C44: ='BALANCE SHEET '!C18-'BALANCE SHEET '!B18 -> -79257 | D44: ='BALANCE SHEET '!D18-'BALANCE SHEET '!C18 -> 91000 | E44: ='BALANCE SHEET '!E18-'BALANCE SHEET '!D18 -> 546000 | F44: ='BALANCE SHEET '!F18-'BALANCE SHEET '!E18 -> 434000 | G44: ='BALANCE SHEET '!G18-'BALANCE SHEET '!F18 -> 514000 | H44: ='BALANCE SHEET '!H18-'BALANCE SHEET '!G18 -> 872000 | I44: ='BALANCE SHEET '!I18-'BALANCE SHEET '!H18 -> 1124000 | ... K44: ='BALANCE SHEET '!K18-'BALANCE SHEET '!J18 -> 922000
A45: change NWC | B45: =('BALANCE SHEET '!B17-'BALANCE SHEET '!B29)-('BALANCE SHEET '!A17-'BALANCE SHEET '!A29) -> #VALUE! | C45: =('BALANCE SHEET '!C17-'BALANCE SHEET '!C29)-('BALANCE SHEET '!B17-'BALANCE SHEET '!B29) -> -1115267 | D45: =('BALANCE SHEET '!D17-'BALANCE SHEET '!D29)-('BALANCE SHEET '!C17-'BALANCE SHEET '!C29) -> 3046000 | E45: =('BALANCE SHEET '!E17-'BALANCE SHEET '!E29)-('BALANCE SHEET '!D17-'BALANCE SHEET '!D29) -> 1354000 | F45: =('BALANCE SHEET '!F17-'BALANCE SHEET '!F29)-('BALANCE SHEET '!E17-'BALANCE SHEET '!E29) -> 1126000 | G45: =('BALANCE SHEET '!G17-'BALANCE SHEET '!G29)-('BALANCE SHEET '!F17-'BALANCE SHEET '!F29) -> 2678000 | H45: =('BALANCE SHEET '!H17-'BALANCE SHEET '!H29)-('BALANCE SHEET '!G17-'BALANCE SHEET '!G29) -> 224000 | I45: =('BALANCE SHEET '!I17-'BALANCE SHEET '!I29)-('BALANCE SHEET '!H17-'BALANCE SHEET '!H29) -> 12364000 | ... K45: =('BALANCE SHEET '!K17-'BALANCE SHEET '!K29)-('BALANCE SHEET '!J17-'BALANCE SHEET '!J29) -> 17204000
A47: CFFA | B47: =B43-B44-B45 -> #VALUE! | C47: =C43-C44-C45 -> 1824549 | D47: =D43-D44-D45 -> -1406000 | E47: =E43-E44-E45 -> 1231000 | F47: =F43-F44-F45 -> 2516000 | G47: =G43-G44-G45 -> -276000 | H47: =H43-H44-H45 -> 3756000 | I47: =I43-I44-I45 -> -3141000 | ... K47: =K43-K44-K45 -> 11603000
A49: Growth | B49: 2015 | C49: 2016 | D49: 2017 | E49: 2018 | F49: 2019 | G49: 2020 | H49: 2021 | I49: 2022 | J49: 2023 | K49: 2024
A51: sales | M51: AVERAGE
A52: ULTI | C52: =(C17-B17)/B17 -> 0.070168217 | D52: =(D17-C17)/C17 -> 0.37924152 | E52: =(E17-D17)/D17 -> 0.40578871 | F52: =(F17-E17)/E17 -> 0.2060943 | G52: =(G17-F17)/F17 -> -0.068111984 | H52: =(H17-G17)/G17 -> 0.52729438 | I52: =(I17-H17)/H17 -> 0.61403298 | J52: =(J17-I17)/I17 -> 0.002229323 | K52: =(K17-J17)/J17 -> 1.2585453 | M52: =AVERAGE(C52:K52) -> 0.37725363
A53: Industry | C53: =(AMD!C100+INTEL!C101+QUALCOMM!C104)/3 -> -0.0062701687 | D53: =(AMD!D100+INTEL!D101+QUALCOMM!D104)/3 -> 0.031010396 | E53: =(AMD!E100+INTEL!E101+QUALCOMM!E104)/3 -> -0.13108 | F53: =(AMD!F100+INTEL!F101+QUALCOMM!F104)/3 -> -0.20805488 | G53: =(AMD!G100+INTEL!G101+QUALCOMM!G104)/3 -> -0.027432006 | H53: =(AMD!H100+INTEL!H101+QUALCOMM!H104)/3 -> -0.08533201 | I53: =(AMD!I100+INTEL!I101+QUALCOMM!I104)/3 -> -0.11063147 | J53: =(AMD!J100+INTEL!J101+QUALCOMM!J104)/3 -> -0.020959005 | K53: =(AMD!K100+INTEL!K101+QUALCOMM!K104)/3 -> 0.12834378 | M53: =AVERAGE(C53:K53) -> -0.047822818
B55: 0.575
A56: 2016 | B56: 1.3218
A57: 2017 | B57: 3.7025
A58: 2018 | B58: 5.7588
A59: 2019 | B59: 4.3386
A60: 2020 | B60: 9.8599
A61: 2021 | B61: 19.4838
A62: 2022 | B62: 18.5445
A63: 2023 | B63: 36.5525
A64: 2024 | B64: 107.8096

Sheet Income statement c
B2: 2015 | C2: 2016 | D2: 2017 | E2: 2018 | F2: 2019 | G2: 2020 | H2: 2021 | I2: 2022 | J2: 2023 | K2: 2024
A3: Report Date | B3: 01/25/2015 | C3: 01/31/2016 | D3: 01/29/2017 | E3: 01/28/2018 | F3: 01/27/2019 | G3: 01/26/2020 | H3: 01/31/2021 | I3: 01/30/2022 | J3: 01/29/2023 | K3: 01/28/2024
A4: Total Revenue | B4: ='INCOME STATEMENT'!B17/'INCOME STATEMENT'!B$17 -> 1 | C4: ='INCOME STATEMENT'!C17/'INCOME STATEMENT'!C$17 -> 1 | D4: ='INCOME STATEMENT'!D17/'INCOME STATEMENT'!D$17 -> 1 | E4: ='INCOME STATEMENT'!E17/'INCOME STATEMENT'!E$17 -> 1 | F4: ='INCOME STATEMENT'!F17/'INCOME STATEMENT'!F$17 -> 1 | G4: ='INCOME STATEMENT'!G17/'INCOME STATEMENT'!G$17 -> 1 | H4: ='INCOME STATEMENT'!H17/'INCOME STATEMENT'!H$17 -> 1 | I4: ='INCOME STATEMENT'!I17/'INCOME STATEMENT'!I$17 -> 1 | ... K4: ='INCOME STATEMENT'!K17/'INCOME STATEMENT'!K$17 -> 1
A5: Direct Costs | B5: ='INCOME STATEMENT'!B18/'INCOME STATEMENT'!B$17 -> 0.444735 | C5: ='INCOME STATEMENT'!C18/'INCOME STATEMENT'!C$17 -> 0.43892216 | D5: ='INCOME STATEMENT'!D18/'INCOME STATEMENT'!D$17 -> 0.41201158 | E5: ='INCOME STATEMENT'!E18/'INCOME STATEMENT'!E$17 -> 0.40065884 | F5: ='INCOME STATEMENT'!F18/'INCOME STATEMENT'!F$17 -> 0.38793103 | G5: ='INCOME STATEMENT'!G18/'INCOME STATEMENT'!G$17 -> 0.38010625 | H5: ='INCOME STATEMENT'!H18/'INCOME STATEMENT'!H$17 -> 0.37655172 | I5: ='INCOME STATEMENT'!I18/'INCOME STATEMENT'!I$17 -> 0.35070967 | ... K5: ='INCOME STATEMENT'!K18/'INCOME STATEMENT'!K$17 -> 0.27282427
A6: Gross Profit | B6: ='INCOME STATEMENT'!B19/'INCOME STATEMENT'!B$17 -> 0.555265 | C6: ='INCOME STATEMENT'!C19/'INCOME STATEMENT'!C$17 -> 0.56107784 | D6: ='INCOME STATEMENT'!D19/'INCOME STATEMENT'!D$17 -> 0.58798842 | E6: ='INCOME STATEMENT'!E19/'INCOME STATEMENT'!E$17 -> 0.59934116 | F6: ='INCOME STATEMENT'!F19/'INCOME STATEMENT'!F$17 -> 0.61206897 | G6: ='INCOME STATEMENT'!G19/'INCOME STATEMENT'!G$17 -> 0.61989375 | H6: ='INCOME STATEMENT'!H19/'INCOME STATEMENT'!H$17 -> 0.62344828 | I6: ='INCOME STATEMENT'!I19/'INCOME STATEMENT'!I$17 -> 0.64929033 | ... K6: ='INCOME STATEMENT'!K19/'INCOME STATEMENT'!K$17 -> 0.72717573
A7: Selling General & Admin | B7: ='INCOME STATEMENT'!B20/'INCOME STATEMENT'!B$17 -> 0.10269407 | C7: ='INCOME STATEMENT'!C20/'INCOME STATEMENT'!C$17 -> 0.12015968 | D7: ='INCOME STATEMENT'!D20/'INCOME STATEMENT'!D$17 -> 0.095947902 | E7: ='INCOME STATEMENT'!E20/'INCOME STATEMENT'!E$17 -> 0.083899526 | F7: ='INCOME STATEMENT'!F20/'INCOME STATEMENT'!F$17 -> 0.084585183 | G7: ='INCOME STATEMENT'!G20/'INCOME STATEMENT'!G$17 -> 0.10010991 | H7: ='INCOME STATEMENT'!H20/'INCOME STATEMENT'!H$17 -> 0.11634183 | I7: ='INCOME STATEMENT'!I20/'INCOME STATEMENT'!I$17 -> 0.080478561 | ... K7: ='INCOME STATEMENT'!K20/'INCOME STATEMENT'!K$17 -> 0.043563901
A8: Research & Development | B8: ='INCOME STATEMENT'!B21/'INCOME STATEMENT'!B$17 -> 0.290446 | C8: ='INCOME STATEMENT'!C21/'INCOME STATEMENT'!C$17 -> 0.26566866 | D8: ='INCOME STATEMENT'!D21/'INCOME STATEMENT'!D$17 -> 0.21172214 | E8: ='INCOME STATEMENT'!E21/'INCOME STATEMENT'!E$17 -> 0.18499074 | F8: ='INCOME STATEMENT'!F21/'INCOME STATEMENT'!F$17 -> 0.20279959 | G8: ='INCOME STATEMENT'!G21/'INCOME STATEMENT'!G$17 -> 0.25911339 | H8: ='INCOME STATEMENT'!H21/'INCOME STATEMENT'!H$17 -> 0.23532234 | I8: ='INCOME STATEMENT'!I21/'INCOME STATEMENT'!I$17 -> 0.19573456 | ... K8: ='INCOME STATEMENT'!K21/'INCOME STATEMENT'!K$17 -> 0.14239519
A9: Restruct Remediation & Impair | B9: ='INCOME STATEMENT'!#REF!/'INCOME STATEMENT'!B$17 -> #REF! | C9: ='INCOME STATEMENT'!#REF!/'INCOME STATEMENT'!C$17 -> #REF! | D9: ='INCOME STATEMENT'!#REF!/'INCOME STATEMENT'!D$17 -> #REF! | E9: ='INCOME STATEMENT'!#REF!/'INCOME STATEMENT'!E$17 -> #REF! | F9: ='INCOME STATEMENT'!#REF!/'INCOME STATEMENT'!F$17 -> #REF! | G9: ='INCOME STATEMENT'!#REF!/'INCOME STATEMENT'!G$17 -> #REF! | H9: ='INCOME STATEMENT'!#REF!/'INCOME STATEMENT'!H$17 -> #REF! | I9: ='INCOME STATEMENT'!#REF!/'INCOME STATEMENT'!I$17 -> #REF! | ... K9: ='INCOME STATEMENT'!#REF!/'INCOME STATEMENT'!K$17 -> #REF!
A10: Total Indirect Operating Costs | B10: ='INCOME STATEMENT'!B22/'INCOME STATEMENT'!B$17 -> 0.39314007 | C10: ='INCOME STATEMENT'!C22/'INCOME STATEMENT'!C$17 -> 0.41197605 | D10: ='INCOME STATEMENT'!D22/'INCOME STATEMENT'!D$17 -> 0.3081042 | E10: ='INCOME STATEMENT'!E22/'INCOME STATEMENT'!E$17 -> 0.26889026 | F10: ='INCOME STATEMENT'!F22/'INCOME STATEMENT'!F$17 -> 0.28738477 | G10: ='INCOME STATEMENT'!G22/'INCOME STATEMENT'!G$17 -> 0.3592233 | H10: ='INCOME STATEMENT'!H22/'INCOME STATEMENT'!H$17 -> 0.35166417 | I10: ='INCOME STATEMENT'!I22/'INCOME STATEMENT'!I$17 -> 0.27621312 | ... K10: ='INCOME STATEMENT'!K22/'INCOME STATEMENT'!K$17 -> 0.1859591
A11: Operating Income(EBIT) | B11: ='INCOME STATEMENT'!B23/'INCOME STATEMENT'!B$17 -> 0.16212493 | C11: ='INCOME STATEMENT'!C23/'INCOME STATEMENT'!C$17 -> 0.1491018 | D11: ='INCOME STATEMENT'!D23/'INCOME STATEMENT'!D$17 -> 0.27988423 | E11: ='INCOME STATEMENT'!E23/'INCOME STATEMENT'!E$17 -> 0.3304509 | F11: ='INCOME STATEMENT'!F23/'INCOME STATEMENT'!F$17 -> 0.32468419 | G11: ='INCOME STATEMENT'!G23/'INCOME STATEMENT'!G$17 -> 0.26067045 | H11: ='INCOME STATEMENT'!H23/'INCOME STATEMENT'!H$17 -> 0.27178411 | I11: ='INCOME STATEMENT'!I23/'INCOME STATEMENT'!I$17 -> 0.37307721 | ... K11: ='INCOME STATEMENT'!K23/'INCOME STATEMENT'!K$17 -> 0.54121664
A12: Interest Income | B12: ='INCOME STATEMENT'!B24/'INCOME STATEMENT'!B$17 -> -0.0038541008 | C12: ='INCOME STATEMENT'!C24/'INCOME STATEMENT'!C$17 -> -0.0015968064 | D12: ='INCOME STATEMENT'!D24/'INCOME STATEMENT'!D$17 -> -0.0005788712 | E12: ='INCOME STATEMENT'!E24/'INCOME STATEMENT'!E$17 -> 0.00082355363 | F12: ='INCOME STATEMENT'!F24/'INCOME STATEMENT'!F$17 -> 0.0066575623 | G12: ='INCOME STATEMENT'!G24/'INCOME STATEMENT'!G$17 -> 0.011540575 | H12: ='INCOME STATEMENT'!H24/'INCOME STATEMENT'!H$17 -> -0.0076161919 | I12: ='INCOME STATEMENT'!I24/'INCOME STATEMENT'!I$17 -> -0.0076911644 | ... K12: ='INCOME STATEMENT'!K24/'INCOME STATEMENT'!K$17 -> 0.0099963888
A13: Other Non-Operating Income | B13: ='INCOME STATEMENT'!B25/'INCOME STATEMENT'!B$17 -> 0.0029669933 | C13: ='INCOME STATEMENT'!C25/'INCOME STATEMENT'!C$17 -> 0.00079840319 | D13: ='INCOME STATEMENT'!D25/'INCOME STATEMENT'!D$17 -> -0.003617945 | E13: ='INCOME STATEMENT'!E25/'INCOME STATEMENT'!E$17 -> -0.0022647725 | F13: ='INCOME STATEMENT'!F25/'INCOME STATEMENT'!F$17 -> 0.0011949471 | G13: ='INCOME STATEMENT'!G25/'INCOME STATEMENT'!G$17 -> -0.00018318373 | H13: ='INCOME STATEMENT'!H25/'INCOME STATEMENT'!H$17 -> 0.00023988006 | I13: ='INCOME STATEMENT'!I25/'INCOME STATEMENT'!I$17 -> 0.0039756261 | ... K13: ='INCOME STATEMENT'!K25/'INCOME STATEMENT'!K$17 -> 0.0038902203
A14: Total Non-Operating Income | B14: ='INCOME STATEMENT'!B26/'INCOME STATEMENT'!B$17 -> -0.00088710751 | C14: ='INCOME STATEMENT'!C26/'INCOME STATEMENT'!C$17 -> -0.00079840319 | D14: ='INCOME STATEMENT'!D26/'INCOME STATEMENT'!D$17 -> -0.0041968162 | E14: ='INCOME STATEMENT'!E26/'INCOME STATEMENT'!E$17 -> -0.0014412189 | F14: ='INCOME STATEMENT'!F26/'INCOME STATEMENT'!F$17 -> 0.0078525094 | G14: ='INCOME STATEMENT'!G26/'INCOME STATEMENT'!G$17 -> 0.011357391 | H14: ='INCOME STATEMENT'!H26/'INCOME STATEMENT'!H$17 -> -0.0073763118 | I14: ='INCOME STATEMENT'!I26/'INCOME STATEMENT'!I$17 -> -0.0037155384 | ... K14: ='INCOME STATEMENT'!K26/'INCOME STATEMENT'!K$17 -> 0.013886609
A15: Earnings Before Tax(EBT) | B15: ='INCOME STATEMENT'!B27/'INCOME STATEMENT'!B$17 -> 0.16123782 | C15: ='INCOME STATEMENT'!C27/'INCOME STATEMENT'!C$17 -> 0.14830339 | D15: ='INCOME STATEMENT'!D27/'INCOME STATEMENT'!D$17 -> 0.27568741 | E15: ='INCOME STATEMENT'!E27/'INCOME STATEMENT'!E$17 -> 0.32900968 | F15: ='INCOME STATEMENT'!F27/'INCOME STATEMENT'!F$17 -> 0.3325367 | G15: ='INCOME STATEMENT'!G27/'INCOME STATEMENT'!G$17 -> 0.27202784 | H15: ='INCOME STATEMENT'!H27/'INCOME STATEMENT'!H$17 -> 0.2644078 | I15: ='INCOME STATEMENT'!I27/'INCOME STATEMENT'!I$17 -> 0.36936167 | ... K15: ='INCOME STATEMENT'!K27/'INCOME STATEMENT'!K$17 -> 0.55510325
A16: Taxation | B16: ='INCOME STATEMENT'!B28/'INCOME STATEMENT'!B17 -> 0.026540385 | C16: ='INCOME STATEMENT'!C28/'INCOME STATEMENT'!C17 -> 0.025748503 | D16: ='INCOME STATEMENT'!D28/'INCOME STATEMENT'!D17 -> 0.034587554 | E16: ='INCOME STATEMENT'!E28/'INCOME STATEMENT'!E17 -> 0.015338686 | F16: ='INCOME STATEMENT'!F28/'INCOME STATEMENT'!F17 -> -0.020911574 | G16: ='INCOME STATEMENT'!G28/'INCOME STATEMENT'!G17 -> 0.015936985 | H16: ='INCOME STATEMENT'!H28/'INCOME STATEMENT'!H17 -> 0.0046176912 | I16: ='INCOME STATEMENT'!I28/'INCOME STATEMENT'!I17 -> 0.0070223675 | ... K16: ='INCOME STATEMENT'!K28/'INCOME STATEMENT'!K17 -> 0.066609763
A17: Net Income | B17: ='INCOME STATEMENT'!B29/'INCOME STATEMENT'!B$17 -> 0.13469744 | C17: ='INCOME STATEMENT'!C29/'INCOME STATEMENT'!C$17 -> 0.12255489 | D17: ='INCOME STATEMENT'!D29/'INCOME STATEMENT'!D$17 -> 0.24109986 | E17: ='INCOME STATEMENT'!E29/'INCOME STATEMENT'!E$17 -> 0.31367099 | F17: ='INCOME STATEMENT'!F29/'INCOME STATEMENT'!F$17 -> 0.35344828 | G17: ='INCOME STATEMENT'!G29/'INCOME STATEMENT'!G$17 -> 0.25609086 | H17: ='INCOME STATEMENT'!H29/'INCOME STATEMENT'!H$17 -> 0.2597901 | I17: ='INCOME STATEMENT'!I29/'INCOME STATEMENT'!I$17 -> 0.3623393 | ... K17: ='INCOME STATEMENT'!K29/'INCOME STATEMENT'!K$17 -> 0.48849348

Sheet CASHFLOW STATEMENT
A4: Powered by Clearbit
A5: NVIDIA Corp (NMS: NVDA)
A6: Standardized Annual Cash Flows | B6: 2015 | C6: 2016 | D6: 2017 | E6: 2018 | F6: 2019 | G6: 2020 | H6: 2021 | I6: 2022 | J6: 2023 | K6: 2024
A7: Report Date | B7: 01/25/2015 | C7: 01/31/2016 | D7: 01/29/2017 | E7: 01/28/2018 | F7: 01/27/2019 | G7: 01/26/2020 | H7: 01/31/2021 | I7: 01/30/2022 | J7: 01/29/2023 | K7: 01/28/2024
A8: Currency | B8: USD | C8: USD | D8: USD | E8: USD | F8: USD | G8: USD | H8: USD | I8: USD | J8: USD | K8: USD
A9: Audit Status | B9: Not Qualified | C9: Not Qualified | D9: Not Qualified | E9: Not Qualified | F9: Not Qualified | G9: Not Qualified | H9: Not Qualified | I9: Not Qualified | J9: Not Qualified | K9: Not Qualified
A10: Consolidated | B10: Yes | C10: Yes | D10: Yes | E10: Yes | F10: Yes | G10: Yes | H10: Yes | I10: Yes | J10: Yes | K10: Yes
A11: Scale | B11: Thousands | C11: Thousands | D11: Thousands | E11: Thousands | F11: Thousands | G11: Thousands | H11: Thousands | I11: Thousands | J11: Thousands | K11: Thousands
A12: Net Income | B12: 630587 | C12: 614000 | D12: 1666000 | E12: 3047000 | F12: 4141000 | G12: 2796000 | H12: 4332000 | I12: 9752000 | J12: 4368000 | K12: 29760000
A13: Adjustments from Inc to Cash | B13: 477596 | C13: 612000 | D13: 685000 | E13: 270000 | F13: 459000 | G13: 1248000 | H13: 2193000 | I13: 2719000 | J13: 3480000 | K13: 2052000
A14: Change in Working Capital | B14: -202527 | C14: -51000 | D14: -679000 | E14: 185000 | F14: -857000 | G14: 717000 | H14: -703000 | I14: -3363000 | J14: -2207000 | K14: -3722000
A15: Cash Flow from Operations | B15: 905656 | C15: 1175000 | D15: 1672000 | E15: 3502000 | F15: 3743000 | G15: 4761000 | H15: 5822000 | I15: 9108000 | J15: 5641000 | K15: 28090000
A16: Purchase of Pty Plant & Equip | B16: -122381 | C16: -86000 | D16: -176000 | E16: -593000 | F16: -600000 | G16: -489000 | H16: -1128000 | I16: -976000 | J16: -1833000 | K16: -1069000
A17: Purchase of Investments | B17: -2861809 | C17: -3477000 | D17: -3134000 | E17: -36000 | F17: -11157000 | G17: -1461000 | H17: -19308000 | I17: -24787000 | J17: -11897000 | K17: -18211000
A18: Disposal of Investments | B18: 2236780 | C18: 3138000 | D18: 2515000 | E18: 1941000 | F18: 7660000 | G18: 8109000 | H18: 9319000 | I18: 16220000 | J18: 21231000 | K18: 9782000
A19: Change in Business Activities | B19: 0 | C19: 0 | D19: 0 | E19: 0 | F19: 0 | G19: 0 | H19: -8524000 | I19: -263000 | J19: -49000 | K19: -83000
A20: Other Investing Cash Flows | B20: 20362 | C20: 25000 | D20: 2000 | E20: -34000 | F20: 0 | G20: -14000 | H20: -34000 | I20: -24000 | J20: -77000 | K20: -985000
A21: Cash Flow from Investing | B21: -727048 | C21: -400000 | D21: -793000 | E21: 1278000 | F21: -4097000 | G21: 6145000 | H21: -19675000 | I21: -9830000 | J21: 7375000 | K21: -10566000
A22: Change in LT Debt | B22: -2917 | C22: -3000 | D22: 1315000 | E22: -812000 | F22: -16000 | G22: 0 | H22: 4968000 | I22: 3977000 | J22: 0 | K22: -1250000
A23: Change in Equity | B23: -813600 | C23: -587000 | D23: -739000 | E23: -909000 | F23: -1442000 | G23: 149000 | H23: 194000 | I23: 281000 | J23: -9684000 | K23: -9130000
... A31: Net Purch of Pty Plant & Equip | B31: -122381 | C31: -86000 | D31: -176000 | E31: -593000 | F31: -600000 | G31: -489000 | H31: -1128000 | I31: -976000 | J31: -1833000 | K31: -1069000

Sheet FINANCIAL RATIOS
A1: Report Date | B1: 2015 | C1: 2016 | D1: 2017 | E1: 2018 | F1: 2019 | G1: 2020 | H1: 2021 | I1: 2022 | J1: 2023 | K1: 2024
A2: Revenue Growth | B2: ='INCOME STATEMENT'!B17/'INCOME STATEMENT'!B17 -> 1 | C2: =('INCOME STATEMENT'!C17-'INCOME STATEMENT'!B17)/'INCOME STATEMENT'!B17 -> 0.070168217 | D2: =('INCOME STATEMENT'!D17-'INCOME STATEMENT'!C17)/'INCOME STATEMENT'!C17 -> 0.37924152 | E2: =('INCOME STATEMENT'!E17-'INCOME STATEMENT'!D17)/'INCOME STATEMENT'!D17 -> 0.40578871 | F2: =('INCOME STATEMENT'!F17-'INCOME STATEMENT'!E17)/'INCOME STATEMENT'!E17 -> 0.2060943 | G2: =('INCOME STATEMENT'!G17-'INCOME STATEMENT'!F17)/'INCOME STATEMENT'!F17 -> -0.068111984 | H2: =('INCOME STATEMENT'!H17-'INCOME STATEMENT'!G17)/'INCOME STATEMENT'!G17 -> 0.52729438 | I2: =('INCOME STATEMENT'!I17-'INCOME STATEMENT'!H17)/'INCOME STATEMENT'!H17 -> 0.61403298 | J2: =('INCOME STATEMENT'!J17-'INCOME STATEMENT'!I17)/'INCOME STATEMENT'!I17 -> 0.002229323 | K2: =('INCOME STATEMENT'!K17-'INCOME STATEMENT'!J17)/'INCOME STATEMENT'!J17 -> 1.2585453
A3: Net Profit Margin | B3: ='INCOME STATEMENT'!B29/'INCOME STATEMENT'!B17 -> 0.13469744 | C3: ='INCOME STATEMENT'!C29/'INCOME STATEMENT'!C17 -> 0.12255489 | D3: ='INCOME STATEMENT'!D29/'INCOME STATEMENT'!D17 -> 0.24109986 | E3: ='INCOME STATEMENT'!E29/'INCOME STATEMENT'!E17 -> 0.31367099 | F3: ='INCOME STATEMENT'!F29/'INCOME STATEMENT'!F17 -> 0.35344828 | G3: ='INCOME STATEMENT'!G29/'INCOME STATEMENT'!G17 -> 0.25609086 | H3: ='INCOME STATEMENT'!H29/'INCOME STATEMENT'!H17 -> 0.2597901 | I3: ='INCOME STATEMENT'!I29/'INCOME STATEMENT'!I17 -> 0.3623393 | ... K3: ='INCOME STATEMENT'!K29/'INCOME STATEMENT'!K17 -> 0.48849348
A4: Gross Profit Margin | B4: ='INCOME STATEMENT'!B19/'INCOME STATEMENT'!B17 -> 0.555265 | C4: ='INCOME STATEMENT'!C19/'INCOME STATEMENT'!C17 -> 0.56107784 | D4: ='INCOME STATEMENT'!D19/'INCOME STATEMENT'!D17 -> 0.58798842 | E4: ='INCOME STATEMENT'!E19/'INCOME STATEMENT'!E17 -> 0.59934116 | F4: ='INCOME STATEMENT'!F19/'INCOME STATEMENT'!F17 -> 0.61206897 | G4: ='INCOME STATEMENT'!G19/'INCOME STATEMENT'!G17 -> 0.61989375 | H4: ='INCOME STATEMENT'!H19/'INCOME STATEMENT'!H17 -> 0.62344828 | I4: ='INCOME STATEMENT'!I19/'INCOME STATEMENT'!I17 -> 0.64929033 | ... K4: ='INCOME STATEMENT'!K19/'INCOME STATEMENT'!K17 -> 0.72717573
A5: Operating Income | B5: ='INCOME STATEMENT'!B23/'INCOME STATEMENT'!B17 -> 0.16212493 | C5: ='INCOME STATEMENT'!C23/'INCOME STATEMENT'!C17 -> 0.1491018 | D5: ='INCOME STATEMENT'!D23/'INCOME STATEMENT'!D17 -> 0.27988423 | E5: ='INCOME STATEMENT'!E23/'INCOME STATEMENT'!E17 -> 0.3304509 | F5: ='INCOME STATEMENT'!F23/'INCOME STATEMENT'!F17 -> 0.32468419 | G5: ='INCOME STATEMENT'!G23/'INCOME STATEMENT'!G17 -> 0.26067045 | H5: ='INCOME STATEMENT'!H23/'INCOME STATEMENT'!H17 -> 0.27178411 | I5: ='INCOME STATEMENT'!I23/'INCOME STATEMENT'!I17 -> 0.37307721 | ... K5: ='INCOME STATEMENT'!K23/'INCOME STATEMENT'!K17 -> 0.54121664
A6: Return On Assets | B6: ='INCOME STATEMENT'!B29/'BALANCE SHEET '!B23 -> 0.08756489 | C6: ='INCOME STATEMENT'!C29/'BALANCE SHEET '!C23 -> 0.083310719 | D6: ='INCOME STATEMENT'!D29/'BALANCE SHEET '!D23 -> 0.16929174 | E6: ='INCOME STATEMENT'!E29/'BALANCE SHEET '!E23 -> 0.27106129 | F6: ='INCOME STATEMENT'!F29/'BALANCE SHEET '!F23 -> 0.31154078 | G6: ='INCOME STATEMENT'!G29/'BALANCE SHEET '!G23 -> 0.16147849 | H6: ='INCOME STATEMENT'!H29/'BALANCE SHEET '!H23 -> 0.15046369 | I6: ='INCOME STATEMENT'!I29/'BALANCE SHEET '!I23 -> 0.2206984 | ... K6: ='INCOME STATEMENT'!K29/'BALANCE SHEET '!K23 -> 0.45277507
A7: Return on equity | B7: ='INCOME STATEMENT'!B29/'BALANCE SHEET '!B39 -> 0.14273191 | C7: ='INCOME STATEMENT'!C29/'BALANCE SHEET '!C39 -> 0.13476734 | D7: ='INCOME STATEMENT'!D29/'BALANCE SHEET '!D39 -> 0.28758847 | E7: ='INCOME STATEMENT'!E29/'BALANCE SHEET '!E39 -> 0.40784366 | F7: ='INCOME STATEMENT'!F29/'BALANCE SHEET '!F39 -> 0.44326697 | G7: ='INCOME STATEMENT'!G29/'BALANCE SHEET '!G39 -> 0.22910521 | H7: ='INCOME STATEMENT'!H29/'BALANCE SHEET '!H39 -> 0.25643758 | I7: ='INCOME STATEMENT'!I29/'BALANCE SHEET '!I39 -> 0.36645123 | ... K7: ='INCOME STATEMENT'!K29/'BALANCE SHEET '!K39 -> 0.6924473
A8: Liquidity Ratio
A9: Current Ratio | B9: ='BALANCE SHEET '!B17/'BALANCE SHEET '!B29 -> 6.3762341 | C9: ='BALANCE SHEET '!C17/'BALANCE SHEET '!C29 -> 2.5746491 | D9: ='BALANCE SHEET '!D17/'BALANCE SHEET '!D29 -> 4.7740492 | E9: ='BALANCE SHEET '!E17/'BALANCE SHEET '!E29 -> 8.0268864 | F9: ='BALANCE SHEET '!F17/'BALANCE SHEET '!F29 -> 7.9435666 | G9: ='BALANCE SHEET '!G17/'BALANCE SHEET '!G29 -> 7.6737668 | H9: ='BALANCE SHEET '!H17/'BALANCE SHEET '!H29 -> 4.0904459 | I9: ='BALANCE SHEET '!I17/'BALANCE SHEET '!I29 -> 6.6502884 | ... K9: ='BALANCE SHEET '!K17/'BALANCE SHEET '!K29 -> 4.1712915
A10: Quick Ratios | B10: =('BALANCE SHEET '!B11+'BALANCE SHEET '!B12+'BALANCE SHEET '!B14)/'BALANCE SHEET '!B29 -> 5.6883988 | C10: =('BALANCE SHEET '!C11+'BALANCE SHEET '!C12+'BALANCE SHEET '!C14)/'BALANCE SHEET '!C29 -> 2.3572948 | D10: =('BALANCE SHEET '!D11+'BALANCE SHEET '!D12+'BALANCE SHEET '!D14)/'BALANCE SHEET '!D29 -> 4.2639821 | E10: =('BALANCE SHEET '!E11+'BALANCE SHEET '!E12+'BALANCE SHEET '!E14)/'BALANCE SHEET '!E29 -> 7.2619254 | F10: =('BALANCE SHEET '!F11+'BALANCE SHEET '!F12+'BALANCE SHEET '!F14)/'BALANCE SHEET '!F29 -> 6.6561324 | G10: =('BALANCE SHEET '!G11+'BALANCE SHEET '!G12+'BALANCE SHEET '!G14)/'BALANCE SHEET '!G29 -> 7.0369955 | H10: =('BALANCE SHEET '!H11+'BALANCE SHEET '!H12+'BALANCE SHEET '!H14)/'BALANCE SHEET '!H29 -> 3.5643312 | I10: =('BALANCE SHEET '!I11+'BALANCE SHEET '!I12+'BALANCE SHEET '!I14)/'BALANCE SHEET '!I29 -> 5.9649366 | ... K10: =('BALANCE SHEET '!K11+'BALANCE SHEET '!K12+'BALANCE SHEET '!K14)/'BALANCE SHEET '!K29 -> 3.3847239
A11: Cash Ratio | B11: ='BALANCE SHEET '!B11/'BALANCE SHEET '!B33 -> 0.17843519 | C11: ='BALANCE SHEET '!C11/'BALANCE SHEET '!C33 -> 0.21179815 | D11: ='BALANCE SHEET '!D11/'BALANCE SHEET '!D33 -> 0.43626482 | E11: ='BALANCE SHEET '!E11/'BALANCE SHEET '!E33 -> 1.0615385 | F11: ='BALANCE SHEET '!F11/'BALANCE SHEET '!F33 -> 0.19797468 | G11: ='BALANCE SHEET '!G11/'BALANCE SHEET '!G33 -> 2.1318724 | H11: ='BALANCE SHEET '!H11/'BALANCE SHEET '!H33 -> 0.071188435 | I11: ='BALANCE SHEET '!I11/'BALANCE SHEET '!I33 -> 0.11322902 | ... K11: ='BALANCE SHEET '!K11/'BALANCE SHEET '!K33 -> 0.32
A12: Leverage Ratio
A13: Debt to Equity Ratio | B13: ='BALANCE SHEET '!B33/'BALANCE SHEET '!B39 -> 0.63001298 | C13: ='BALANCE SHEET '!C33/'BALANCE SHEET '!C39 -> 0.61764706 | D13: ='BALANCE SHEET '!D33/'BALANCE SHEET '!D39 -> 0.69877438 | E13: ='BALANCE SHEET '!E33/'BALANCE SHEET '!E39 -> 0.50461786 | F13: ='BALANCE SHEET '!F33/'BALANCE SHEET '!F39 -> 0.42282167 | G13: ='BALANCE SHEET '!G33/'BALANCE SHEET '!G39 -> 0.41879712 | H13: ='BALANCE SHEET '!H33/'BALANCE SHEET '!H39 -> 0.7043154 | I13: ='BALANCE SHEET '!I33/'BALANCE SHEET '!I39 -> 0.66041635 | ... K13: ='BALANCE SHEET '!K33/'BALANCE SHEET '!K39 -> 0.52934059
A14: Debt Ratio | B14: ='BALANCE SHEET '!B33/'BALANCE SHEET '!B23 -> 0.38650795 | C14: ='BALANCE SHEET '!C33/'BALANCE SHEET '!C23 -> 0.38181818 | D14: ='BALANCE SHEET '!D33/'BALANCE SHEET '!D23 -> 0.41134031 | E14: ='BALANCE SHEET '!E33/'BALANCE SHEET '!E23 -> 0.33537941 | F14: ='BALANCE SHEET '!F33/'BALANCE SHEET '!F23 -> 0.29717123 | G14: ='BALANCE SHEET '!G33/'BALANCE SHEET '!G23 -> 0.29517759 | H14: ='BALANCE SHEET '!H33/'BALANCE SHEET '!H23 -> 0.41325414 | I14: ='BALANCE SHEET '!I33/'BALANCE SHEET '!I23 -> 0.39774142 | ... K14: ='BALANCE SHEET '!K33/'BALANCE SHEET '!K23 -> 0.34612342
A17: Standardized Annual Income Statement | C17: ='INCOME STATEMENT'!C12 -> 0.070168217 | D17: ='INCOME STATEMENT'!D12 -> 0.37924152 | E17: ='INCOME STATEMENT'!E12 -> 0.40578871 | F17: ='INCOME STATEMENT'!F12 -> 0.2060943 | G17: ='INCOME STATEMENT'!G12 -> -0.068111984 | H17: ='INCOME STATEMENT'!H12 -> 0.52729438 | I17: ='INCOME STATEMENT'!I12 -> 0.61403298 | J17: ='INCOME STATEMENT'!J12 -> 0.002229323 | K17: ='INCOME STATEMENT'!K12 -> 1.2585453
A18: industry | C18: ='INCOME STATEMENT'!C53 -> -0.0062701687 | D18: ='INCOME STATEMENT'!D53 -> 0.031010396 | E18: ='INCOME STATEMENT'!E53 -> -0.13108 | F18: ='INCOME STATEMENT'!F53 -> -0.20805488 | G18: ='INCOME STATEMENT'!G53 -> -0.027432006 | H18: ='INCOME STATEMENT'!H53 -> -0.08533201 | I18: ='INCOME STATEMENT'!I53 -> -0.11063147 | J18: ='INCOME STATEMENT'!J53 -> -0.020959005 | K18: ='INCOME STATEMENT'!K53 -> 0.12834378
A19: Profitibility/return on investment
A20: EBIT/TA | B20: ='INCOME STATEMENT'!B23/'BALANCE SHEET '!B23 -> 0.10539511 | C20: ='INCOME STATEMENT'!C23/'BALANCE SHEET '!C23 -> 0.10135685 | D20: ='INCOME STATEMENT'!D23/'BALANCE SHEET '!D23 -> 0.19652474 | E20: ='INCOME STATEMENT'!E23/'BALANCE SHEET '!E23 -> 0.28556178 | F20: ='INCOME STATEMENT'!F23/'BALANCE SHEET '!F23 -> 0.28618718 | G20: ='INCOME STATEMENT'!G23/'BALANCE SHEET '!G23 -> 0.16436616 | H20: ='INCOME STATEMENT'!H23/'BALANCE SHEET '!H23 -> 0.1574103 | I20: ='INCOME STATEMENT'!I23/'BALANCE SHEET '!I23 -> 0.22723878 | ... K20: ='INCOME STATEMENT'!K23/'BALANCE SHEET '!K23 -> 0.50164314
A21: competitors | B21: =(AMD!B90+INTEL!B91+QUALCOMM!B94)/3 -> 0.043023434 | C21: =(AMD!C90+INTEL!C91+QUALCOMM!C94)/3 -> 0.057258474 | D21: =(AMD!D90+INTEL!D91+QUALCOMM!D94)/3 -> 0.21004713 | E21: =(AMD!E90+INTEL!E91+QUALCOMM!E94)/3 -> 0.16855101 | F21: =(AMD!F90+INTEL!F91+QUALCOMM!F94)/3 -> 0.1450254 | G21: =(AMD!G90+INTEL!G91+QUALCOMM!G94)/3 -> 0.16434233 | H21: =(AMD!H90+INTEL!H91+QUALCOMM!H94)/3 -> 0.087512296 | I21: =(AMD!I90+INTEL!I91+QUALCOMM!I94)/3 -> 0.024476337 | ... K21: =(AMD!K90+INTEL!K91+QUALCOMM!K94)/3 -> 0.069472984
A22: NI/TA | B22: ='INCOME STATEMENT'!B29/'BALANCE SHEET '!B23 -> 0.08756489 | C22: ='INCOME STATEMENT'!C29/'BALANCE SHEET '!C23 -> 0.083310719 | D22: ='INCOME STATEMENT'!D29/'BALANCE SHEET '!D23 -> 0.16929174 | E22: ='INCOME STATEMENT'!E29/'BALANCE SHEET '!E23 -> 0.27106129 | F22: ='INCOME STATEMENT'!F29/'BALANCE SHEET '!F23 -> 0.31154078 | G22: ='INCOME STATEMENT'!G29/'BALANCE SHEET '!G23 -> 0.16147849 | H22: ='INCOME STATEMENT'!H29/'BALANCE SHEET '!H23 -> 0.15046369 | I22: ='INCOME STATEMENT'!I29/'BALANCE SHEET '!I23 -> 0.2206984 | ... K22: ='INCOME STATEMENT'!K29/'BALANCE SHEET '!K23 -> 0.45277507
A23: competitors | B23: =(AMD!B91+INTEL!B92+QUALCOMM!B95)/3 -> 0.033669184 | C23: =(AMD!C91+INTEL!C92+QUALCOMM!C95)/3 -> 0.056680575 | D23: =(AMD!D91+INTEL!D92+QUALCOMM!D95)/3 -> 0.18751418 | E23: =(AMD!E91+INTEL!E92+QUALCOMM!E95)/3 -> 0.20503132 | F23: =(AMD!F91+INTEL!F92+QUALCOMM!F95)/3 -> 0.11303959 | G23: =(AMD!G91+INTEL!G92+QUALCOMM!G95)/3 -> 0.1204072 | H23: =(AMD!H91+INTEL!H92+QUALCOMM!H95)/3 -> 0.0092870416 | I23: =(AMD!I91+INTEL!I92+QUALCOMM!I95)/3 -> -0.011365868 | ... K23: =(AMD!K91+INTEL!K92+QUALCOMM!K95)/3 -> 0.035863397
A24: NI/TE | B24: ='INCOME STATEMENT'!B29/'BALANCE SHEET '!B23 -> 0.08756489 | C24: ='INCOME STATEMENT'!C29/'BALANCE SHEET '!C23 -> 0.083310719 | D24: ='INCOME STATEMENT'!D29/'BALANCE SHEET '!D23 -> 0.16929174 | E24: ='INCOME STATEMENT'!E29/'BALANCE SHEET '!E23 -> 0.27106129 | F24: ='INCOME STATEMENT'!F29/'BALANCE SHEET '!F23 -> 0.31154078 | G24: ='INCOME STATEMENT'!G29/'BALANCE SHEET '!G23 -> 0.16147849 | H24: ='INCOME STATEMENT'!H29/'BALANCE SHEET '!H23 -> 0.15046369 | I24: ='INCOME STATEMENT'!I29/'BALANCE SHEET '!I23 -> 0.2206984 | ... K24: ='INCOME STATEMENT'!K29/'BALANCE SHEET '!K23 -> 0.45277507
A25: competitors | B25: =(AMD!B92+INTEL!B93+QUALCOMM!B96)/3 -> 0.070783064 | C25: =(AMD!C92+INTEL!C93+QUALCOMM!C96)/3 -> 0.12507167 | D25: =(AMD!D92+INTEL!D93+QUALCOMM!D96)/3 -> 0.40631077 | E25: =(AMD!E92+INTEL!E93+QUALCOMM!E96)/3 -> 0.51457094 | F25: =(AMD!F92+INTEL!F93+QUALCOMM!F96)/3 -> 0.41129006 | G25: =(AMD!G92+INTEL!G93+QUALCOMM!G96)/3 -> 0.47689492 | H25: =(AMD!H92+INTEL!H93+QUALCOMM!H96)/3 -> -1.6300763 | I25: =(AMD!I92+INTEL!I93+QUALCOMM!I96)/3 -> -0.32570771 | ... K25: =(AMD!K92+INTEL!K93+QUALCOMM!K96)/3 -> -0.60102637
A26: Profit margin
A27: Gross Margin | B27: ='INCOME STATEMENT'!B19/'INCOME STATEMENT'!B17 -> 0.555265 | C27: ='INCOME STATEMENT'!C19/'INCOME STATEMENT'!C17 -> 0.56107784 | D27: ='INCOME STATEMENT'!D19/'INCOME STATEMENT'!D17 -> 0.58798842 | E27: ='INCOME STATEMENT'!E19/'INCOME STATEMENT'!E17 -> 0.59934116 | F27: ='INCOME STATEMENT'!F19/'INCOME STATEMENT'!F17 -> 0.61206897 | G27: ='INCOME STATEMENT'!G19/'INCOME STATEMENT'!G17 -> 0.61989375 | H27: ='INCOME STATEMENT'!H19/'INCOME STATEMENT'!H17 -> 0.62344828 | I27: ='INCOME STATEMENT'!I19/'INCOME STATEMENT'!I17 -> 0.64929033 | ... K27: ='INCOME STATEMENT'!K19/'INCOME STATEMENT'!K17 -> 0.72717573
A28: competitors | B28: =(AMD!B93+INTEL!B94+QUALCOMM!B97)/3 -> 0.44999281 | C28: =(AMD!C93+INTEL!C94+QUALCOMM!C97)/3 -> 0.46886836 | D28: =(AMD!D93+INTEL!D94+QUALCOMM!D97)/3 -> 0.49564942 | E28: =(AMD!E93+INTEL!E94+QUALCOMM!E97)/3 -> 0.52493669 | F28: =(AMD!F93+INTEL!F94+QUALCOMM!F97)/3 -> 0.53095351 | G28: =(AMD!G93+INTEL!G94+QUALCOMM!G97)/3 -> 0.53640518 | H28: =(AMD!H93+INTEL!H94+QUALCOMM!H97)/3 -> 0.50292796 | I28: =(AMD!I93+INTEL!I94+QUALCOMM!I97)/3 -> 0.47227941 | ... K28: =(AMD!K93+INTEL!K94+QUALCOMM!K97)/3 -> 0.51665899
A29: CGS/Revenue | B29: ='INCOME STATEMENT'!B18/'INCOME STATEMENT'!B17 -> 0.444735 | C29: ='INCOME STATEMENT'!C18/'INCOME STATEMENT'!C17 -> 0.43892216 | D29: ='INCOME STATEMENT'!D18/'INCOME STATEMENT'!D17 -> 0.41201158 | E29: ='INCOME STATEMENT'!E18/'INCOME STATEMENT'!E17 -> 0.40065884 | F29: ='INCOME STATEMENT'!F18/'INCOME STATEMENT'!F17 -> 0.38793103 | G29: ='INCOME STATEMENT'!G18/'INCOME STATEMENT'!G17 -> 0.38010625 | H29: ='INCOME STATEMENT'!H18/'INCOME STATEMENT'!H17 -> 0.37655172 | I29: ='INCOME STATEMENT'!I18/'INCOME STATEMENT'!I17 -> 0.35070967 | ... K29: ='INCOME STATEMENT'!K18/'INCOME STATEMENT'!K17 -> 0.27282427
A30: competitors | B30: =(AMD!B96+INTEL!B97+QUALCOMM!B100)/3 -> 0.55000719 | C30: =(AMD!C96+INTEL!C97+QUALCOMM!C100)/3 -> 0.53113164 | D30: =(AMD!D96+INTEL!D97+QUALCOMM!D100)/3 -> 0.50435058 | E30: =(AMD!E96+INTEL!E97+QUALCOMM!E100)/3 -> 0.47506331 | F30: =(AMD!F96+INTEL!F97+QUALCOMM!F100)/3 -> 0.46904649 | G30: =(AMD!G96+INTEL!G97+QUALCOMM!G100)/3 -> 0.46359482 | H30: =(AMD!H96+INTEL!H97+QUALCOMM!H100)/3 -> 0.49707204 | I30: =(AMD!I96+INTEL!I97+QUALCOMM!I100)/3 -> 0.52772059 | ... K30: =(AMD!K96+INTEL!K97+QUALCOMM!K100)/3 -> 0.48334101
A31: SGA/Revenue | B31: ='INCOME STATEMENT'!B20/'INCOME STATEMENT'!B17 -> 0.10269407 | C31: ='INCOME STATEMENT'!C20/'INCOME STATEMENT'!C17 -> 0.12015968 | D31: ='INCOME STATEMENT'!D20/'INCOME STATEMENT'!D17 -> 0.095947902 | E31: ='INCOME STATEMENT'!E20/'INCOME STATEMENT'!E17 -> 0.083899526 | F31: ='INCOME STATEMENT'!F20/'INCOME STATEMENT'!F17 -> 0.084585183 | G31: ='INCOME STATEMENT'!G20/'INCOME STATEMENT'!G17 -> 0.10010991 | H31: ='INCOME STATEMENT'!H20/'INCOME STATEMENT'!H17 -> 0.11634183 | I31: ='INCOME STATEMENT'!I20/'INCOME STATEMENT'!I17 -> 0.080478561 | ... K31: ='INCOME STATEMENT'!K20/'INCOME STATEMENT'!K17 -> 0.043563901
A32: competitors | B32: =(AMD!B97+INTEL!B98+QUALCOMM!B101)/3 -> 0.092741439 | C32: =(AMD!C97+INTEL!C98+QUALCOMM!C101)/3 -> 0.09073078 | D32: =(AMD!D97+INTEL!D98+QUALCOMM!D101)/3 -> 0.085767495 | E32: =(AMD!E97+INTEL!E98+QUALCOMM!E101)/3 -> 0.084798878 | F32: =(AMD!F97+INTEL!F98+QUALCOMM!F101)/3 -> 0.092976633 | G32: =(AMD!G97+INTEL!G98+QUALCOMM!G101)/3 -> 0.08756109 | H32: =(AMD!H97+INTEL!H98+QUALCOMM!H101)/3 -> 0.10750716 | I32: =(AMD!I97+INTEL!I98+QUALCOMM!I101)/3 -> 0.11533518 | ... K32: =(AMD!K97+INTEL!K98+QUALCOMM!K101)/3 -> 0.11522451
A33: R&D/Revenue | B33: ='INCOME STATEMENT'!B21/'INCOME STATEMENT'!B17 -> 0.290446 | C33: ='INCOME STATEMENT'!C21/'INCOME STATEMENT'!C17 -> 0.26566866 | D33: ='INCOME STATEMENT'!D21/'INCOME STATEMENT'!D17 -> 0.21172214 | E33: ='INCOME STATEMENT'!E21/'INCOME STATEMENT'!E17 -> 0.18499074 | F33: ='INCOME STATEMENT'!F21/'INCOME STATEMENT'!F17 -> 0.20279959 | G33: ='INCOME STATEMENT'!G21/'INCOME STATEMENT'!G17 -> 0.25911339 | H33: ='INCOME STATEMENT'!H21/'INCOME STATEMENT'!H17 -> 0.23532234 | I33: ='INCOME STATEMENT'!I21/'INCOME STATEMENT'!I17 -> 0.19573456 | ... K33: ='INCOME STATEMENT'!K21/'INCOME STATEMENT'!K17 -> 0.14239519
A34: competitors | B34: =(AMD!B94+INTEL!B95+QUALCOMM!B98)/3 -> 0.26624982 | C34: =(AMD!C94+INTEL!C95+QUALCOMM!C98)/3 -> 0.25138047 | D34: =(AMD!D94+INTEL!D95+QUALCOMM!D98)/3 -> 0.21216176 | E34: =(AMD!E94+INTEL!E95+QUALCOMM!E98)/3 -> 0.20304055 | F34: =(AMD!F94+INTEL!F95+QUALCOMM!F98)/3 -> 0.2192814 | G34: =(AMD!G94+INTEL!G95+QUALCOMM!G98)/3 -> 0.2098426 | H34: =(AMD!H94+INTEL!H95+QUALCOMM!H98)/3 -> 0.21876037 | I34: =(AMD!I94+INTEL!I95+QUALCOMM!I98)/3 -> 0.23023832 | ... K34: =(AMD!K94+INTEL!K95+QUALCOMM!K98)/3 -> 0.21031692
A35: Operating Costs/Sales | B35: =SUM('INCOME STATEMENT'!B20:B21)/'INCOME STATEMENT'!B17 -> 0.39314007 | C35: =SUM('INCOME STATEMENT'!C20:C21)/'INCOME STATEMENT'!C17 -> 0.38582834 | D35: =SUM('INCOME STATEMENT'!D20:D21)/'INCOME STATEMENT'!D17 -> 0.30767004 | E35: =SUM('INCOME STATEMENT'!E20:E21)/'INCOME STATEMENT'!E17 -> 0.26889026 | F35: =SUM('INCOME STATEMENT'!F20:F21)/'INCOME STATEMENT'!F17 -> 0.28738477 | G35: =SUM('INCOME STATEMENT'!G20:G21)/'INCOME STATEMENT'!G17 -> 0.3592233 | H35: =SUM('INCOME STATEMENT'!H20:H21)/'INCOME STATEMENT'!H17 -> 0.35166417 | I35: =SUM('INCOME STATEMENT'!I20:I21)/'INCOME STATEMENT'!I17 -> 0.27621312 | ... K35: =SUM('INCOME STATEMENT'!K20:K21)/'INCOME STATEMENT'!K17 -> 0.1859591
A36: Tax rate | B36: ='INCOME STATEMENT'!B28/'INCOME STATEMENT'!B27 -> 0.16460397 | C36: ='INCOME STATEMENT'!C28/'INCOME STATEMENT'!C27 -> 0.17362046 | D36: ='INCOME STATEMENT'!D28/'INCOME STATEMENT'!D27 -> 0.12545932 | E36: ='INCOME STATEMENT'!E28/'INCOME STATEMENT'!E27 -> 0.046620776 | F36: ='INCOME STATEMENT'!F28/'INCOME STATEMENT'!F27 -> -0.06288501 | G36: ='INCOME STATEMENT'!G28/'INCOME STATEMENT'!G27 -> 0.058585859 | H36: ='INCOME STATEMENT'!H28/'INCOME STATEMENT'!H27 -> 0.017464278 | I36: ='INCOME STATEMENT'!I28/'INCOME STATEMENT'!I27 -> 0.019012172 | ... K36: ='INCOME STATEMENT'!K28/'INCOME STATEMENT'!K27 -> 0.11999527
A37: Interest(on Avg Debt | B37: =('INCOME STATEMENT'!B26*-1)/AVERAGE('BALANCE SHEET '!B30:C30) -> 0.0058973551 | C37: =('INCOME STATEMENT'!C26*-1)/AVERAGE('BALANCE SHEET '!C30:D30) -> 0.004002001 | D37: =('INCOME STATEMENT'!D26*-1)/AVERAGE('BALANCE SHEET '!D30:E30) -> 0.014594867 | E37: =('INCOME STATEMENT'!E26*-1)/AVERAGE('BALANCE SHEET '!E30:F30) -> 0.0070475711 | F37: =('INCOME STATEMENT'!F26*-1)/AVERAGE('BALANCE SHEET '!F30:G30) -> -0.046242775 | G37: =('INCOME STATEMENT'!G26*-1)/AVERAGE('BALANCE SHEET '!G30:H30) -> -0.031175361 | H37: =('INCOME STATEMENT'!H26*-1)/AVERAGE('BALANCE SHEET '!H30:I30) -> 0.014547605 | I37: =('INCOME STATEMENT'!I26*-1)/AVERAGE('BALANCE SHEET '!I30:J30) -> 0.0096856991 | ... K37: =('INCOME STATEMENT'!K26*-1)/AVERAGE('BALANCE SHEET '!K30:L30) -> -0.10001182
A38: competitors | B38: =(AMD!B103+INTEL!B103+QUALCOMM!B106)/3 -> -0.021739315 | C38: =(AMD!C103+INTEL!C103+QUALCOMM!C106)/3 -> 0.025014656 | D38: =(AMD!D103+INTEL!D103+QUALCOMM!D106)/3 -> -0.072253864 | E38: =(AMD!E103+INTEL!E103+QUALCOMM!E106)/3 -> 0.043696217 | F38: =(AMD!F103+INTEL!F103+QUALCOMM!F106)/3 -> 0.10413051 | G38: =(AMD!G103+INTEL!G103+QUALCOMM!G106)/3 -> 0.0084702183 | H38: =(AMD!H103+INTEL!H103+QUALCOMM!H106)/3 -> 0.034206306 | I38: =(AMD!I103+INTEL!I103+QUALCOMM!I106)/3 -> -0.034908729 | ... K38: =(AMD!K103+INTEL!K103+QUALCOMM!K106)/3 -> 0.0098855579
A39: Net income/Revenue | B39: ='INCOME STATEMENT'!B29/'INCOME STATEMENT'!B17 -> 0.13469744 | C39: ='INCOME STATEMENT'!C29/'INCOME STATEMENT'!C17 -> 0.12255489 | D39: ='INCOME STATEMENT'!D29/'INCOME STATEMENT'!D17 -> 0.24109986 | E39: ='INCOME STATEMENT'!E29/'INCOME STATEMENT'!E17 -> 0.31367099 | F39: ='INCOME STATEMENT'!F29/'INCOME STATEMENT'!F17 -> 0.35344828 | G39: ='INCOME STATEMENT'!G29/'INCOME STATEMENT'!G17 -> 0.25609086 | H39: ='INCOME STATEMENT'!H29/'INCOME STATEMENT'!H17 -> 0.2597901 | I39: ='INCOME STATEMENT'!I29/'INCOME STATEMENT'!I17 -> 0.3623393 | ... K39: ='INCOME STATEMENT'!K29/'INCOME STATEMENT'!K17 -> 0.48849348
A40: AP, Acr Exp/Sales | B40: ='BALANCE SHEET '!B24/'INCOME STATEMENT'!B17 -> 0.12246377 | C40: ='BALANCE SHEET '!C24/'INCOME STATEMENT'!C17 -> 0.11716567 | D40: ='BALANCE SHEET '!D24/'INCOME STATEMENT'!D17 -> 0.12460203 | E40: ='BALANCE SHEET '!E24/'INCOME STATEMENT'!E17 -> 0.10376776 | F40: ='BALANCE SHEET '!F24/'INCOME STATEMENT'!F17 -> 0.089706384 | G40: ='BALANCE SHEET '!G24/'INCOME STATEMENT'!G17 -> 0.12218355 | H40: ='BALANCE SHEET '!H24/'INCOME STATEMENT'!H17 -> 0.12761619 | I40: ='BALANCE SHEET '!I24/'INCOME STATEMENT'!I17 -> 0.11859999 | ... K40: ='BALANCE SHEET '!K24/'INCOME STATEMENT'!K17 -> 0.12304258
A41: Depreciation/FA | B41: =('BALANCE SHEET '!B19-'BALANCE SHEET '!A19)/AVERAGE('BALANCE SHEET '!A18:B18) -> #VALUE! | C41: =('BALANCE SHEET '!C19-'BALANCE SHEET '!B19)/AVERAGE('BALANCE SHEET '!B18:C18) -> 0.010551684 | D41: =('BALANCE SHEET '!D19-'BALANCE SHEET '!C19)/AVERAGE('BALANCE SHEET '!C18:D18) -> 0.031427324 | E41: =('BALANCE SHEET '!E19-'BALANCE SHEET '!D19)/AVERAGE('BALANCE SHEET '!D18:E18) -> 0.047814208 | F41: =('BALANCE SHEET '!F19-'BALANCE SHEET '!E19)/AVERAGE('BALANCE SHEET '!E18:F18) -> 0.01381781 | G41: =('BALANCE SHEET '!G19-'BALANCE SHEET '!F19)/AVERAGE('BALANCE SHEET '!F18:G18) -> 0.10049423 | H41: =('BALANCE SHEET '!H19-'BALANCE SHEET '!G19)/AVERAGE('BALANCE SHEET '!G18:H18) -> 0.12720282 | I41: =('BALANCE SHEET '!I19-'BALANCE SHEET '!H19)/AVERAGE('BALANCE SHEET '!H18:I18) -> 0.1201748 | ... K41: =('BALANCE SHEET '!K19-'BALANCE SHEET '!J19)/AVERAGE('BALANCE SHEET '!J18:K18) -> 0.11706406
A42: FA/Sales | B42: ='BALANCE SHEET '!B18/'INCOME STATEMENT'!B17 -> 0.25189688 | C42: ='BALANCE SHEET '!C18/'INCOME STATEMENT'!C17 -> 0.21956088 | D42: ='BALANCE SHEET '!D18/'INCOME STATEMENT'!D17 -> 0.1723589 | E42: ='BALANCE SHEET '!E18/'INCOME STATEMENT'!E17 -> 0.17881408 | F42: ='BALANCE SHEET '!F18/'INCOME STATEMENT'!F17 -> 0.18530215 | G42: ='BALANCE SHEET '!G18/'INCOME STATEMENT'!G17 -> 0.24592416 | H42: ='BALANCE SHEET '!H18/'INCOME STATEMENT'!H17 -> 0.21331334 | I42: ='BALANCE SHEET '!I18/'INCOME STATEMENT'!I17 -> 0.17392435 | ... K42: ='BALANCE SHEET '!K18/'INCOME STATEMENT'!K17 -> 0.12184433
A43: Other Assets/Sales | B43: =SUM('BALANCE SHEET '!B21:B22)/'INCOME STATEMENT'!B17 -> 0.19882252 | C43: =SUM('BALANCE SHEET '!C21:C22)/'INCOME STATEMENT'!C17 -> 0.16986028 | D43: =SUM('BALANCE SHEET '!D21:D22)/'INCOME STATEMENT'!D17 -> 0.11345876 | E43: =SUM('BALANCE SHEET '!E21:E22)/'INCOME STATEMENT'!E17 -> 0.10181182 | F43: =SUM('BALANCE SHEET '!F21:F22)/'INCOME STATEMENT'!F17 -> 0.11360533 | G43: =SUM('BALANCE SHEET '!G21:G22)/'INCOME STATEMENT'!G17 -> 0.12850339 | H43: =SUM('BALANCE SHEET '!H21:H22)/'INCOME STATEMENT'!H17 -> 0.58656672 | I43: =SUM('BALANCE SHEET '!I21:I22)/'INCOME STATEMENT'!I17 -> 0.33202051 | ... K43: =SUM('BALANCE SHEET '!K21:K22)/'INCOME STATEMENT'!K17 -> 0.18692755
A44: Operating Efficiency
A45: CGS/Revenue | B45: =B29 -> 0.444735 | C45: =C29 -> 0.43892216 | D45: =D29 -> 0.41201158 | E45: =E29 -> 0.40065884 | F45: =F29 -> 0.38793103 | G45: =G29 -> 0.38010625 | H45: =H29 -> 0.37655172 | I45: =I29 -> 0.35070967 | ... K45: =K29 -> 0.27282427
A46: Revenue/TA | B46: ='INCOME STATEMENT'!B17/'BALANCE SHEET '!B23 -> 0.65008579 | C46: ='INCOME STATEMENT'!C17/'BALANCE SHEET '!C23 -> 0.6797829 | D46: ='INCOME STATEMENT'!D17/'BALANCE SHEET '!D23 -> 0.70216441 | E46: ='INCOME STATEMENT'!E17/'BALANCE SHEET '!E23 -> 0.86415799 | F46: ='INCOME STATEMENT'!F17/'BALANCE SHEET '!F23 -> 0.88143244 | G46: ='INCOME STATEMENT'!G17/'BALANCE SHEET '!G23 -> 0.63055154 | H46: ='INCOME STATEMENT'!H17/'BALANCE SHEET '!H23 -> 0.57917405 | I46: ='INCOME STATEMENT'!I17/'BALANCE SHEET '!I23 -> 0.60909317 | ... K46: ='INCOME STATEMENT'!K17/'BALANCE SHEET '!K23 -> 0.92688048
A47: Sales/AR | B47: ='INCOME STATEMENT'!B17/'BALANCE SHEET '!B14 -> 9.8841666 | C47: ='INCOME STATEMENT'!C17/'BALANCE SHEET '!C14 -> 9.9207921 | D47: ='INCOME STATEMENT'!D17/'BALANCE SHEET '!D14 -> 8.3656174 | E47: ='INCOME STATEMENT'!E17/'BALANCE SHEET '!E14 -> 7.6790514 | F47: ='INCOME STATEMENT'!F17/'BALANCE SHEET '!F14 -> 8.2275281 | G47: ='INCOME STATEMENT'!G17/'BALANCE SHEET '!G14 -> 6.5890163 | H47: ='INCOME STATEMENT'!H17/'BALANCE SHEET '!H14 -> 6.864965 | I47: ='INCOME STATEMENT'!I17/'BALANCE SHEET '!I14 -> 5.787957 | ... K47: ='INCOME STATEMENT'!K17/'BALANCE SHEET '!K14 -> 6.0928093
A48: Receivable/Days | B48: =360/B47 -> 36.421887 | C48: =360/C47 -> 36.287425 | D48: =360/D47 -> 43.033285 | E48: =360/E47 -> 46.880791 | F48: =360/F47 -> 43.755548 | G48: =360/G47 -> 54.63638 | H48: =360/H47 -> 52.44018 | I48: =360/I47 -> 62.198113 | ... K48: =360/K47 -> 59.086044
A49: Sales/Payable | B49: ='BALANCE SHEET '!B17/'BALANCE SHEET '!B24 -> 9.9653716 | C49: ='BALANCE SHEET '!C17/'BALANCE SHEET '!C24 -> 10.311755 | D49: ='BALANCE SHEET '!D17/'BALANCE SHEET '!D24 -> 9.9140534 | E49: ='BALANCE SHEET '!E17/'BALANCE SHEET '!E24 -> 9.1815476 | F49: ='BALANCE SHEET '!F17/'BALANCE SHEET '!F24 -> 10.044719 | G49: ='BALANCE SHEET '!G17/'BALANCE SHEET '!G24 -> 10.262369 | H49: ='BALANCE SHEET '!H17/'BALANCE SHEET '!H24 -> 7.5446429 | I49: ='BALANCE SHEET '!I17/'BALANCE SHEET '!I24 -> 9.0316416 | ... K49: ='BALANCE SHEET '!K17/'BALANCE SHEET '!K24 -> 5.9158218
A50: Payable/Days | B50: =306/B49 -> 30.706331 | C50: =306/C49 -> 29.674872 | D50: =306/D49 -> 30.865276 | E50: =306/E49 -> 33.327715 | F50: =306/F49 -> 30.463768 | G50: =306/G49 -> 29.817677 | H50: =306/H49 -> 40.55858 | I50: =306/I49 -> 33.880884 | ... K50: =306/K49 -> 51.725696
A51: Leverage
A52: TD/TA | B52: ='BALANCE SHEET '!B33/'BALANCE SHEET '!B23 -> 0.38650795 | C52: ='BALANCE SHEET '!C33/'BALANCE SHEET '!C23 -> 0.38181818 | D52: ='BALANCE SHEET '!D33/'BALANCE SHEET '!D23 -> 0.41134031 | E52: ='BALANCE SHEET '!E33/'BALANCE SHEET '!E23 -> 0.33537941 | F52: ='BALANCE SHEET '!F33/'BALANCE SHEET '!F23 -> 0.29717123 | G52: ='BALANCE SHEET '!G33/'BALANCE SHEET '!G23 -> 0.29517759 | H52: ='BALANCE SHEET '!H33/'BALANCE SHEET '!H23 -> 0.41325414 | I52: ='BALANCE SHEET '!I33/'BALANCE SHEET '!I23 -> 0.39774142 | ... K52: ='BALANCE SHEET '!K33/'BALANCE SHEET '!K23 -> 0.34612342
A53: Debt/Equity | B53: ='BALANCE SHEET '!B33/'BALANCE SHEET '!B39 -> 0.63001298 | C53: ='BALANCE SHEET '!C33/'BALANCE SHEET '!C39 -> 0.61764706 | D53: ='BALANCE SHEET '!D33/'BALANCE SHEET '!D39 -> 0.69877438 | E53: ='BALANCE SHEET '!E33/'BALANCE SHEET '!E39 -> 0.50461786 | F53: ='BALANCE SHEET '!F33/'BALANCE SHEET '!F39 -> 0.42282167 | G53: ='BALANCE SHEET '!G33/'BALANCE SHEET '!G39 -> 0.41879712 | H53: ='BALANCE SHEET '!H33/'BALANCE SHEET '!H39 -> 0.7043154 | I53: ='BALANCE SHEET '!I33/'BALANCE SHEET '!I39 -> 0.66041635 | ... K53: ='BALANCE SHEET '!K33/'BALANCE SHEET '!K39 -> 0.52934059
A54: TA/Equity | B54: ='BALANCE SHEET '!B23/'BALANCE SHEET '!B39 -> 1.630013 | C54: ='BALANCE SHEET '!C23/'BALANCE SHEET '!C39 -> 1.6176471 | D54: ='BALANCE SHEET '!D23/'BALANCE SHEET '!D39 -> 1.6987744 | E54: ='BALANCE SHEET '!E23/'BALANCE SHEET '!E39 -> 1.5046179 | F54: ='BALANCE SHEET '!F23/'BALANCE SHEET '!F39 -> 1.4228217 | G54: ='BALANCE SHEET '!G23/'BALANCE SHEET '!G39 -> 1.4187971 | H54: ='BALANCE SHEET '!H23/'BALANCE SHEET '!H39 -> 1.7043154 | I54: ='BALANCE SHEET '!I23/'BALANCE SHEET '!I39 -> 1.6604164 | ... K54: ='BALANCE SHEET '!K23/'BALANCE SHEET '!K39 -> 1.5293406
A55: EBIT/Interest | B55: ='INCOME STATEMENT'!B23/'INCOME STATEMENT'!B26 -> -182.7568 | C55: ='INCOME STATEMENT'!C23/'INCOME STATEMENT'!C26 -> -186.75 | D55: ='INCOME STATEMENT'!D23/'INCOME STATEMENT'!D26 -> -66.689655 | E55: ='INCOME STATEMENT'!E23/'INCOME STATEMENT'!E26 -> -229.28571 | F55: ='INCOME STATEMENT'!F23/'INCOME STATEMENT'!F26 -> 41.347826 | G55: ='INCOME STATEMENT'!G23/'INCOME STATEMENT'!G26 -> 22.951613 | H55: ='INCOME STATEMENT'!H23/'INCOME STATEMENT'!H26 -> -36.845528 | I55: ='INCOME STATEMENT'!I23/'INCOME STATEMENT'!I26 -> -100.41 | ... K55: ='INCOME STATEMENT'!K23/'INCOME STATEMENT'!K26 -> 38.973995
A56: Liquidity
A57: CA/CL | B57: ='BALANCE SHEET '!B17/'BALANCE SHEET '!B29 -> 6.3762341 | C57: ='BALANCE SHEET '!C17/'BALANCE SHEET '!C29 -> 2.5746491 | D57: ='BALANCE SHEET '!D17/'BALANCE SHEET '!D29 -> 4.7740492 | E57: ='BALANCE SHEET '!E17/'BALANCE SHEET '!E29 -> 8.0268864 | F57: ='BALANCE SHEET '!F17/'BALANCE SHEET '!F29 -> 7.9435666 | G57: ='BALANCE SHEET '!G17/'BALANCE SHEET '!G29 -> 7.6737668 | H57: ='BALANCE SHEET '!H17/'BALANCE SHEET '!H29 -> 4.0904459 | I57: ='BALANCE SHEET '!I17/'BALANCE SHEET '!I29 -> 6.6502884 | ... K57: ='BALANCE SHEET '!K17/'BALANCE SHEET '!K29 -> 4.1712915
A58: Cash + AR/CL | B58: =('BALANCE SHEET '!B11+'BALANCE SHEET '!B14)/'BALANCE SHEET '!B29 -> 1.0828778 | C58: =('BALANCE SHEET '!C11+'BALANCE SHEET '!C14)/'BALANCE SHEET '!C29 -> 0.46831136 | D58: =('BALANCE SHEET '!D11+'BALANCE SHEET '!D14)/'BALANCE SHEET '!D29 -> 1.4496644 | E58: =('BALANCE SHEET '!E11+'BALANCE SHEET '!E14)/'BALANCE SHEET '!E29 -> 4.5680833 | F58: =('BALANCE SHEET '!F11+'BALANCE SHEET '!F14)/'BALANCE SHEET '!F29 -> 1.6598947 | G58: =('BALANCE SHEET '!G11+'BALANCE SHEET '!G14)/'BALANCE SHEET '!G29 -> 7.036435 | H58: =('BALANCE SHEET '!H11+'BALANCE SHEET '!H14)/'BALANCE SHEET '!H29 -> 0.83464968 | I58: =('BALANCE SHEET '!I11+'BALANCE SHEET '!I14)/'BALANCE SHEET '!I29 -> 1.5317186 | ... K58: =('BALANCE SHEET '!K11+'BALANCE SHEET '!K14)/'BALANCE SHEET '!K29 -> 1.625341
A59: Cash/Revenue | B59: ='BALANCE SHEET '!B13/'INCOME STATEMENT'!B17 -> 0.98757494 | C59: ='BALANCE SHEET '!C13/'INCOME STATEMENT'!C17 -> 1.0053892 | D59: ='BALANCE SHEET '!D13/'INCOME STATEMENT'!D17 -> 0.98379161 | E59: ='BALANCE SHEET '!E13/'INCOME STATEMENT'!E17 -> 0.7317274 | F59: ='BALANCE SHEET '!F13/'INCOME STATEMENT'!F17 -> 0.63349266 | G59: ='BALANCE SHEET '!G13/'INCOME STATEMENT'!G17 -> 0.99807657 | H59: ='BALANCE SHEET '!H13/'INCOME STATEMENT'!H17 -> 0.69331334 | I59: ='BALANCE SHEET '!I13/'INCOME STATEMENT'!I17 -> 0.78799138 | ... K59: ='BALANCE SHEET '!K13/'INCOME STATEMENT'!K17 -> 0.42651259
A60: AR/Sales | B60: ='BALANCE SHEET '!B14/'INCOME STATEMENT'!B17 -> 0.10117191 | C60: ='BALANCE SHEET '!C14/'INCOME STATEMENT'!C17 -> 0.1007984 | D60: ='BALANCE SHEET '!D14/'INCOME STATEMENT'!D17 -> 0.1195369 | E60: ='BALANCE SHEET '!E14/'INCOME STATEMENT'!E17 -> 0.13022442 | F60: ='BALANCE SHEET '!F14/'INCOME STATEMENT'!F17 -> 0.12154319 | G60: ='BALANCE SHEET '!G14/'INCOME STATEMENT'!G17 -> 0.15176772 | H60: ='BALANCE SHEET '!H14/'INCOME STATEMENT'!H17 -> 0.14566717 | I60: ='BALANCE SHEET '!I14/'INCOME STATEMENT'!I17 -> 0.17277253 | ... K60: ='BALANCE SHEET '!K14/'INCOME STATEMENT'!K17 -> 0.1641279
A61: competitors | B61: =AVERAGE(AMD!B98,INTEL!B99,QUALCOMM!B102) -> 0.1344589 | C61: =AVERAGE(AMD!C98,INTEL!C99,QUALCOMM!C102) -> 0.1088064 | D61: =AVERAGE(AMD!D98,INTEL!D99,QUALCOMM!D102) -> 0.11929177 | E61: =AVERAGE(AMD!E98,INTEL!E99,QUALCOMM!E102) -> 0.14597118 | F61: =AVERAGE(AMD!F98,INTEL!F99,QUALCOMM!F102) -> 0.17779935 | G61: =AVERAGE(AMD!G98,INTEL!G99,QUALCOMM!G102) -> 0.13298689 | H61: =AVERAGE(AMD!H98,INTEL!H99,QUALCOMM!H102) -> 0.099229864 | I61: =AVERAGE(AMD!I98,INTEL!I99,QUALCOMM!I102) -> 0.10835809 | ... K61: =AVERAGE(AMD!K98,INTEL!K99,QUALCOMM!K102) -> 0.1042434

Sheet Projected Financial statement
A1: Projected Financial Statements
A2: Report Year | B2: 2023 | C2: 2024 | D2: 2025 | E2: 2026 | F2: 2027 | G2: 2028 | H2: 2029 | I2: 2030 | J2: 2031 | K2: 2032
A3: External Factors
A5: Risk Free Rate | D5: 0.0425 | E5: 0.0425 | F5: 0.0375 | G5: 0.0375 | H5: 0.0375 | I5: 0.035 | J5: 0.035 | K5: 0.035
A6: Market risk premium | D6: 0.0453 | E6: 0.0453 | F6: 0.0453 | G6: 0.0453 | H6: 0.0453 | I6: 0.0453 | J6: 0.0453 | K6: 0.0453
A7: Interest rate on debt (cost of debt) | D7: 0.0475 | E7: 0.045 | F7: 0.044 | G7: 0.044 | H7: 0.044 | I7: 0.044 | J7: 0.044 | K7: 0.044
A8: Annual sales growth | D8: 0.4 | E8: 0.35 | F8: 0.3 | G8: 0.25 | H8: 0.2 | I8: 0.18 | J8: 0.15 | K8: 0.12
A9: Cost of equity | D9: =D6*D42+D5 -> 0.119057 | E9: =E6*E42+E5 -> 0.119057 | F9: =F6*F42+F5 -> 0.114057 | G9: =G6*G42+G5 -> 0.114057 | H9: =H6*H42+H5 -> 0.114057 | I9: =I6*I42+I5 -> 0.111557 | J9: =J6*J42+J5 -> 0.111557 | K9: =K6*K42+K5 -> 0.111557
A10: Capital Structure (% debt) | C10: =C94/(C94+D44) -> 0.0025472669 | D10: =C10 -> 0.0025472669 | E10: =D10 -> 0.0025472669 | F10: =E10 -> 0.0025472669 | G10: =F10 -> 0.0025472669 | H10: =G10 -> 0.0025472669 | I10: =H10 -> 0.0025472669 | J10: =I10 -> 0.0025472669 | K10: =J10 -> 0.0025472669
A11: WACC (discount rate) | D11: =(1-D10)*D9+D10*D7*(1-D26) -> 0.11886021 | E11: =(1-E10)*E9+E10*E7*(1-E26) -> 0.1188546 | F11: =(1-F10)*F9+F10*F7*(1-F26) -> 0.1138651 | G11: =(1-G10)*G9+G10*G7*(1-G26) -> 0.1138651 | H11: =(1-H10)*H9+H10*H7*(1-H26) -> 0.1138651 | I11: =(1-I10)*I9+I10*I7*(1-I26) -> 0.11137147 | J11: =(1-J10)*J9+J10*J7*(1-J26) -> 0.11137147 | K11: =(1-K10)*K9+K10*K7*(1-K26) -> 0.11137147
A12: Perpetual CF growth | D12: 0.03
A13: Perpetual discount | D13: =K11 -> 0.11137147
A15: Debt portion to fin operations | D15: 1 | E15: 1 | F15: 1 | G15: 1 | H15: 1 | I15: 1 | J15: 1 | K15: 1
A16: Payout ratio | B16: 0 | C16: 0 | D16: 0 | E16: 0 | F16: 0 | G16: 0 | H16: 0 | I16: 0 | J16: 0 | K16: 0
A17: stock price | B17: 134.43
A19: Projected Assumptions
A21: Year | B21: 2023 | C21: 2024 | D21: 2025 | E21: 2026 | F21: 2027 | G21: 2028 | H21: 2029 | I21: 2030 | J21: 2031 | K21: 2032
A22: Sales Growth | C22: 1.26 | D22: 0.17 | E22: 0.24 | F22: 0.34 | G22: 0.47 | H22: 0.35 | I22: 0.29 | J22: 0.24 | K22: 0.17
A23: COGS/sales | C23: ='INCOME STATEMENT'!K18/'INCOME STATEMENT'!K17 -> 0.27282427 | D23: 0.2728 | E23: 0.2728 | F23: 0.2728 | G23: 0.2728 | H23: 0.2728 | I23: 0.2728 | J23: 0.2728 | K23: 0.2728
A24: SGA/Sales | C24: ='INCOME STATEMENT'!K20/'INCOME STATEMENT'!K17 -> 0.043563901 | D24: =C24 -> 0.043563901 | E24: =D24 -> 0.043563901 | F24: =E24 -> 0.043563901 | G24: =F24 -> 0.043563901 | H24: =G24 -> 0.043563901 | I24: =H24 -> 0.043563901 | J24: =I24 -> 0.043563901 | K24: =J24 -> 0.043563901
A25: Depreciation/sales | C25: ='BALANCE SHEET '!K19/'INCOME STATEMENT'!K17 -> 0.05759824 | D25: =C25 -> 0.05759824 | E25: =D25 -> 0.05759824 | F25: =E25 -> 0.05759824 | G25: =F25 -> 0.05759824 | H25: =G25 -> 0.05759824 | I25: =H25 -> 0.05759824 | J25: =I25 -> 0.05759824 | K25: =J25 -> 0.05759824
A26: Tax Rate | C26: ='INCOME STATEMENT'!K28/'INCOME STATEMENT'!K27 -> 0.11999527 | D26: =C26 -> 0.11999527 | E26: =D26 -> 0.11999527 | F26: =E26 -> 0.11999527 | G26: =F26 -> 0.11999527 | H26: =G26 -> 0.11999527 | I26: =H26 -> 0.11999527 | J26: =I26 -> 0.11999527 | K26: =J26 -> 0.11999527
A27: Cash/Sales | C27: ='BALANCE SHEET '!K11/'INCOME STATEMENT'!K17 -> 0.11949706 | D27: =C27 -> 0.11949706 | E27: =D27 -> 0.11949706 | F27: =E27 -> 0.11949706 | G27: =F27 -> 0.11949706 | H27: =G27 -> 0.11949706 | I27: =H27 -> 0.11949706 | J27: =I27 -> 0.11949706 | K27: =J27 -> 0.11949706
A28: Receivables/Sales | C28: ='BALANCE SHEET '!K14/'INCOME STATEMENT'!K17 -> 0.1641279 | D28: =C28 -> 0.1641279 | E28: =D28 -> 0.1641279 | F28: =E28 -> 0.1641279 | G28: =F28 -> 0.1641279 | H28: =G28 -> 0.1641279 | I28: =H28 -> 0.1641279 | J28: =I28 -> 0.1641279 | K28: =J28 -> 0.1641279
A29: Inventories/Sales | C29: ='BALANCE SHEET '!K15/'INCOME STATEMENT'!K17 -> 0.086701028 | D29: =C29 -> 0.086701028 | E29: =D29 -> 0.086701028 | F29: =E29 -> 0.086701028 | G29: =F29 -> 0.086701028 | H29: =G29 -> 0.086701028 | I29: =H29 -> 0.086701028 | J29: =I29 -> 0.086701028 | K29: =J29 -> 0.086701028
A30: RD/Sales | C30: ='INCOME STATEMENT'!K21/'INCOME STATEMENT'!K17 -> 0.14239519 | D30: =C30 -> 0.14239519 | E30: =D30 -> 0.14239519 | F30: =E30 -> 0.14239519 | G30: =F30 -> 0.14239519 | H30: =G30 -> 0.14239519 | I30: =H30 -> 0.14239519 | J30: =I30 -> 0.14239519 | K30: =J30 -> 0.14239519
A31: FA/Sales | C31: ='BALANCE SHEET '!K18/'INCOME STATEMENT'!K17 -> 0.12184433 | D31: =C31 -> 0.12184433 | E31: =D31 -> 0.12184433 | F31: =E31 -> 0.12184433 | G31: =F31 -> 0.12184433 | H31: =G31 -> 0.12184433 | I31: =H31 -> 0.12184433 | J31: =I31 -> 0.12184433 | K31: =J31 -> 0.12184433
A32: Other Assets/Sales | C32: ='BALANCE SHEET '!K22/'INCOME STATEMENT'!K17 -> 0.095958767 | D32: =C32 -> 0.095958767 | E32: =D32 -> 0.095958767 | F32: =E32 -> 0.095958767 | G32: =F32 -> 0.095958767 | H32: =G32 -> 0.095958767 | I32: =H32 -> 0.095958767 | J32: =I32 -> 0.095958767 | K32: =J32 -> 0.095958767
A33: Accounts Payable/sales | C33: ='BALANCE SHEET '!K25/'INCOME STATEMENT'!K17 -> 0.044302551 | D33: =C33 -> 0.044302551 | E33: =D33 -> 0.044302551 | F33: =E33 -> 0.044302551 | G33: =F33 -> 0.044302551 | H33: =G33 -> 0.044302551 | I33: =H33 -> 0.044302551 | J33: =I33 -> 0.044302551 | K33: =J33 -> 0.044302551
A34: Other Current Liabilities/Sales | C34: ='BALANCE SHEET '!K28/'INCOME STATEMENT'!K17 -> 0.030941204 | D34: =C34 -> 0.030941204 | E34: =D34 -> 0.030941204 | F34: =E34 -> 0.030941204 | G34: =F34 -> 0.030941204 | H34: =G34 -> 0.030941204 | I34: =H34 -> 0.030941204 | J34: =I34 -> 0.030941204 | K34: =J34 -> 0.030941204
A35: LT debt/Slales | C35: ='BALANCE SHEET '!K30/'INCOME STATEMENT'!K17 -> 0.13884968 | D35: =C35 -> 0.13884968 | E35: 0.1388 | F35: 0.1388 | G35: 0.1388 | H35: 0.1388 | I35: 0.1388 | J35: 0.1388 | K35: 0.1388
A36: Deferred LT liabilities/Sales | C36: ='BALANCE SHEET '!K31/'INCOME STATEMENT'!K17 -> 0.016988937 | D36: =C36 -> 0.016988937 | E36: 0.02 | F36: 0.02 | G36: 0.02 | H36: 0.02 | I36: 0.02 | J36: 0.02 | K36: 0.02
A37: Other Liabilites/Sales | C37: ='BALANCE SHEET '!K32/'INCOME STATEMENT'!K17 -> 0.043087883 | D37: =C37 -> 0.043087883 | E37: =D37 -> 0.043087883 | F37: =E37 -> 0.043087883 | G37: =F37 -> 0.043087883 | H37: =G37 -> 0.043087883 | I37: =H37 -> 0.043087883 | J37: =I37 -> 0.043087883 | K37: =J37 -> 0.043087883
A38: Paid in Capital/Slaes | C38: ='BALANCE SHEET '!K35/'INCOME STATEMENT'!K17 -> 0.21555432 | D38: =C38 -> 0.21555432 | E38: 0.07 | F38: 0.07 | G38: 0.07 | H38: 0.07 | I38: 0.07 | J38: 0.07 | K38: 0.07
A39: Retained Earnings/Sales | C39: ='BALANCE SHEET '!K36/'INCOME STATEMENT'!K17 -> 0.48942911 | D39: =C39 -> 0.48942911 | E39: 0.048 | F39: 0.048 | G39: 0.048 | H39: 0.048 | I39: 0.048 | J39: 0.048 | K39: 0.048
A40: interest rate | D40: 0.05 | E40: 0.05 | F40: 0.05 | G40: 0.05 | H40: 0.05 | I40: 0.05 | J40: 0.05 | K40: 0.05
A41: annual decrease | D41: 0.006 | E41: 0.006 | F41: 0.006 | G41: 0.006 | H41: 0.006 | I41: 0.006 | J41: 0.006 | K41: 0.006
A42: Beta | C42: 1.69 | D42: 1.69 | E42: 1.69 | F42: 1.69 | G42: 1.69 | H42: 1.69 | I42: 1.69 | J42: 1.69 | K42: 1.69
A43: number of shares | D43: ='INCOME STATEMENT'!K37 -> 24640000
A44: market cap | D44: =D43*B17 -> 3312355200
A45: total non-operating income | B45: =B61/B52 -> -0.0015941277 | C45: 0.0139 | D45: 0.0142 | E45: 0.0138 | F45: 0.0123 | G45: 0.01 | H45: 0.01 | I45: 0.008 | J45: 0.008 | K45: 0.01
A47: Income Statement
A49: Report Year | B49: 2023 | C49: 2024 | D49: 2025 | E49: 2026 | F49: 2027 | G49: 2028 | H49: 2029 | I49: 2030 | J49: 2031 | K49: 2032
A50: Sales Revenue | B50: - | C50: 60922000
A51: Y/Y Growth in Total Revenue, % | C51: =IFERROR(C52/B52-1,"NA") -> 1.2585453 | D51: 0.17 | E51: 0.24 | F51: 0.34 | G51: 0.47 | H51: 0.35 | I51: 0.29 | J51: 0.24 | K51: 0.17
A52: Total Revenue | B52: 26974000 | C52: 60922000 | D52: =C52*(1+D51) -> 71278740 | E52: =D52*(1+E51) -> 88385638 | F52: =E52*(1+F51) -> 1.1843675e+08 | G52: =F52*(1+G51) -> 1.7410203e+08 | H52: =G52*(1+H51) -> 2.3503774e+08 | I52: =H52*(1+I51) -> 3.0319868e+08 | J52: =I52*(1+J51) -> 3.7596637e+08 | K52: =J52*(1+K51) -> 4.3988065e+08
A53: Direct Costs | B53: 11618000 | C53: 16621000 | D53: =D52*D23 -> 19444840 | E53: =E52*E23 -> 24111602 | F53: =F52*F23 -> 32309547 | G53: =G52*G23 -> 47495033 | H53: =H52*H23 -> 64118295 | I53: =I52*I23 -> 82712601 | J53: =J52*J23 -> 1.0256363e+08 | K53: =K52*K23 -> 1.1999944e+08
A54: Gross Profit | B54: 15356000 | C54: 44301000 | D54: =D52-D53 -> 51833900 | E54: =E52-E53 -> 64274036 | F54: =F52-F53 -> 86127208 | G54: =G52-G53 -> 1.26607e+08 | H54: =H52-H53 -> 1.7091944e+08 | I54: =I52-I53 -> 2.2048608e+08 | J54: =J52-J53 -> 2.7340274e+08 | K54: =K52-K53 -> 3.1988121e+08
A55: Selling General & Admin | B55: 2440000 | C55: 2654000 | D55: =D52*D24 -> 3105180 | E55: =E52*E24 -> 3850423.2 | F55: =F52*F24 -> 5159567.1 | G55: =G52*G24 -> 7584563.6 | H55: =H52*H24 -> 10239161 | I55: =I52*I24 -> 13208518 | J55: =J52*J24 -> 16378562 | K55: =K52*K24 -> 19162917
A56: Research & Development | B56: 7339000 | C56: 8675000 | D56: =D52*D30 -> 10149750 | E56: =E52*E30 -> 12585690 | F56: =F52*F30 -> 16864825 | G56: =G52*G30 -> 24791292 | H56: =H52*H30 -> 33468244 | I56: =I52*I30 -> 43174035 | J56: =J52*J30 -> 53535804 | K56: =K52*K30 -> 62636890
A57: Total Indirect Operating Costs | B57: =B55+B56 -> 9779000 | C57: =C55+C56 -> 11329000 | D57: =D55+D56 -> 13254930 | E57: =E55+E56 -> 16436113 | F57: =F55+F56 -> 22024392 | G57: =G55+G56 -> 32375856 | H57: =H55+H56 -> 43707405 | I57: =I55+I56 -> 56382553 | ... K57: =K55+K56 -> 81799808
A58: Operating Income | B58: 4224000 | C58: 32972000 | D58: =D54-D57 -> 38578970 | E58: =E54-E57 -> 47837922 | F58: =F54-F57 -> 64102816 | G58: =G54-G57 -> 94231140 | H58: =H54-H57 -> 1.2721204e+08 | I58: =I54-I57 -> 1.6410353e+08 | J58: =J54-J57 -> 2.0348838e+08 | K58: =K54-K57 -> 2.380814e+08
A59: Interest Income | B59: 5000 | C59: 609000
A60: Other Non-Operating Income | B60: -48000 | C60: 237000 | D60: =D52*D25 -> 4105530 | E60: =E52*E25 -> 5090857.2 | F60: =F52*F25 -> 6821748.6 | G60: =G52*G25 -> 10027971 | H60: =H52*H25 -> 13537760 | I60: =I52*I25 -> 17463711 | J60: =J52*J25 -> 21655001 | K60: =K52*K25 -> 25336351
A61: Total Non-Operating Income | B61: -43000 | C61: 846000 | D61: =D52*D45 -> 1012158.1 | E61: =E52*E45 -> 1219721.8 | F61: =F52*F45 -> 1456772.1 | G61: =G52*G45 -> 1741020.3 | H61: =H52*H45 -> 2350377.4 | I61: =I52*I45 -> 2425589.5 | J61: =J52*J45 -> 3007730.9 | K61: =K52*K45 -> 4398806.5
A62: Earnings Before Tax | B62: =B58 -> 4224000 | C62: =C58 -> 32972000 | D62: =D58+D61 -> 39591128 | E62: =E58+E61 -> 49057644 | F62: =F58+F61 -> 65559588 | G62: =G58+G61 -> 95972160 | H62: =H58+H61 -> 1.2956242e+08 | I62: =I58+I61 -> 1.6652912e+08 | J62: =J58+J61 -> 2.0649611e+08 | K62: =K58+K61 -> 2.4248021e+08
A63: Net Income | B63: 4368000 | C63: 29760000 | D63: =D62-D71 -> 34840380 | E63: =E62-E71 -> 43170959 | F63: =F62-F71 -> 57692748 | G63: =G62-G71 -> 84455955 | H63: =H62-H71 -> 1.1401554e+08 | I63: =I62-I71 -> 1.4654641e+08 | J63: =J62-J71 -> 1.8171755e+08 | K63: =K62-K71 -> 2.1338373e+08
A64: EPS Net Basic | B64: 0.18 | C64: 1.21
A65: EPS Continuing Basic | B65: 0.18 | C65: 1.21
A66: Average Shares Diluted | B66: 25070000 | C66: 24940000
A67: EPS Net Diluted | B67: 0.17 | C67: 1.19
A68: EPS Continuing Diluted | B68: 0.17 | C68: 1.19
A69: Shares Outstanding | B69: 24660000 | C69: 24640000
A70: Depriciation & Amoriztion | B70: 5768 | C70: 34480
A71: Taxation | B71: 123000 | C71: 4058000 | D71: =D62*D26 -> 4750748 | E71: =E62*E26 -> 5886685.2 | F71: =F62*F26 -> 7866840.4 | G71: =G62*G26 -> 11516205 | H71: =H62*H26 -> 15546877 | I71: =I62*I26 -> 19982706 | J71: =J62*J26 -> 24778556 | K71: =K62*K26 -> 29096478
A72: average share basic | B72: 24640000 | C72: 246900 | D72: =C72*(1-D41) -> 245418.6 | E72: =D72*(1-E41) -> 243946.09 | F72: =E72*(1-F41) -> 242482.41 | G72: =F72*(1-G41) -> 241027.52 | H72: =G72*(1-H41) -> 239581.35 | I72: =H72*(1-I41) -> 238143.86 | J72: =I72*(1-J41) -> 236715 | K72: =J72*(1-K41) -> 235294.71
A74: Profit Margin | B74: =B63/B52 -> 0.16193371 | C74: =C63/C52 -> 0.48849348 | D74: =D63/D52 -> 0.48879062 | E74: =E63/E52 -> 0.48843862 | F74: =F63/F52 -> 0.48711862 | G74: =G63/G52 -> 0.4850946 | H74: =H63/H52 -> 0.4850946 | I74: =I63/I52 -> 0.48333459 | ... K74: =K63/K52 -> 0.4850946
A75: Depreciation | B75: ='BALANCE SHEET '!J19-'BALANCE SHEET '!I19 -> 791000 | C75: ='BALANCE SHEET '!K19-'BALANCE SHEET '!J19 -> 815000 | D75: =D25*AVERAGE(C85:D85) -> 463893.64 | E75: =E25*AVERAGE(D85:E85) -> 560263.8 | F75: =F25*AVERAGE(E85:F85) -> 725741.71 | G75: =G25*AVERAGE(F85:G85) -> 1026521.3 | H75: =H25*AVERAGE(G85:H85) -> 1435675.3 | I75: =I25*AVERAGE(H85:I85) -> 1888676.7 | J75: =J25*AVERAGE(I85:J85) -> 2383196.5 | K75: =K25*AVERAGE(J85:K85) -> 2862814.8
A78: Balance Sheet
A80: Cash & Equivs & ST Investments | B80: 13296000 | C80: 25984000 | D80: =D27*D52 -> 8517600 | E80: =E27*E52 -> 10561824 | F80: =F27*F52 -> 14152844 | G80: =G27*G52 -> 20804681 | H80: =H27*H52 -> 28086319 | I80: =I27*I52 -> 36231352 | J80: =J27*J52 -> 44926876 | K80: =K27*K52 -> 52564445
A81: Receivables (ST) | B81: 3827000 | C81: 9999000 | D81: =D52*D28 -> 11698830 | E81: =E52*E28 -> 14506549 | F81: =F52*F28 -> 19438776 | G81: =G52*G28 -> 28575001 | H81: =H52*H28 -> 38576251 | I81: =I52*I28 -> 49763364 | J81: =J52*J28 -> 61706571 | K81: =K52*K28 -> 72196688
A82: Inventories | B82: 5159000 | C82: 5282000 | D82: =D52*D29 -> 6179940 | E82: =E52*E29 -> 7663125.6 | F82: =F52*F29 -> 10268588 | G82: =G52*G29 -> 15094825 | H82: =H52*H29 -> 20378013 | I82: =I52*I29 -> 26287637 | J82: =J52*J29 -> 32596670 | K82: =K52*K29 -> 38138104
A84: Total Current Assets | B84: 23073000 | C84: 44345000 | D84: =SUM(D80:D82) -> 26396370 | E84: =SUM(E80:E82) -> 32731499 | F84: =SUM(F80:F82) -> 43860208 | G84: =SUM(G80:G82) -> 64474506 | H84: =SUM(H80:H82) -> 87040584 | I84: =SUM(I80:I82) -> 1.1228235e+08 | J84: =SUM(J80:J82) -> 1.3923012e+08 | K84: =SUM(K80:K82) -> 1.6289924e+08
A85: Gross Property Plant & Equip | B85: 6501000 | C85: 7423000 | D85: =D52*D31 -> 8684910 | E85: =E52*E31 -> 10769288 | F85: =F52*F31 -> 14430846 | G85: =G52*G31 -> 21213344 | H85: =H52*H31 -> 28638015 | I85: =I52*I31 -> 36943039 | J85: =J52*J31 -> 45809368 | K85: =K52*K31 -> 53596961
A86: Accumulated Deprecation | B86: 2694000 | C86: 3509000 | D86: =C86+D75 -> 3972893.6 | E86: =D86+E75 -> 4533157.4 | F86: =E86+F75 -> 5258899.1 | G86: =F86+G75 -> 6285420.5 | H86: =G86+H75 -> 7721095.8 | I86: =H86+I75 -> 9609772.4 | J86: =I86+J75 -> 11992969 | K86: =J86+K75 -> 14855784
A87: Net Property Plant & Equip | B87: 3807000 | C87: 3914000 | D87: =D85-D86 -> 4712016.4 | E87: =E85-E86 -> 6236131 | F87: =F85-F86 -> 9171947.3 | G87: =G85-G86 -> 14927924 | H87: =H85-H86 -> 20916919 | I87: =I85-I86 -> 27333267 | J87: =J85-J86 -> 33816400 | K87: =K85-K86 -> 38741177
A88: Other Assets | B88: 1183000 | C88: 5846000 | D88: =D32*D52 -> 6839820 | E88: =E32*E52 -> 8481376.8 | F88: =F32*F52 -> 11365045 | G88: =G32*G52 -> 16706616 | H88: =H32*H52 -> 22553932 | I88: =I32*I52 -> 29094572 | J88: =J32*J52 -> 36077269 | K88: =K32*K52 -> 42210405
A89: Total LT Assets | B89: =SUM(B87:B88) -> 4990000 | C89: =SUM(C87:C88) -> 9760000 | D89: =SUM(D87:D88) -> 11551836 | E89: =SUM(E87:E88) -> 14717508 | F89: =SUM(F87:F88) -> 20536992 | G89: =SUM(G87:G88) -> 31634540 | H89: =SUM(H87:H88) -> 43470851 | I89: =SUM(I87:I88) -> 56427838 | ... K89: =SUM(K87:K88) -> 80951582
A90: Total Assets | B90: =B84+B89 -> 28063000 | C90: =C84+C89 -> 54105000 | D90: =D84+D89 -> 37948206 | E90: =E84+E89 -> 47449007 | F90: =F84+F89 -> 64397201 | G90: =G84+G89 -> 96109046 | H90: =H84+H89 -> 1.3051143e+08 | I90: =I84+I89 -> 1.6871019e+08 | ... K90: =K84+K89 -> 2.4385082e+08
A91: Accounts Payable & Accrued Exps | B91: 2919000 | C91: 7496000 | D91: =D52*D33 -> 3157830 | E91: =E52*E33 -> 3915709.2 | F91: =F52*F33 -> 5247050.3 | G91: =G52*G33 -> 7713164 | H91: =H52*H33 -> 10412771 | I91: =I52*I33 -> 13432475 | J91: =J52*J33 -> 16656269 | K91: =K52*K33 -> 19487835
A92: Other Current Liabilities | B92: 2394000 | C92: 2394000 | D92: =D52*D37 -> 3071250 | E92: =E52*E37 -> 3808350 | F92: =F52*F37 -> 5103189 | G92: =G52*G37 -> 7501687.8 | H92: =H52*H37 -> 10127279 | I92: =I52*I37 -> 13064189 | J92: =J52*J37 -> 16199595 | K92: =K52*K37 -> 18953526
A93: Total Current Liabilities | B93: 6563000 | C93: 10631000 | D93: =SUM(D91:D92) -> 6229080 | E93: =SUM(E91:E92) -> 7724059.2 | F93: =SUM(F91:F92) -> 10350239 | G93: =SUM(G91:G92) -> 15214852 | H93: =SUM(H91:H92) -> 20540050 | I93: =SUM(I91:I92) -> 26496664 | J93: =SUM(J91:J92) -> 32855864 | K93: =SUM(K91:K92) -> 38441361
A94: LT Debt & Leases | B94: 9703000 | C94: 8459000 | D94: =C94*(1+D51) -> 9897030 | E94: =D94*(1+E51) -> 12272317 | F94: =E94*(1+F51) -> 16444905 | G94: =F94*(1+G51) -> 24174010 | H94: =G94*(1+H51) -> 32634914 | I94: =H94*(1+I51) -> 42099039 | J94: =I94*(1+J51) -> 52202809 | K94: =J94*(1+K51) -> 61077286
A95: Total Liabilities | B95: 19081000 | C95: 22750000 | D95: =SUM(D93:D94) -> 16126110 | E95: =SUM(E93:E94) -> 19996376 | F95: =SUM(F93:F94) -> 26795144 | G95: =SUM(G93:G94) -> 39388862 | H95: =SUM(H93:H94) -> 53174964 | I95: =SUM(I93:I94) -> 68595704 | J95: =SUM(J93:J94) -> 85058672 | K95: =SUM(K93:K94) -> 99518647
A96: Additional Paid-In Capital | B96: 11971000 | C96: 13132000 | D96: =D52*7% -> 4989511.8 | E96: =E52*7% -> 6186994.6 | F96: =F52*7% -> 8290572.8 | G96: =G52*7% -> 12187142 | H96: =H52*7% -> 16452642 | I96: =I52*7% -> 21223908 | J96: =J52*7% -> 26317646 | K96: =K52*7% -> 30791645
A97: Retained Earnings | B97: 10171000 | C97: 29817000 | D97: =C97+D52*(1-0%) -> 101095740 | E97: =D97+E52*(1-0%) -> 1.8948138e+08 | F97: =E97+F52*(1-0%) -> 3.0791813e+08 | G97: =F97+G52*(1-0%) -> 4.8202016e+08 | H97: =G97+H52*(1-0%) -> 7.170579e+08 | I97: =H97+I52*(1-0%) -> 1.0202566e+09 | J97: =I97+J52*(1-0%) -> 1.396223e+09 | K97: =J97+K52*(1-0%) -> 1.8361036e+09
A98: Total Equity | B98: 22101000 | C98: 42978000 | D98: =D99-D95 -> 21822096 | E98: =E99-E95 -> 27452630 | F98: =F99-F95 -> 37602056 | G98: =G99-G95 -> 56720184 | H98: =H99-H95 -> 77336470 | I98: =I99-I95 -> 1.0011449e+08 | J98: =J99-J95 -> 1.2406511e+08 | K98: =K99-K95 -> 1.4433217e+08
A99: Total Liabilities & Equity | B99: 41182000 | C99: 65728000 | D99: =D90 -> 37948206 | E99: =E90 -> 47449007 | F99: =F90 -> 64397201 | G99: =G90 -> 96109046 | H99: =H90 -> 1.3051143e+08 | I99: =I90 -> 1.6871019e+08 | J99: =J90 -> 2.0912379e+08 | K99: =K90 -> 2.4385082e+08
A101: Investment Module
A103: Current Asset Investment | B103: =SUM(B81,B88)-SUM(A81,A88) -> 5010000 | C103: =SUM(C81,C88)-SUM(B81,B88) -> 10835000 | D103: =SUM(D81,D88)-SUM(C81,C88) -> 2693650 | E103: =SUM(E81,E88)-SUM(D81,D88) -> 4449276 | F103: =SUM(F81,F88)-SUM(E81,E88) -> 7815894.8 | G103: =SUM(G81,G88)-SUM(F81,F88) -> 14477796 | H103: =SUM(H81,H88)-SUM(G81,G88) -> 15848566 | I103: =SUM(I81,I88)-SUM(H81,H88) -> 17727753 | ... K103: =SUM(K81,K88)-SUM(J81,J88) -> 16623253
A104: Investment in new Fixed Assets | B104: =B85-0 -> 6501000 | C104: =C85-B85 -> 922000 | D104: =D85-C85 -> 1261910 | E104: =E85-D85 -> 2084378.4 | F104: =F85-E85 -> 3661558.1 | G104: =G85-F85 -> 6782497.8 | H104: =H85-G85 -> 7424670.5 | I104: =I85-H85 -> 8305024.3 | J104: =J85-I85 -> 8866329.4 | K104: =K85-J85 -> 7787592.6
A105: Replacement of Depreciated Assets | B105: =B75 -> 791000 | C105: =C75 -> 815000 | D105: =D75 -> 463893.64 | E105: =E75 -> 560263.8 | F105: =F75 -> 725741.71 | G105: =G75 -> 1026521.3 | H105: =H75 -> 1435675.3 | I105: =I75 -> 1888676.7 | ... K105: =K75 -> 2862814.8
A106: Fixed Asset Investment | B106: =B104+B105 -> 7292000 | C106: =C104+C105 -> 1737000 | D106: =D104+D105 -> 1725803.6 | E106: =E104+E105 -> 2644642.2 | F106: =F104+F105 -> 4387299.8 | G106: =G104+G105 -> 7809019.2 | H106: =H104+H105 -> 8860345.8 | I106: =I104+I105 -> 10193701 | ... K106: =K104+K105 -> 10650407
A107: Total Investment | B107: =B106+B103 -> 12302000 | C107: =C106+C103 -> 12572000 | D107: =D106+D103 -> 4419453.6 | E107: =E106+E103 -> 7093918.2 | F107: =F106+F103 -> 12203195 | G107: =G106+G103 -> 22286815 | H107: =H106+H103 -> 24708912 | I107: =I106+I103 -> 27921454 | ... K107: =K106+K103 -> 27273660
A109: Financiang Module
A111: Required financing | B111: =B107 -> 12302000 | C111: =C107 -> 12572000 | D111: =D107 -> 4419453.6 | E111: =E107 -> 7093918.2 | F111: =F107 -> 12203195 | G111: =G107 -> 22286815 | H111: =H107 -> 24708912 | I111: =I107 -> 27921454 | ... K111: =K107 -> 27273660
A112: Sources of funds:
A113: Net income | B113: =B63 -> 4368000 | C113: =C63 -> 29760000 | D113: =D63 -> 34840380 | E113: =E63 -> 43170959 | F113: =F63 -> 57692748 | G113: =G63 -> 84455955 | H113: =H63 -> 1.1401554e+08 | I113: =I63 -> 1.4654641e+08 | ... K113: =K63 -> 2.1338373e+08
A114: Depreciation | B114: =B75 -> 791000 | C114: =C75 -> 815000 | D114: =D75 -> 463893.64 | E114: =E75 -> 560263.8 | F114: =F75 -> 725741.71 | G114: =G75 -> 1026521.3 | H114: =H75 -> 1435675.3 | I114: =I75 -> 1888676.7 | ... K114: =K75 -> 2862814.8
A115: Earnings CF | B115: =B113+B114 -> 5159000 | C115: =C113+C114 -> 30575000 | D115: =D113+D114 -> 35304273 | E115: =E113+E114 -> 43731223 | F115: =F113+F114 -> 58418489 | G115: =G113+G114 -> 85482476 | H115: =H113+H114 -> 1.1545121e+08 | I115: =I113+I114 -> 1.4843509e+08 | ... K115: =K113+K114 -> 2.1624654e+08
...

Sheet Relative Value
C2: NVDIA | E2: AMD | F2: Intel | G2: Qualcomm
B3: Market Cap | C3: =C4*134.43 -> 3312355200 | E3: =E4*110.84 -> 179117440 | F3: =F4*24.87 -> 10768710 | G3: =G4*165.43 -> 184123590
B4: Shares outstanding | C4: ='Projected Financial statement'!D43 -> 24640000 | E4: =AMD!B86 -> 1616000 | F4: =INTEL!B87 -> 433000 | G4: =QUALCOMM!B90 -> 1113000
B5: NET INCOME | C5: ='Projected Financial statement'!C63 -> 29760000 | E5: =AMD!B77 -> 854000 | F5: =INTEL!B78 -> -18756 | G5: =QUALCOMM!B82 -> 10142000
B6: NET INCOME (last) | C6: ='Projected Financial statement'!B63 -> 4368000 | E6: =AMD!C77 -> 1320000 | F6: =INTEL!C78 -> 1689 | G6: =QUALCOMM!C82 -> 7232000
B7: EBITDA | C7: ='Projected Financial statement'!C58+'Projected Financial statement'!C75 -> 33787000 | E7: =AMD!B67+(AMD!B25-AMD!C25) -> 681000 | F7: =INTEL!B66+(INTEL!B18-INTEL!C18) -> -7495 | G7: =QUALCOMM!B72+(QUALCOMM!B26-QUALCOMM!C26) -> 11279000
B8: SALES | C8: ='Projected Financial statement'!C52 -> 60922000 | E8: =AMD!B58 -> 22680000 | F8: =INTEL!B57 -> 53101 | G8: =QUALCOMM!B65 -> 38962000
B9: BOOK VALUE (EQUITY) | C9: ='Projected Financial statement'!C98 -> 42978000 | E9: =AMD!B48 -> 55892000 | F9: =INTEL!B45 -> 99270 | G9: =QUALCOMM!B51 -> 26274000
I10: Average
B11: P/E | C11: =C3/C5 -> 111.30226 | E11: =E3/E5 -> 209.73939 | F11: =F3/F5 -> -574.14747 | G11: =G3/G5 -> 18.154564 | I11: =AVERAGE(E11,G11) -> 113.94698
B12: P/E (forward or last earnings) | C12: =C3/C6 -> 758.32308 | E12: =E3/E6 -> 135.69503 | F12: =F3/F6 -> 6375.7904 | G12: =G3/G6 -> 25.459567 | I12: =AVERAGE(E12,G12) -> 80.577299
B13: EBITDA multiplier | C13: =C3/C7 -> 98.036381 | E13: =E3/E7 -> 263.0212 | F13: =F3/F7 -> -1436.7859 | G13: =G3/G7 -> 16.324461 | I13: =AVERAGE(E13,G13) -> 139.67283
B14: Sales multiplier | C14: =C3/C8 -> 54.370428 | E14: =E3/E8 -> 7.8975944 | F14: =F3/F8 -> 202.79675 | G14: =G3/G8 -> 4.7257222 | I14: =AVERAGE(E14,G14) -> 6.3116583
B15: Book Value multiplier | C15: =C3/C9 -> 77.070948 | E15: =E3/E9 -> 3.2047062 | F15: =F3/F9 -> 108.479 | G15: =G3/G9 -> 7.0078248 | I15: =AVERAGE(E15,G15) -> 5.1062655
B17: ULTI
B19: P/E (forward or last earnings) | C19: =I11*C6 -> 4.977204e+08 | D19: =C19/'Projected Financial statement'!$D$43 -> 20.199691
B20: EBITDA multiplier | C20: =I12*C7 -> 2.7224652e+09 | D20: =C20/'Projected Financial statement'!$D$43 -> 110.48966
B21: Sales multiplier | C21: =I13*C8 -> 8.5091483e+09 | D21: =C21/'Projected Financial statement'!$D$43 -> 345.33881
B22: Book Value multiplier | C22: =I14*C9 -> 2.7126245e+08 | D22: =C22/'Projected Financial statement'!$D$43 -> 11.009028
C24: Average | D24: =AVERAGE(D19:D22) -> 121.7593

Sheet COMPARISION
B1: NVDA | C1: AMD | D1: INTC | E1: QCOM
B2: NVIDIA Corporation | C2: Advanced Micro Devices, Inc. | D2: Intel Corporation | E2: QUALCOMM Incorporated
A3: Revenue | B3: 113.27B | C3: 24.30B | D3: 54.25B | E3: 38.96B
A4: gross profit | B4: 85.93B | C4: 11.75B | D4: 18.81B | E4: 21.90B
A5: Gross Margin | B5: 0.7586 | C5: 0.4838 | D5: 0.3467 | E5: 0.5621
A6: Profit Margin | B6: 0.5569 | C6: 0.0752 | D6: -0.2942 | E6: 0.2603

Sheet AMD
A4: Powered by Clearbit
A5: Advanced Micro Devices Inc (NMS: AMD)
A7: Exchange rate used is that of the Year End reported date
A10: Standardized Annual Balance Sheet
A11: Report Date | B11: 12/30/2023 | C11: 12/31/2022 | D11: 12/25/2021 | E11: 12/26/2020 | F11: 12/28/2019 | G11: 12/29/2018 | H11: 12/30/2017 | I11: 12/31/2016 | J11: 12/26/2015 | K11: 12/27/2014
A12: Currency | B12: USD | C12: USD | D12: USD | E12: USD | F12: USD | G12: USD | H12: USD | I12: USD | J12: USD | K12: USD
A13: Audit Status | B13: Not Qualified | C13: Not Qualified | D13: Not Qualified | E13: Not Qualified | F13: Not Qualified | G13: Not Qualified | H13: Not Qualified | I13: Not Qualified | J13: Not Qualified | K13: Not Qualified
A14: Consolidated | B14: Yes | C14: Yes | D14: Yes | E14: Yes | F14: Yes | G14: Yes | H14: Yes | I14: Yes | J14: Yes | K14: Yes
A15: Scale | B15: Thousands | C15: Thousands | D15: Thousands | E15: Thousands | F15: Thousands | G15: Thousands | H15: Thousands | I15: Thousands | J15: Thousands | K15: Thousands
A16: Cash & Equivalents | B16: 3933000 | C16: 4835000 | D16: 2535000 | E16: 1595000 | F16: 1503000 | G16: 1156000 | H16: 1185000 | I16: 1264000 | J16: 785000 | K16: 1040000
A17: Short Term Investments | B17: 1840000 | C17: 1020000 | D17: 1073000 | E17: 695000 | F17: 0 | G17: 0 | H17: 0 | I17: 0 | J17: 0 | K17: 0
A18: Cash & Equivs & ST Investments | B18: 5773000 | C18: 5855000 | D18: 3608000 | E18: 2290000 | F18: 1503000 | G18: 1156000 | H18: 1185000 | I18: 1264000 | J18: 785000 | K18: 1040000
A19: Receivables (ST) | B19: 5376000 | C19: 4126000 | D19: 2706000 | E19: 2066000 | F19: 1859000 | G19: 1235000 | H19: 400000 | I19: 311000 | J19: 533000 | K19: 818000
A20: Related Parties (ST Asset) | B20: 9000 | C20: 2000 | D20: 2000 | E20: 10000 | F20: 0 | G20: 0 | H20: 0 | I20: 0 | J20: 0 | K20: 0
A21: Inventories | B21: 4351000 | C21: 3771000 | D21: 1955000 | E21: 1399000 | F21: 982000 | G21: 845000 | H21: 739000 | I21: 751000 | J21: 678000 | K21: 685000
A22: Other Current Assets | B22: 1259000 | C22: 1265000 | D22: 312000 | E22: 378000 | F22: 253000 | G22: 247000 | H22: 221000 | I22: 109000 | J22: 248000 | K22: 80000
A23: Total Current Assets | B23: 16768000 | C23: 15019000 | D23: 8583000 | E23: 6143000 | F23: 4597000 | G23: 3540000 | H23: 2622000 | I23: 2530000 | J23: 2320000 | K23: 2736000
A24: Gross Property Plant & Equip | B24: 3376000 | C24: 3020000 | D24: 1836000 | E24: 1553000 | F24: 1268000 | G24: 1055000 | H24: 1001000 | I24: 881000 | J24: 984000 | K24: 1680000
A25: Accumulated Depreciation | B25: 1787000 | C25: 1507000 | D25: 1134000 | E25: 912000 | F25: 768000 | G25: 707000 | H25: 740000 | I25: 717000 | J25: 796000 | K25: 1378000
A26: Net Property Plant & Equip | B26: 1589000 | C26: 1513000 | D26: 702000 | E26: 641000 | F26: 500000 | G26: 348000 | H26: 261000 | I26: 164000 | J26: 188000 | K26: 302000
A27: Long Term Investments | B27: 99000 | C27: 83000 | D27: 69000 | E27: 63000 | F27: 58000 | G27: 58000 | H27: 58000 | I27: 59000 | J27: 0 | K27: 0
... A35: Accrued Expenses | B35: 3082000 | C35: 3077000 | D35: 2424000 | E35: 1796000 | F35: 1084000 | G35: 763000 | H35: 541000 | I35: 391000 | J35: 472000 | K35: 558000
A36: Current Debt | B36: 751000 | C36: 0 | D36: 312000 | E36: 0 | F36: 0 | G36: 136000 | H36: 70000 | I36: - | J36: 230000 | K36: 177000
A37: Other Current Liabilities | B37: 438000 | C37: 336000 | D37: 98000 | E37: 75000 | F37: 74000 | G37: 24000 | H37: 79000 | I37: 132000 | J37: 177000 | K37: 72000
A38: Total Current Liabilities | B38: 6689000 | C38: 6369000 | D38: 4240000 | E38: 2417000 | F38: 2359000 | G38: 1984000 | H38: 1486000 | I38: 1346000 | J38: 1403000 | K38: 1440000
A39: LT Debt & Leases | B39: 1717000 | C39: 2467000 | D39: 1000 | E39: 330000 | F39: 486000 | G39: 1114000 | H39: 1325000 | I39: 1435000 | J39: 2032000 | K39: 2035000
A40: Deferred LT Liabilities | B40: 1202000 | C40: 1934000 | D40: 0 | E40: 0 | F40: 0 | G40: 0 | H40: 0 | I40: 0 | J40: 0 | K40: 0
A41: Other Liabilities | B41: 2385000 | C41: 2060000 | D41: 681000 | E41: 378000 | F41: 356000 | G41: 192000 | H41: 118000 | I41: 124000 | J41: 86000 | K41: 105000
A42: Total Liabilities | B42: 11993000 | C42: 12830000 | D42: 4922000 | E42: 3125000 | F42: 3201000 | G42: 3290000 | H42: 2929000 | I42: 2905000 | J42: 3521000 | K42: 3580000
A43: Common Share Capital | B43: 17000 | C43: 16000 | D43: 12000 | E43: 12000 | F43: 12000 | G43: 10000 | H43: 9000 | I43: 9000 | J43: 8000 | K43: 8000
A44: Additional Paid-In Capital | B44: 59676000 | C44: 58005000 | D44: 11069000 | E44: 10544000 | F44: 9963000 | G44: 8750000 | H44: 8464000 | I44: 8334000 | J44: 7017000 | K44: 6949000
A45: Retained Earnings | B45: 723000 | C45: -131000 | D45: -1451000 | E45: -4605000 | F45: -7095000 | G45: -7436000 | H45: -7760000 | I45: -7803000 | J45: -7306000 | K45: -6646000
A46: Accum Other Comprehensive Income | B46: -10000 | C46: -41000 | D46: -3000 | E46: 17000 | F46: 0 | G46: -8000 | H46: 6000 | I46: -5000 | J46: -8000 | K46: -5000
A47: Treasury Stock | B47: 4514000 | C47: 3099000 | D47: 2130000 | E47: 131000 | F47: 53000 | G47: 50000 | H47: 108000 | I47: 119000 | J47: 123000 | K47: 119000
A48: Total Equity | B48: 55892000 | C48: 54750000 | D48: 7497000 | E48: 5837000 | F48: 2827000 | G48: 1266000 | H48: 611000 | I48: 416000 | J48: -412000 | K48: 187000
A49: Total Liabilities & Equity | B49: 67885000 | C49: 67580000 | D49: 12419000 | E49: 8962000 | F49: 6028000 | G49: 4556000 | H49: 3540000 | I49: 3321000 | J49: 3109000 | K49: 3767000
A51: Standardized Annual Income Statement
A52: Report Date | B52: 12/30/2023 | C52: 12/31/2022 | D52: 12/25/2021 | E52: 12/26/2020 | F52: 12/28/2019 | G52: 12/29/2018 | H52: 12/30/2017 | I52: 12/31/2016 | J52: 12/26/2015 | K52: 12/27/2014
A53: Currency | B53: USD | C53: USD | D53: USD | E53: USD | F53: USD | G53: USD | H53: USD | I53: USD | J53: USD | K53: USD
A54: Audit Status | B54: Not Qualified | C54: Not Qualified | D54: Not Qualified | E54: Not Qualified | F54: Not Qualified | G54: Not Qualified | H54: Not Qualified | I54: Not Qualified | J54: Not Qualified | K54: Not Qualified
A55: Consolidated | B55: Yes | C55: Yes | D55: Yes | E55: Yes | F55: Yes | G55: Yes | H55: Yes | I55: Yes | J55: Yes | K55: Yes
A56: Scale | B56: Thousands | C56: Thousands | D56: Thousands | E56: Thousands | F56: Thousands | G56: Thousands | H56: Thousands | I56: Thousands | J56: Thousands | K56: Thousands
A57: Other Revenue | B57: 22680000 | C57: 23601000 | D57: 16434000 | E57: 9763000 | F57: 6731000 | G57: 6475000 | H57: 5329000 | I57: 4272000 | J57: 3991000 | K57: 5506000
A58: Total Revenue | B58: 22680000 | C58: 23601000 | D58: 16434000 | E58: 9763000 | F58: 6731000 | G58: 6475000 | H58: 5329000 | I58: 4272000 | J58: 3991000 | K58: 5506000
A59: Direct Costs | B59: 12220000 | C59: 12998000 | D59: 8505000 | E59: 5416000 | F59: 3863000 | G59: 4028000 | H59: 3506000 | I59: 3274000 | J59: 2911000 | K59: 3667000
A60: Gross Profit | B60: 10460000 | C60: 10603000 | D60: 7929000 | E60: 4347000 | F60: 2868000 | G60: 2447000 | H60: 1823000 | I60: 998000 | J60: 1080000 | K60: 1839000
A61: Selling General & Admin | B61: 2352000 | C61: 2336000 | D61: 1448000 | E61: 995000 | F61: 750000 | G61: 562000 | H61: 511000 | I61: 460000 | J61: 482000 | K61: 604000
A62: Depreciation & Amortization | B62: 1869000 | C62: 2100000 | D62: 0 | E62: 0 | F62: 0 | G62: 0 | H62: 0 | I62: 0 | J62: 3000 | K62: 14000
A63: Research & Development | B63: 5872000 | C63: 5005000 | D63: 2845000 | E63: 1983000 | F63: 1547000 | G63: 1434000 | H63: 1160000 | I63: 1008000 | J63: 947000 | K63: 1072000
A64: Restruct Remediation & Impair | B64: 0 | C64: 0 | D64: 0 | E64: 0 | F64: 0 | G64: 0 | H64: 0 | I64: -10000 | J64: 129000 | K64: 304000
A65: Other Operating Expense | B65: -34000 | C65: -102000 | D65: -12000 | E65: 0 | F65: -60000 | G65: 0 | H65: -52000 | I65: -88000 | J65: 0 | K65: 0
A66: Total Indirect Operating Costs | B66: 10059000 | C66: 9339000 | D66: 4281000 | E66: 2978000 | F66: 2237000 | G66: 1996000 | H66: 1619000 | I66: 1370000 | J66: 1561000 | K66: 1994000
A67: Operating Income | B67: 401000 | C67: 1264000 | D67: 3648000 | E67: 1369000 | F67: 631000 | G67: 451000 | H67: 204000 | I67: -372000 | J67: -481000 | K67: -155000
A68: Interest Income | B68: 100000 | C68: -23000 | D68: -26000 | E68: -39000 | F68: -79000 | G68: -121000 | H68: -120000 | I68: -154000 | J68: -160000 | K68: -174000
... A73: Taxation | B73: -346000 | C73: -122000 | D73: 513000 | E73: -1210000 | F73: 31000 | G73: -9000 | H73: 19000 | I73: 39000 | J73: 14000 | K73: 5000
A74: Equity Earnings | B74: 15000 | C74: 14000 | D74: 6000 | E74: 5000 | F74: 0 | G74: -2000 | H74: -7000 | I74: -10000 | J74: - | K74: -
A75: Extraordinary Items | B75: 0 | C75: 0 | D75: 0 | E75: 0 | F75: 0 | G75: 0 | H75: 0 | I75: 0 | J75: 0 | K75: 0
A76: Accounting Changes | B76: 0 | C76: 0 | D76: 0 | E76: 0 | F76: 0 | G76: 0 | H76: 0 | I76: 0 | J76: 0 | K76: 0
A77: Net Income | B77: 854000 | C77: 1320000 | D77: 3162000 | E77: 2490000 | F77: 341000 | G77: 337000 | H77: 43000 | I77: -497000 | J77: -660000 | K77: -403000
A78: Preference Dividends & Similar | B78: 0 | C78: 0 | D78: 0 | E78: 0 | F78: 0 | G78: 0 | H78: 0 | I78: 0 | J78: 0 | K78: 0
A79: Net Income to Common | B79: 854000 | C79: 1320000 | D79: 3162000 | E79: 2490000 | F79: 341000 | G79: 337000 | H79: 43000 | I79: -497000 | J79: -660000 | K79: -403000
A80: Average Shares Basic | B80: 1614000 | C80: 1561000 | D80: 1213000 | E80: 1184000 | F80: 1091000 | G80: 982000 | H80: 952000 | I80: 835000 | J80: 783000 | K80: 768000
A81: EPS Net Basic | B81: 0.53 | C81: 0.85 | D81: 2.61 | E81: 2.1 | F81: 0.31 | G81: 0.34 | H81: 0.04 | I81: -0.6 | J81: -0.84 | K81: -0.53
A82: EPS Continuing Basic | B82: 0.53 | C82: 0.85 | D82: 2.61 | E82: 2.1 | F82: 0.31 | G82: 0.34 | H82: 0.04 | I82: -0.6 | J82: -0.84 | K82: -0.52
A83: Average Shares Diluted | B83: 1625000 | C83: 1571000 | D83: 1229000 | E83: 1207000 | F83: 1120000 | G83: 1064000 | H83: 1039000 | I83: 835000 | J83: 783000 | K83: 768000
A84: EPS Net Diluted | B84: 0.53 | C84: 0.84 | D84: 2.57 | E84: 2.06 | F84: 0.3 | G84: 0.32 | H84: 0.04 | I84: -0.6 | J84: -0.84 | K84: -0.53
A85: EPS Continuing Diluted | B85: 0.53 | C85: 0.84 | D85: 2.57 | E85: 2.06 | F85: 0.3 | G85: 0.32 | H85: 0.04 | I85: -0.6 | J85: -0.84 | K85: -0.52
A86: Shares Outstanding | B86: 1616000 | C86: 1612000 | D86: 1207000 | E86: 1211000 | F86: 1170000 | G86: 1005000 | H86: 967000 | I86: 935000 | J86: 792000 | K86: 776000
A90: EBIT/TA | B90: =B67/B32 -> 0.0059070487 | C90: =C67/C32 -> 0.018703759 | D90: =D67/D32 -> 0.29374346 | E90: =E67/E32 -> 0.15275608 | F90: =F67/F32 -> 0.10467817 | G90: =G67/G32 -> 0.098990342 | H90: =H67/H32 -> 0.057627119 | I90: =I67/I32 -> -0.11201445 | ... K90: =K67/K32 -> -0.041146801
A91: NI/TA | B91: =B77/B32 -> 0.012580099 | C91: =C77/C32 -> 0.019532406 | D91: =D77/D32 -> 0.25460987 | E91: =E77/E32 -> 0.27783977 | F91: =F77/F32 -> 0.056569343 | G91: =G77/G32 -> 0.073968393 | H91: =H77/H32 -> 0.012146893 | I91: =I77/I32 -> -0.14965372 | ... K91: =K77/K32 -> -0.10698168
A92: NI/TE | B92: =B77/B48 -> 0.015279468 | C92: =C77/C48 -> 0.024109589 | D92: =D77/D48 -> 0.42176871 | E92: =E77/E48 -> 0.426589 | F92: =F77/F48 -> 0.12062257 | G92: =G77/G48 -> 0.26619273 | H92: =H77/H48 -> 0.070376432 | I92: =I77/I48 -> -1.1947115 | ... K92: =K77/K48 -> -2.1550802
A93: Gross margin | B93: =B60/B58 -> 0.46119929 | C93: =C60/C58 -> 0.44926062 | D93: =D60/D58 -> 0.48247536 | E93: =E60/E58 -> 0.44525248 | F93: =F60/F58 -> 0.42608825 | G93: =G60/G58 -> 0.37791506 | H93: =H60/H58 -> 0.34209045 | I93: =I60/I58 -> 0.23361423 | ... K93: =K60/K58 -> 0.33399927
A94: RD/Sales | B94: =B63/B58 -> 0.25890653 | C94: =C63/C58 -> 0.21206729 | D94: =D63/D58 -> 0.17311671 | E94: =E63/E58 -> 0.2031138 | F94: =F63/F58 -> 0.22983212 | G94: =G63/G58 -> 0.22146718 | H94: =H63/H58 -> 0.21767686 | I94: =I63/I58 -> 0.23595506 | ... K94: =K63/K58 -> 0.19469669
A95: NI/Revenue | B95: =B77/B58 -> 0.037654321 | C95: =C77/C58 -> 0.055929833 | D95: =D77/D58 -> 0.19240599 | E95: =E77/E58 -> 0.25504456 | F95: =F77/F58 -> 0.05066112 | G95: =G77/G58 -> 0.052046332 | H95: =H77/H58 -> 0.0080690561 | I95: =I77/I58 -> -0.11633895 | ... K95: =K77/K58 -> -0.07319288
A96: COGS/Sales | B96: =B59/B58 -> 0.53880071 | C96: =C59/C58 -> 0.55073938 | D96: =D59/D58 -> 0.51752464 | E96: =E59/E58 -> 0.55474752 | F96: =F59/F58 -> 0.57391175 | G96: =G59/G58 -> 0.62208494 | H96: =H59/H58 -> 0.65790955 | I96: =I59/I58 -> 0.76638577 | ... K96: =K59/K58 -> 0.66600073
A97: SGA/Sales | B97: =B61/B58 -> 0.1037037 | C97: =C61/C58 -> 0.098978857 | D97: =D61/D58 -> 0.088110016 | E97: =E61/E58 -> 0.10191539 | F97: =F61/F58 -> 0.11142475 | G97: =G61/G58 -> 0.086795367 | H97: =H61/H58 -> 0.095890411 | I97: =I61/I58 -> 0.1076779 | ... K97: =K61/K58 -> 0.10969851
A98: AR/Sales | B98: =B19/B58 -> 0.23703704 | C98: =C19/C58 -> 0.1748231 | D98: =D19/D58 -> 0.16465863 | E98: =E19/E58 -> 0.21161528 | F98: =F19/F58 -> 0.27618482 | G98: =G19/G58 -> 0.19073359 | H98: =H19/H58 -> 0.075060987 | I98: =I19/I58 -> 0.072799625 | ... K98: =K19/K58 -> 0.1485652
A100: sales Growth | C100: =(C58-B58)/B58 -> 0.040608466 | D100: =(D58-C58)/C58 -> -0.30367357 | E100: =(E58-D58)/D58 -> -0.40592674 | F100: =(F58-E58)/E58 -> -0.31056028 | G100: =(G58-F58)/F58 -> -0.038032982 | H100: =(H58-G58)/G58 -> -0.17698842 | I100: =(I58-H58)/H58 -> -0.19834866 | J100: =(J58-I58)/I58 -> -0.065777154 | K100: =(K58-J58)/J58 -> 0.37960411
A103: Interest(on avg Debt) | B103: =(B71*-1)/AVERAGE(B39:C39) -> -0.043977055 | C103: =(C71*-1)/AVERAGE(C39:D39) -> 0.064829822 | D103: =(D71*-1)/AVERAGE(D39:E39) -> -0.12688822 | E103: =(E71*-1)/AVERAGE(E39:F39) -> 0.23039216 | F103: =(F71*-1)/AVERAGE(F39:G39) -> 0.32375 | G103: =(G71*-1)/AVERAGE(G39:H39) -> 0.099220992 | H103: =(H71*-1)/AVERAGE(H39:I39) -> 0.097826087 | I103: =(I71*-1)/AVERAGE(I39:J39) -> 0.043841938 | ... K103: =(K71*-1)/AVERAGE(K39:L39) -> 0.11941032

Sheet INTEL
A1: Intel Corp (NMS: INTC)
A3: Report Date | B3: 12/28/2024 | C3: 12/30/2023 | D3: 12/31/2022 | E3: 12/25/2021 | F3: 12/26/2020 | G3: 12/28/2019 | H3: 12/29/2018 | I3: 12/30/2017 | J3: 12/31/2016 | K3: 12/26/2015
A4: Currency | B4: USD | C4: USD | D4: USD | E4: USD | F4: USD | G4: USD | H4: USD | I4: USD | J4: USD | K4: USD
A5: Audit Status | B5: Not Qualified | C5: Not Qualified | D5: Not Qualified | E5: Not Qualified | F5: Not Qualified | G5: Not Qualified | H5: Not Qualified | I5: Not Qualified | J5: Not Qualified | K5: Not Qualified
A6: Consolidated | B6: Yes | C6: Yes | D6: Yes | E6: Yes | F6: Yes | G6: Yes | H6: Yes | I6: Yes | J6: Yes | K6: Yes
A7: Scale | B7: Millions | C7: Millions | D7: Millions | E7: Millions | F7: Millions | G7: Millions | H7: Millions | I7: Millions | J7: Millions | K7: Millions
A8: Cash & Equivalents | B8: 8249 | C8: 7079 | D8: 11144 | E8: 4827 | F8: 5865 | G8: 4194 | H8: 3019 | I8: 3433 | J8: 5560 | K8: 15308
A9: Short Term Investments | B9: 13813 | C9: 17955 | D9: 17194 | E9: 23586 | F9: 18030 | G9: 8929 | H9: 8631 | I9: 10569 | J9: 11539 | K9: 10005
A10: Cash & Equivs & ST Investments | B10: 22062 | C10: 25034 | D10: 28338 | E10: 28413 | F10: 23895 | G10: 13123 | H10: 11650 | I10: 14002 | J10: 17099 | K10: 25313
A11: Receivables (ST) | B11: 3478 | C11: 3402 | D11: 4133 | E11: 9457 | F11: 6782 | G11: 7659 | H11: 6722 | I11: 5607 | J11: 4690 | K11: 4787
A12: Inventories | B12: 12198 | C12: 11127 | D12: 13224 | E12: 10776 | F12: 8427 | G12: 8744 | H12: 7253 | I12: 6983 | J12: 5553 | K12: 5167
A13: Current Tax Assets | B13: - | C13: - | D13: - | E13: - | F13: - | G13: - | H13: - | I13: - | J13: - | K13: 2036
A14: Assets Held for Sale (ST) | B14: - | C14: - | D14: 45 | E14: 6942 | F14: 5400 | G14: - | H14: - | I14: - | J14: 5210 | K14: -
A15: Other Current Assets | B15: 9586 | C15: 3706 | D15: 4667 | E15: 2130 | F15: 2745 | G15: 1713 | H15: 3162 | I15: 2908 | J15: 2956 | K15: 3053
A16: Total Current Assets | B16: 47324 | C16: 43269 | D16: 50407 | E16: 57718 | F16: 47249 | G16: 31239 | H16: 28787 | I16: 29500 | J16: 35508 | K16: 40356
A17: Gross Property Plant & Equip | B17: 210112 | C17: 194657 | D17: 174246 | E17: 148539 | F17: 134229 | G17: 128707 | H17: 114318 | I17: 100395 | J17: 90105 | K17: 83396
A18: Accumulated Depreciation | B18: 102193 | C18: 98010 | D18: 93386 | E18: 85294 | F18: 77645 | G18: 73321 | H18: 65342 | I18: 59286 | J18: 53934 | K18: 51538
A19: Net Property Plant & Equip | B19: 107919 | C19: 96647 | D19: 80860 | E19: 63245 | F19: 56584 | G19: 55386 | H19: 48976 | I19: 41109 | J19: 36171 | K19: 31858
A20: Receivables (LT) | B20: - | C20: - | D20: - | E20: - | F20: - | G20: 554 | H20: 479 | I20: 860 | J20: 299 | K20: 960
A21: Long Term Investments | B21: 5383 | C21: 5829 | D21: 5912 | E21: 7138 | F21: 7344 | G21: 7243 | H21: 9430 | I21: 12404 | J21: 15322 | K21: 12374
A22: Intangible Assets | B22: 28384 | C22: 32180 | D22: 33609 | E22: 34233 | F22: 35997 | G22: 37103 | H22: 36349 | I22: 37134 | J22: 23593 | K22: 15265
A23: Prepayments (LT) | B23: - | C23: - | D23: - | E23: - | F23: 1502 | G23: 1641 | H23: 1507 | I23: 714 | J23: 347 | K23: 623
A24: Deferred LT Assets | B24: - | C24: - | D24: - | E24: - | F24: 1232 | G24: 1209 | H24: 1122 | I24: 840 | J24: 907 | K24: 600
A25: Other Assets | B25: 7475 | C25: 13647 | D25: 11315 | E25: 6072 | F25: 3183 | G25: 2149 | H25: 1313 | I25: 688 | J25: 1180 | K25: 1029
A26: Total Assets | B26: 196485 | C26: 191572 | D26: 182103 | E26: 168406 | F26: 153091 | G26: 136524 | H26: 127963 | I26: 123249 | J26: 113327 | K26: 103065
A27: Accounts Payable & Accrued Exps | B27: 30000 | C27: 24516 | D27: 25537 | E27: 22871 | F27: 22250 | G27: 18617 | H27: 15365 | I27: 13989 | J27: 12030 | K27: 10845
A28: Accounts Payable | B28: 12556 | C28: 8578 | D28: 9595 | E28: 5747 | F28: 5581 | G28: 4128 | H28: 3824 | I28: 2928 | J28: 2475 | K28: 2063
A29: Accrued Expenses | B29: 17444 | C29: 15938 | D29: 15942 | E29: 17124 | F29: 16669 | G29: 14489 | H29: 11541 | I29: 11061 | J29: 9555 | K29: 8782
A30: Current Debt | B30: 3729 | C30: 2288 | D30: 4367 | E30: 4591 | F30: 2504 | G30: 3693 | H30: 1261 | I30: 1776 | J30: 4634 | K30: 2634
A31: Other Current Liabilities | B31: 1937 | C31: 1249 | D31: 2251 | E31: 0 | F31: 0 | G31: 0 | H31: 0 | I31: 1656 | J31: 3638 | K31: 2188
A32: Total Current Liabilities | B32: 35666 | C32: 28053 | D32: 32155 | E32: 27462 | F32: 24754 | G32: 22310 | H32: 16626 | I32: 17421 | J32: 20302 | K32: 15667
A33: LT Debt & Leases | B33: 46282 | C33: 46978 | D33: 37684 | E33: 33510 | F33: 33897 | G33: 25308 | H33: 25098 | I33: 25037 | J33: 20649 | K33: 20036
A34: Deferred LT Liabilities | B34: - | C34: - | D34: 202 | E34: 2667 | F34: 3843 | G34: 2044 | H34: 1665 | I34: 3046 | J34: 1730 | K34: 2539
A35: Minority Interests | B35: 5762 | C35: 4375 | D35: 1863 | E35: 0 | F35: 0 | G35: 0 | H35: 0 | I35: 0 | J35: 0 | K35: 0
A36: Other Liabilities | B36: 9505 | C36: 6576 | D36: 8776 | E36: 9376 | F36: 9559 | G36: 9203 | H36: 9592 | I36: 7860 | J36: 3538 | K36: 2841
A37: Total Liabilities | B37: 97215 | C37: 85982 | D37: 80680 | E37: 73015 | F37: 72053 | G37: 58865 | H37: 52981 | I37: 53364 | J37: 46219 | K37: 41083
A38: Temporary Equity | B38: - | C38: - | D38: - | E38: - | F38: - | G38: 155 | H38: 419 | I38: 866 | J38: 882 | K38: 897
A39: Common Share Capital | B39: 4.33 | C39: 4.228 | D39: 31580 | E39: 28006 | F39: 25556 | G39: 25261 | H39: 25365 | I39: 26074 | J39: 25373 | K39: 23411
A40: Additional Paid-In Capital | B40: 50944.67 | C40: 36644.772 | D40: - | E40: - | F40: - | G40: - | H40: - | I40: - | J40: - | K40: -
A41: Retained Earnings | B41: 49032 | C41: 69156 | D41: 70405 | E41: 68265 | F41: 56233 | G41: 53523 | H41: 50172 | I41: 42083 | J41: 40747 | K41: 37614
A42: Accum Other Comprehensive Income | B42: -711 | C42: -215 | D42: -562 | E42: -880 | F42: -751 | G42: -1280 | H42: -974 | I42: 862 | J42: 106 | K42: 60
A43: For Curr Trans (BS) | B43: 4 | C43: 5 | D43: - | E43: - | F43: - | G43: - | H43: - | I43: -9 | J43: -519 | K43: -515
A44: Other Equity | B44: -4 | C44: -5 | D44: 0 | E44: 0 | F44: 0 | G44: 0 | H44: 0 | I44: 9 | J44: 519 | K44: 515
A45: Total Equity | B45: 99270 | C45: 105590 | D45: 101423 | E45: 95391 | F45: 81038 | G45: 77659 | H45: 74982 | I45: 69885 | J45: 67108 | K45: 61982
A46: Total Liabilities & Equity | B46: 196485 | C46: 191572 | D46: 182103 | E46: 168406 | F46: 153091 | G46: 136524 | H46: 127963 | I46: 123249 | J46: 113327 | K46: 103065
A50: Standardized Annual Income Statement
A51: Report Date | B51: 12/28/2024 | C51: 12/30/2023 | D51: 12/31/2022 | E51: 12/25/2021 | F51: 12/26/2020 | G51: 12/28/2019 | H51: 12/29/2018 | I51: 12/30/2017 | J51: 12/31/2016 | K51: 12/26/2015
A52: Currency | B52: USD | C52: USD | D52: USD | E52: USD | F52: USD | G52: USD | H52: USD | I52: USD | J52: USD | K52: USD
A53: Audit Status | B53: Not Qualified | C53: Not Qualified | D53: Not Qualified | E53: Not Qualified | F53: Not Qualified | G53: Not Qualified | H53: Not Qualified | I53: Not Qualified | J53: Not Qualified | K53: Not Qualified
A54: Consolidated | B54: Yes | C54: Yes | D54: Yes | E54: Yes | F54: Yes | G54: Yes | H54: Yes | I54: Yes | J54: Yes | K54: Yes
A55: Scale | B55: Millions | C55: Millions | D55: Millions | E55: Millions | F55: Millions | G55: Millions | H55: Millions | I55: Millions | J55: Millions | K55: Millions
A56: Sales Revenue | B56: 53101 | C56: 54228 | D56: - | E56: - | F56: - | G56: - | H56: - | I56: - | J56: - | K56: -
A57: Total Revenue | B57: 53101 | C57: 54228 | D57: 63054 | E57: 79024 | F57: 77867 | G57: 71965 | H57: 70848 | I57: 62761 | J57: 59387 | K57: 55355
A58: Direct Costs | B58: 35756 | C58: 32517 | D58: 36188 | E58: 35209 | F58: 34255 | G58: 29825 | H58: 27111 | I58: 23692 | J58: 23196 | K58: 20676
A59: Gross Profit | B59: 17345 | C59: 21711 | D59: 26866 | E59: 43815 | F59: 43612 | G59: 42140 | H59: 43737 | I59: 39069 | J59: 36191 | K59: 34679
A60: Selling General & Admin | B60: 5507 | C60: 5634 | D60: 7002 | E60: 6543 | F60: 6180 | G60: 6150 | H60: 6750 | I60: 7474 | J60: 8397 | K60: 7930
A61: Depreciation & Amortization | B61: - | C61: - | D61: - | E61: - | F61: - | G61: 200 | H61: 200 | I61: 177 | J61: 294 | K61: 265
A62: Research & Development | B62: 16546 | C62: 16046 | D62: 17528 | E62: 15190 | F62: 13556 | G62: 13362 | H62: 13543 | I62: 13098 | J62: 12740 | K62: 12128
A63: Restruct Remediation & Impair | B63: 6112 | C63: 267 | D63: 2 | E63: 2626 | F63: 198 | G63: 393 | H63: -72 | I63: 384 | J63: 1886 | K63: 354
A64: Other Operating Expense | B64: 858 | C64: -329 | D64: 0 | E64: 0 | F64: 0 | G64: 0 | H64: 0 | I64: 0 | J64: 0 | K64: 0
A65: Total Indirect Operating Costs | B65: 29023 | C65: 21618 | D65: 24532 | E65: 24359 | F65: 19934 | G65: 20105 | H65: 20421 | I65: 21133 | J65: 23317 | K65: 20677
A66: Operating Income | B66: -11678 | C66: 93 | D66: 2334 | E66: 19456 | F66: 23678 | G66: 22035 | H66: 23316 | I66: 17936 | J66: 12874 | K66: 14002
A67: Interest Income | B67: 211 | C67: 629 | D67: 1166 | E67: -482 | F67: -504 | G67: 484 | H67: 126 | I67: -235 | J67: -444 | K67: -105
A68: Gains on Sale of Assets | B68: -126 | C68: -19 | D68: 4268 | E68: 2729 | F68: 1904 | G68: 1539 | H68: -125 | I68: 2815 | J68: 470 | K68: 358
A69: Other Non-Operating Income | B69: 15 | C69: 0 | D69: 0 | E69: 0 | F69: 0 | G69: 0 | H69: 0 | I69: 68 | J69: 74 | K69: 52
A70: Total Non-Operating Income | B70: 100 | C70: 610 | D70: 5434 | E70: 2247 | F70: 1400 | G70: 2023 | H70: 1 | I70: 2648 | J70: 100 | K70: 305
A71: Earnings Before Tax | B71: -11578 | C71: 703 | D71: 7768 | E71: 21703 | F71: 25078 | G71: 24058 | H71: 23317 | I71: 20584 | J71: 12974 | K71: 14307
A72: Taxation | B72: 8023 | C72: -913 | D72: -249 | E72: 1835 | F72: 4179 | G72: 3010 | H72: 2264 | I72: 10751 | J72: 2620 | K72: 2792
A73: Earnings After Tax | B73: -19601 | C73: - | D73: - | E73: - | F73: - | G73: - | H73: - | I73: - | J73: - | K73: -
A74: Minority Interests | B74: -477 | C74: -14 | D74: 3 | E74: - | F74: - | G74: - | H74: - | I74: - | J74: - | K74: -
A75: Equity Earnings | B75: 368 | C75: 59 | D75: - | E75: - | F75: - | G75: - | H75: - | I75: -232 | J75: -38 | K75: -95
A76: Extraordinary Items | B76: 0 | C76: 0 | D76: 0 | E76: 0 | F76: 0 | G76: 0 | H76: 0 | I76: 0 | J76: 0 | K76: 0
A77: Accounting Changes | B77: 0 | C77: 0 | D77: 0 | E77: 0 | F77: 0 | G77: 0 | H77: 0 | I77: 0 | J77: 0 | K77: 0
A78: Net Income | B78: -18756 | C78: 1689 | D78: 8014 | E78: 19868 | F78: 20899 | G78: 21048 | H78: 21053 | I78: 9601 | J78: 10316 | K78: 11420
A79: Preference Dividends & Similar | B79: 0 | C79: 0 | D79: 0 | E79: 0 | F79: 0 | G79: 0 | H79: 0 | I79: 0 | J79: 0 | K79: 0
A80: Net Income to Common | B80: -18756 | C80: 1689 | D80: 8014 | E80: 19868 | F80: 20899 | G80: 21048 | H80: 21053 | I80: 9601 | J80: 10316 | K80: 11420
A81: Average Shares Basic | B81: 4280 | C81: 4190 | D81: 4108 | E81: 4059 | F81: 4199 | G81: 4417 | H81: 4611 | I81: 4701 | J81: 4730 | K81: 4742
A82: EPS Net Basic | B82: -4.38 | C82: 0.4 | D82: 1.95 | E82: 4.89 | F82: 4.98 | G82: 4.77 | H82: 4.57 | I82: 2.04 | J82: 2.18 | K82: 2.41
A83: EPS Continuing Basic | B83: -4.38 | C83: 0.4 | D83: 1.95 | E83: 4.89 | F83: 4.98 | G83: 4.77 | H83: 4.57 | I83: 2.04 | J83: 2.18 | K83: 2.41
A84: Average Shares Diluted | B84: 4280 | C84: 4212 | D84: 4123 | E84: 4090 | F84: 4232 | G84: 4473 | H84: 4701 | I84: 4835 | J84: 4875 | K84: 4894
A85: EPS Net Diluted | B85: -4.38 | C85: 0.4 | D85: 1.94 | E85: 4.86 | F85: 4.94 | G85: 4.71 | H85: 4.48 | I85: 1.99 | J85: 2.12 | K85: 2.33
A86: EPS Continuing Diluted | B86: -4.38 | C86: 0.4 | D86: 1.94 | E86: 4.86 | F86: 4.94 | G86: 4.71 | H86: 4.48 | I86: 1.99 | J86: 2.12 | K86: 2.33
A87: Shares Outstanding | B87: 433000 | C87: 422800 | D87: 413700 | E87: 4070000 | F87: 4062000 | G87: 4290000 | H87: 451600 | I87: 468700 | J87: 473000 | K87: 472500
A91: EBIT/TA | B91: =B66/B26 -> -0.059434562 | C91: =C66/C26 -> 0.00048545716 | D91: =D66/D26 -> 0.012816922 | E91: =E66/E26 -> 0.11553033 | F91: =F66/F26 -> 0.15466618 | G91: =G66/G26 -> 0.16140019 | H91: =H66/H26 -> 0.18220892 | I91: =I66/I26 -> 0.14552654 | ... K91: =K66/K26 -> 0.13585601
A92: NI/TA | B92: =B78/B26 -> -0.095457669 | C92: =C78/C26 -> 0.0088165285 | D92: =D78/D26 -> 0.044008061 | E92: =E78/E26 -> 0.11797679 | F92: =F78/F26 -> 0.13651358 | G92: =G78/G26 -> 0.1541707 | H92: =H78/H26 -> 0.16452412 | I92: =I78/I26 -> 0.077899212 | ... K92: =K78/K26 -> 0.11080386
A93: NI/TE | B93: =B78/B45 -> -0.18893926 | C93: =C78/C45 -> 0.015995833 | D93: =D78/D45 -> 0.079015608 | E93: =E78/E45 -> 0.20827961 | F93: =F78/F45 -> 0.25789136 | G93: =G78/G45 -> 0.27103105 | H93: =H78/H45 -> 0.28077405 | I93: =I78/I45 -> 0.13738284 | ... K93: =K78/K45 -> 0.18424704
A94: Gross margin | B94: =B59/B57 -> 0.32664168 | C94: =C59/C57 -> 0.40036513 | D94: =D59/D57 -> 0.42607923 | E94: =E59/E57 -> 0.55445181 | F94: =F59/F57 -> 0.56008322 | G94: =G59/G57 -> 0.58556243 | H94: =H59/H57 -> 0.6173357 | I94: =I59/I57 -> 0.62250442 | ... K94: =K59/K57 -> 0.62648361
A95: RD/Sales | B95: =B62/B57 -> 0.31159489 | C95: =C62/C57 -> 0.2958988 | D95: =D62/D57 -> 0.27798395 | E95: =E62/E57 -> 0.19222009 | F95: =F62/F57 -> 0.17409172 | G95: =G62/G57 -> 0.18567359 | H95: =H62/H57 -> 0.19115571 | I95: =I62/I57 -> 0.20869648 | ... K95: =K62/K57 -> 0.21909493
A96: NI/Revenue | B96: =B78/B57 -> -0.35321369 | C96: =C78/C57 -> 0.031146271 | D96: =D78/D57 -> 0.12709741 | E96: =E78/E57 -> 0.25141729 | F96: =F78/F57 -> 0.26839354 | G96: =G78/G57 -> 0.29247551 | H96: =H78/H57 -> 0.29715729 | I96: =I78/I57 -> 0.15297717 | ... K96: =K78/K57 -> 0.20630476
A97: COGS/Sales | B97: =B58/B57 -> 0.67335832 | C97: =C58/C57 -> 0.59963487 | D97: =D58/D57 -> 0.57392077 | E97: =E58/E57 -> 0.44554819 | F97: =F58/F57 -> 0.43991678 | G97: =G58/G57 -> 0.41443757 | H97: =H58/H57 -> 0.3826643 | I97: =I58/I57 -> 0.37749558 | ... K97: =K58/K57 -> 0.37351639
A98: SGA/Sales | B98: =B60/B57 -> 0.10370803 | C98: =C60/C57 -> 0.10389467 | D98: =D60/D57 -> 0.11104767 | E98: =E60/E57 -> 0.082797631 | F98: =F60/F57 -> 0.079366099 | G98: =G60/G57 -> 0.085458209 | H98: =H60/H57 -> 0.09527439 | I98: =I60/I57 -> 0.11908669 | ... K98: =K60/K57 -> 0.14325716
A99: AR/Sales | B99: =B11/B57 -> 0.065497825 | C99: =C11/C57 -> 0.062735118 | D99: =D11/D57 -> 0.065546991 | E99: =E11/E57 -> 0.1196725 | F99: =F11/F57 -> 0.08709723 | G99: =G11/G57 -> 0.10642674 | H99: =H11/H57 -> 0.094879178 | I99: =I11/I57 -> 0.089338921 | ... K99: =K11/K57 -> 0.086478186
A101: sales Growth | C101: =(C57-B57)/B57 -> 0.021223706 | D101: =(D57-C57)/C57 -> 0.16275725 | E101: =(E57-D57)/D57 -> 0.25327497 | F101: =(F57-E57)/E57 -> -0.014641122 | G101: =(G57-F57)/F57 -> -0.075795908 | H101: =(H57-G57)/G57 -> -0.015521434 | I101: =(I57-H57)/H57 -> -0.11414578 | J101: =(J57-I57)/I57 -> -0.0537595 | K101: =(K57-J57)/J57 -> -0.067893647
A103: Interest(on avg Debt) | B103: =(B70*-1)/AVERAGE(B33:C33) -> -0.0021445421 | C103: =(C70*-1)/AVERAGE(C33:D33) -> -0.014410243 | D103: =(D70*-1)/AVERAGE(D33:E33) -> -0.15265331 | E103: =(E70*-1)/AVERAGE(E33:F33) -> -0.066669634 | F103: =(F70*-1)/AVERAGE(F33:G33) -> -0.047293303 | G103: =(G70*-1)/AVERAGE(G33:H33) -> -0.080268222 | H103: =(H70*-1)/AVERAGE(H33:I33) -> -3.9892291e-05 | I103: =(I70*-1)/AVERAGE(I33:J33) -> -0.11592173 | ... K103: =(K70*-1)/AVERAGE(K33:L33) -> -0.015222599

Sheet QUALCOMM
A4: Powered by Clearbit
A5: Qualcomm Inc (NMS: QCOM)
A7: Exchange rate used is that of the Year End reported date
A10: Standardized Annual Balance Sheet
A11: Report Date | B11: 09/29/2024 | C11: 09/24/2023 | D11: 09/25/2022 | E11: 09/26/2021 | F11: 09/27/2020 | G11: 09/29/2019 | H11: 09/30/2018 | I11: 09/24/2017 | J11: 09/25/2016 | K11: 09/27/2015
A12: Currency | B12: USD | C12: USD | D12: USD | E12: USD | F12: USD | G12: USD | H12: USD | I12: USD | J12: USD | K12: USD
A13: Audit Status | B13: Not Qualified | C13: Not Qualified | D13: Not Qualified | E13: Not Qualified | F13: Not Qualified | G13: Not Qualified | H13: Not Qualified | I13: Not Qualified | J13: Not Qualified | K13: Not Qualified
A14: Consolidated | B14: Yes | C14: Yes | D14: Yes | E14: Yes | F14: Yes | G14: Yes | H14: Yes | I14: Yes | J14: Yes | K14: Yes
A15: Scale | B15: Thousands | C15: Thousands | D15: Thousands | E15: Thousands | F15: Thousands | G15: Thousands | H15: Thousands | I15: Thousands | J15: Thousands | K15: Thousands
A16: Cash & Equivalents | B16: 7849000 | C16: 8450000 | D16: 2773000 | E16: 7116000 | F16: 6707000 | G16: 11839000 | H16: 11777000 | I16: 35029000 | J16: 5946000 | K16: 7560000
A17: Short Term Investments | B17: 5451000 | C17: 2874000 | D17: 3609000 | E17: 5298000 | F17: 4507000 | G17: 421000 | H17: 311000 | I17: 2279000 | J17: 12702000 | K17: 9761000
A18: Cash & Equivs & ST Investments | B18: 13300000 | C18: 11324000 | D18: 6382000 | E18: 12414000 | F18: 11214000 | G18: 12260000 | H18: 12088000 | I18: 37308000 | J18: 18648000 | K18: 17321000
A19: Receivables (ST) | B19: 3929000 | C19: 3183000 | D19: 5643000 | E19: 3579000 | F19: 4003000 | G19: 2471000 | H19: 2904000 | I19: 3632000 | J19: 2219000 | K19: 1964000
A20: Inventories | B20: 6423000 | C20: 6422000 | D20: 6341000 | E20: 3228000 | F20: 2598000 | G20: 1400000 | H20: 1693000 | I20: 2035000 | J20: 1556000 | K20: 1492000
A21: Current Tax Assets | B21: 0 | C21: 0 | D21: 0 | E21: 0 | F21: 0 | G21: 0 | H21: 0 | I21: 0 | J21: 0 | K21: 635000
A22: Assets Held for Sale (ST) | B22: 0 | C22: 341000 | D22: 733000 | E22: 0 | F22: 0 | G22: 0 | H22: 0 | I22: 0 | J22: 0 | K22: 0
A23: Other Current Assets | B23: 1579000 | C23: 1194000 | D23: 1625000 | E23: 854000 | F23: 704000 | G23: 634000 | H23: 699000 | I23: 618000 | J23: 558000 | K23: 687000
A24: Total Current Assets | B24: 25231000 | C24: 22464000 | D24: 20724000 | E24: 20075000 | F24: 18519000 | G24: 16765000 | H24: 17384000 | I24: 43593000 | J24: 22981000 | K24: 22099000
A25: Gross Property Plant & Equip | B25: 13541000 | C25: 12710000 | D25: 11770000 | E25: 10454000 | F25: 8845000 | G25: 7648000 | H25: 7461000 | I25: 7419000 | J25: 6040000 | K25: 5894000
A26: Accumulated Depreciation | B26: 8876000 | C26: 7668000 | D26: 6602000 | E26: 5895000 | F26: 5134000 | G26: 4567000 | H26: 4486000 | I26: 4203000 | J26: 3734000 | K26: 3360000
A27: Net Property Plant & Equip | B27: 4665000 | C27: 5042000 | D27: 5168000 | E27: 4559000 | F27: 3711000 | G27: 3081000 | H27: 2975000 | I27: 3216000 | J27: 2306000 | K27: 2534000
... A52: Total Liabilities & Equity | B52: 55154000 | C52: 51040000 | D52: 49014000 | E52: 41240000 | F52: 35594000 | G52: 32957000 | H52: 32686000 | I52: 65486000 | J52: 52359000 | K52: 50796000
A57: Standardized Annual Income Statement
A58: Report Date | B58: 09/29/2024 | C58: 09/24/2023 | D58: 09/25/2022 | E58: 09/26/2021 | F58: 09/27/2020 | G58: 09/29/2019 | H58: 09/30/2018 | I58: 09/24/2017 | J58: 09/25/2016 | K58: 09/27/2015
A59: Currency | B59: USD | C59: USD | D59: USD | E59: USD | F59: USD | G59: USD | H59: USD | I59: USD | J59: USD | K59: USD
A60: Audit Status | B60: Not Qualified | C60: Not Qualified | D60: Not Qualified | E60: Not Qualified | F60: Not Qualified | G60: Not Qualified | H60: Not Qualified | I60: Not Qualified | J60: Not Qualified | K60: Not Qualified
A61: Consolidated | B61: Yes | C61: Yes | D61: Yes | E61: Yes | F61: Yes | G61: Yes | H61: Yes | I61: Yes | J61: Yes | K61: Yes
A62: Scale | B62: Thousands | C62: Thousands | D62: Thousands | E62: Thousands | F62: Thousands | G62: Thousands | H62: Thousands | I62: Thousands | J62: Thousands | K62: Thousands
A63: Sales Revenue | B63: 38962000 | C63: 30028000 | D63: 37171000 | E63: 26741000 | F63: 16298000 | G63: 14611000 | H63: 17400000 | I63: 16647000 | J63: 15467000 | K63: 17079000
A64: Other Revenue | B64: - | C64: 5792000 | D64: 7029000 | E64: 6825000 | F64: 7233000 | G64: 9662000 | H64: 5332000 | I64: 5644000 | J64: 8087000 | K64: 8202000
A65: Total Revenue | B65: 38962000 | C65: 35820000 | D65: 44200000 | E65: 33566000 | F65: 23531000 | G65: 24273000 | H65: 22732000 | I65: 22291000 | J65: 23554000 | K65: 25281000
A66: Direct Costs | B66: 17060000 | C66: 15869000 | D66: 18635000 | E66: 14262000 | F66: 9255000 | G66: 8599000 | H66: 10244000 | I66: 9792000 | J66: 9749000 | K66: 10378000
A67: Gross Profit | B67: 21902000 | C67: 19951000 | D67: 25565000 | E67: 19304000 | F67: 14276000 | G67: 15674000 | H67: 12488000 | I67: 12499000 | J67: 13805000 | K67: 14903000
A68: Selling General & Admin | B68: 2759000 | C68: 2483000 | D68: 2570000 | E68: 2339000 | F68: 2074000 | G68: 2195000 | H68: 2986000 | I68: 2658000 | J68: 2385000 | K68: 2344000
A69: Research & Development | B69: 8893000 | C69: 8818000 | D69: 8194000 | E69: 7176000 | F69: 5975000 | G69: 5398000 | H69: 5625000 | I69: 5485000 | J69: 5151000 | K69: 5490000
A70: Other Operating Expense | B70: 179000 | C70: 862000 | D70: -1059000 | E70: 0 | F70: -28000 | G70: 414000 | H70: 3135000 | I70: 1742000 | J70: -226000 | K70: 1293000
A71: Total Indirect Operating Costs | B71: 11831000 | C71: 12163000 | D71: 9705000 | E71: 9515000 | F71: 8021000 | G71: 8007000 | H71: 11746000 | I71: 9885000 | J71: 7310000 | K71: 9127000
A72: Operating Income | B72: 10071000 | C72: 7788000 | D72: 15860000 | E72: 9789000 | F72: 6255000 | G72: 7667000 | H72: 742000 | I72: 2614000 | J72: 6495000 | K72: 5776000
A73: Interest Income | B73: -22000 | C73: -381000 | D73: -399000 | E73: -476000 | F73: -446000 | G73: -311000 | H73: -143000 | I73: 125000 | J73: 314000 | K73: 423000
A74: Gains on Sale of Assets | B74: 387000 | C74: 82000 | D74: -287000 | E74: 883000 | F74: 314000 | G74: 342000 | H74: 97000 | I74: 562000 | J74: 280000 | K74: 520000
A75: Foreign Exchange Gains | B75: - | C75: - | D75: 19000 | E75: -32000 | F75: -25000 | G75: 11000 | H75: 37000 | I75: -30000 | J75: - | K75: -
A76: Other Non-Operating Income | B76: -100000 | C76: -46000 | D76: -188000 | E76: 97000 | F76: -358000 | G76: -135000 | H76: -75000 | I76: -177000 | J76: -172000 | K76: -200000
A77: Total Non-Operating Income | B77: 265000 | C77: -345000 | D77: -855000 | E77: 472000 | F77: -515000 | G77: -93000 | H77: -84000 | I77: 480000 | J77: 422000 | K77: 743000
A78: Earnings Before Tax | B78: 10336000 | C78: 7443000 | D78: 15005000 | E78: 10261000 | F78: 5740000 | G78: 7574000 | H78: 658000 | I78: 3094000 | J78: 6917000 | K78: 6519000
A79: Taxation | B79: 226000 | C79: 104000 | D79: 2012000 | E79: 1231000 | F79: 521000 | G79: 3095000 | H79: 5377000 | I79: 555000 | J79: 1131000 | K79: 1219000
A80: Earnings After Tax | B80: 10110000 | C80: - | D80: - | E80: - | F80: - | G80: - | H80: - | I80: - | J80: - | K80: -
A81: Equity Earnings | B81: - | C81: - | D81: -7000 | E81: 13000 | F81: -21000 | G81: -93000 | H81: -145000 | I81: -74000 | J81: -84000 | K81: -32000
A82: Net Income | B82: 10142000 | C82: 7232000 | D82: 12936000 | E82: 9043000 | F82: 5198000 | G82: 4386000 | H82: -4864000 | I82: 2466000 | J82: 5705000 | K82: 5271000
A83: Net Income to Common | B83: 10142000 | C83: 7232000 | D83: 12936000 | E83: 9043000 | F83: 5198000 | G83: 4386000 | H83: -4864000 | I83: 2466000 | J83: 5705000 | K83: 5271000
A84: Average Shares Basic | B84: 1116000 | C84: 1117000 | D84: 1123000 | E84: 1131000 | F84: 1135000 | G84: 1210000 | H84: 1463000 | I84: 1477000 | J84: 1484000 | K84: 1618000
A85: EPS Net Basic | B85: 9.09 | C85: 6.47 | D85: 11.52 | E85: 7.99 | F85: 4.58 | G85: 3.63 | H85: -3.32 | I85: 1.67 | J85: 3.84 | K85: 3.26
A86: EPS Continuing Basic | B86: 9.06 | C86: 6.57 | D86: 11.56 | E86: 7.99 | F86: 4.58 | G86: 3.63 | H86: -3.32 | I86: 1.67 | J86: 3.84 | K86: 3.26
A87: Average Shares Diluted | B87: 1130000 | C87: 1126000 | D87: 1137000 | E87: 1149000 | F87: 1149000 | G87: 1220000 | H87: 1463000 | I87: 1490000 | J87: 1498000 | K87: 1639000
A88: EPS Net Diluted | B88: 8.97 | C88: 6.42 | D88: 11.37 | E88: 7.87 | F88: 4.52 | G88: 3.59 | H88: -3.32 | I88: 1.65 | J88: 3.81 | K88: 3.22
A89: EPS Continuing Diluted | B89: 8.94 | C89: 6.52 | D89: 11.41 | E89: 7.87 | F89: 4.52 | G89: 3.59 | H89: -3.32 | I89: 1.65 | J89: 3.81 | K89: 3.22
A90: Shares Outstanding | B90: 1113000 | C90: 1114000 | D90: 1121000 | E90: 1125000 | F90: 1131000 | G90: 1145000 | H90: 1219000 | I90: 1474000 | J90: 1476000 | K90: 1524000
A94: EBIT/TA | B94: =B72/B33 -> 0.18259782 | C94: =C72/C33 -> 0.15258621 | D94: =D72/D33 -> 0.32358102 | E94: =E72/E33 -> 0.23736663 | F94: =F72/F33 -> 0.17573186 | G94: =G72/G33 -> 0.23263647 | H94: =H72/H33 -> 0.022700851 | I94: =I72/I33 -> 0.039916929 | ... K94: =K72/K33 -> 0.11370974
A95: NI/TA | B95: =B82/B33 -> 0.18388512 | C95: =C82/C33 -> 0.14169279 | D95: =D82/D33 -> 0.26392459 | E95: =E82/E33 -> 0.2192774 | F95: =F82/F33 -> 0.14603585 | G95: =G82/G33 -> 0.1330825 | H95: =H82/H33 -> -0.14880989 | I95: =I82/I33 -> 0.037656904 | ... K95: =K82/K33 -> 0.10376801
A96: NI/TE | B96: =B82/B51 -> 0.38600898 | C96: =C82/C51 -> 0.33510959 | D96: =D82/D51 -> 0.718148 | E96: =E82/E51 -> 0.90884422 | F96: =F82/F51 -> 0.85535626 | G96: =G82/G51 -> 0.89346099 | H96: =H82/H51 -> -5.2413793 | I96: =I82/I51 -> 0.080205555 | ... K96: =K82/K51 -> 0.16775405
A97: Gross margin | B97: =B67/B65 -> 0.56213747 | C97: =C67/C65 -> 0.55697934 | D97: =D67/D65 -> 0.57839367 | E97: =E67/E65 -> 0.57510576 | F97: =F67/F65 -> 0.60668905 | G97: =G67/G65 -> 0.64573806 | H97: =H67/H65 -> 0.54935773 | I97: =I67/I65 -> 0.56071957 | ... K97: =K67/K65 -> 0.58949409
A98: RD/Sales | B98: =B69/B65 -> 0.22824804 | C98: =C69/C65 -> 0.24617532 | D98: =D69/D65 -> 0.18538462 | E98: =E69/E65 -> 0.21378776 | F98: =F69/F65 -> 0.25392036 | G98: =G69/G65 -> 0.22238701 | H98: =H69/H65 -> 0.24744853 | I98: =I69/I65 -> 0.24606343 | ... K98: =K69/K65 -> 0.21715913
A99: NI/Revenue | B99: =B82/B65 -> 0.26030491 | C99: =C82/C65 -> 0.20189838 | D99: =D82/D65 -> 0.29266968 | E99: =E82/E65 -> 0.26940952 | F99: =F82/F65 -> 0.22090009 | G99: =G82/G65 -> 0.1806946 | H99: =H82/H65 -> -0.21397149 | I99: =I82/I65 -> 0.11062761 | ... K99: =K82/K65 -> 0.2084965
A100: COGS/Sales | B100: =B66/B65 -> 0.43786253 | C100: =C66/C65 -> 0.44302066 | D100: =D66/D65 -> 0.42160633 | E100: =E66/E65 -> 0.42489424 | F100: =F66/F65 -> 0.39331095 | G100: =G66/G65 -> 0.35426194 | H100: =H66/H65 -> 0.45064227 | I100: =I66/I65 -> 0.43928043 | ... K100: =K66/K65 -> 0.41050591
A101: SGA/Sales | B101: =B68/B65 -> 0.070812587 | C101: =C68/C65 -> 0.069318816 | D101: =D68/D65 -> 0.058144796 | E101: =E68/E65 -> 0.069683608 | F101: =F68/F65 -> 0.088139051 | G101: =G68/G65 -> 0.090429696 | H101: =H68/H65 -> 0.13135668 | I101: =I68/I65 -> 0.11924095 | ... K101: =K68/K65 -> 0.092717851
A102: AR/Sales | B102: =B19/B65 -> 0.10084185 | C102: =C19/C65 -> 0.088860972 | D102: =D19/D65 -> 0.12766968 | E102: =E19/E65 -> 0.10662575 | F102: =F19/F65 -> 0.17011602 | G102: =G19/G65 -> 0.10180035 | H102: =H19/H65 -> 0.12774943 | I102: =I19/I65 -> 0.16293571 | ... K102: =K19/K65 -> 0.0776868
A104: sales Growth | C104: =(C65-B65)/B65 -> -0.080642677 | D104: =(D65-C65)/C65 -> 0.23394752 | E104: =(E65-D65)/D65 -> -0.24058824 | F104: =(F65-E65)/E65 -> -0.29896324 | G104: =(G65-F65)/F65 -> 0.031532872 | H104: =(H65-G65)/G65 -> -0.063486178 | I104: =(I65-H65)/H65 -> -0.019399965 | J104: =(J65-I65)/I65 -> 0.056659638 | K104: =(K65-J65)/J65 -> 0.07332088
A106: Interest(on Avg Debt) | B106: =(B77*-1)/AVERAGE(B40:C40) -> -0.019096346 | C106: =(C77*-1)/AVERAGE(C40:D40) -> 0.024624389 | D106: =(D77*-1)/AVERAGE(D40:E40) -> 0.06277994 | E106: =(E77*-1)/AVERAGE(E40:F40) -> -0.032633871 | F106: =(F77*-1)/AVERAGE(F40:G40) -> 0.035934829 | G106: =(G77*-1)/AVERAGE(G40:H40) -> 0.0064578849 | H106: =(H77*-1)/AVERAGE(H40:I40) -> 0.0048327244 | I106: =(I77*-1)/AVERAGE(I40:J40) -> -0.032646399 | ... K106: =(K77*-1)/AVERAGE(K40:L40) -> -0.074531046

Sheet Sheet1
A1: ear | B1: 2015 | C1: 2016 | D1: 2017 | E1: 2018 | F1: 2019 | G1: 2020 | H1: 2021 | I1: 2022 | J1: 2023 | K1: 2024
A2: AMD Price (USD) | B2: 2 | C2: 5 | D2: 11 | E2: 19 | F2: 29 | G2: 55 | H2: 85 | I2: 95 | J2: 110 | K2: 100
A3: AMD Shares Outstanding | B3: 790000000 | C3: 910000000 | D3: 970000000 | E3: 1000000000 | F3: 1100000000 | G3: 1200000000 | H3: 1250000000 | I3: 1300000000 | J3: 1350000000 | K3: 1400000000
A4: Intel Price (USD) | B4: 31 | C4: 33 | D4: 40 | E4: 48 | F4: 58 | G4: 60 | H4: 55 | I4: 45 | J4: 35 | K4: 25
A5: Intel Shares Outstanding | B5: 4730000000 | C5: 4730000000 | D5: 4690000000 | E5: 4600000000 | F5: 4450000000 | G5: 4300000000 | H5: 4100000000 | I5: 4050000000 | J5: 4000000000 | K5: 3950000000
A6: NVIDIA Price (USD) | B6: 20 | C6: 30 | D6: 60 | E6: 150 | F6: 170 | G6: 300 | H6: 500 | I6: 400 | J6: 450 | K6: 600
A7: NVIDIA Shares Outstanding | B7: 540000000 | C7: 560000000 | D7: 600000000 | E7: 620000000 | F7: 620000000 | G7: 620000000 | H7: 620000000 | I7: 620000000 | J7: 2,460,000,000 (Stock Split) | K7: 2500000000
A8: Qualcomm Price (USD) | B8: 47.53 | C8: 45.17 | D8: 46.32 | E8: 51.98 | F8: 63.18 | G8: 92.94 | H8: 134.73 | I8: 131.41 | J8: 115.81 | K8: 169.22
A9: Qualcomm Shares Outstanding | B9: 1560000000 | C9: 1480000000 | D9: 1480000000 | E9: 1520000000 | F9: 1500000000 | G9: 1410000000 | H9: 1420000000 | I9: 1120000000 | J9: 1120000000 | K9: 1120000000
