Workbook

Sheet standardized
A4: Powered by Clearbit
A5: NVIDIA Corp (NMS: NVDA)
A7: Exchange rate used is that of the Year End reported date
A10: Standardized Annual Income Statement
A11: Report Date | B11: 01/25/2015 | C11: 01/31/2016 | D11: 01/29/2017 | E11: 01/28/2018 | F11: 01/27/2019 | G11: 01/26/2020 | H11: 01/31/2021 | I11: 01/30/2022 | J11: 01/29/2023 | K11: 01/28/2024
A12: Currency | B12: USD | C12: USD | D12: USD | E12: USD | F12: USD | G12: USD | H12: USD | I12: USD | J12: USD | K12: USD
A13: Audit Status | B13: Not Qualified | C13: Not Qualified | D13: Not Qualified | E13: Not Qualified | F13: Not Qualified | G13: Not Qualified | H13: Not Qualified | I13: Not Qualified | J13: Not Qualified | K13: Not Qualified
A14: Consolidated | B14: Yes | C14: Yes | D14: Yes | E14: Yes | F14: Yes | G14: Yes | H14: Yes | I14: Yes | J14: Yes | K14: Yes
A15: Scale | B15: Thousands | C15: Thousands | D15: Thousands | E15: Thousands | F15: Thousands | G15: Thousands | H15: Thousands | I15: Thousands | J15: Thousands | K15: Thousands
A16: Sales Revenue | B16: - | C16: - | D16: - | E16: - | F16: - | G16: - | H16: - | I16: - | J16: - | K16: 60922000
A17: Total Revenue | B17: 4681507 | C17: 5010000 | D17: 6910000 | E17: 9714000 | F17: 11716000 | G17: 10918000 | H17: 16675000 | I17: 26914000 | J17: 26974000 | K17: 60922000
A18: Direct Costs | B18: 2082030 | C18: 2199000 | D18: 2847000 | E18: 3892000 | F18: 4545000 | G18: 4150000 | H18: 6279000 | I18: 9439000 | J18: 11618000 | K18: 16621000
A19: Gross Profit | B19: 2599477 | C19: 2811000 | D19: 4063000 | E19: 5822000 | F19: 7171000 | G19: 6768000 | H19: 10396000 | I19: 17475000 | J19: 15356000 | K19: 44301000
A20: Selling General & Admin | B20: 480763 | C20: 602000 | D20: 663000 | E20: 815000 | F20: 991000 | G20: 1093000 | H20: 1940000 | I20: 2166000 | J20: 2440000 | K20: 2654000
A21: Research & Development | B21: 1359725 | C21: 1331000 | D21: 1463000 | E21: 1797000 | F21: 2376000 | G21: 2829000 | H21: 3924000 | I21: 5268000 | J21: 7339000 | K21: 8675000
A22: Restruct Remediation & Impair | B22: - | C22: - | D22: - | E22: - | F22: - | G22: - | H22: - | I22: - | J22: 1353000 | K22: -
A23: Total Indirect Operating Costs | B23: 1840488 | C23: 2064000 | D23: 2129000 | E23: 2612000 | F23: 3367000 | G23: 3922000 | H23: 5864000 | I23: 7434000 | J23: 11132000 | K23: 11329000
A24: Operating Income | B24: 758989 | C24: 747000 | D24: 1934000 | E24: 3210000 | F24: 3804000 | G24: 2846000 | H24: 4532000 | I24: 10041000 | J24: 4224000 | K24: 32972000
A25: Interest Income | B25: -18043 | C25: -8000 | D25: -4000 | E25: 8000 | F25: 78000 | G25: 126000 | H25: -127000 | I25: -207000 | J25: 5000 | K25: 609000
A26: Other Non-Operating Income | B26: 13890 | C26: 4000 | D26: -25000 | E26: -22000 | F26: 14000 | G26: -2000 | H26: 4000 | I26: 107000 | J26: -48000 | K26: 237000
A27: Total Non-Operating Income | B27: -4153 | C27: -4000 | D27: -29000 | E27: -14000 | F27: 92000 | G27: 124000 | H27: -123000 | I27: -100000 | J27: -43000 | K27: 846000
A28: Earnings Before Tax | B28: 754836 | C28: 743000 | D28: 1905000 | E28: 3196000 | F28: 3896000 | G28: 2970000 | H28: 4409000 | I28: 9941000 | J28: 4181000 | K28: 33818000
A29: Taxation | B29: 124249 | C29: 129000 | D29: 239000 | E29: 149000 | F29: -245000 | G29: 174000 | H29: 77000 | I29: 189000 | J29: -187000 | K29: 4058000
A30: Extraordinary Items | B30: 0 | C30: 0 | D30: 0 | E30: 0 | F30: 0 | G30: 0 | H30: 0 | I30: 0 | J30: 0 | K30: 0
A31: Accounting Changes | B31: 0 | C31: 0 | D31: 0 | E31: 0 | F31: 0 | G31: 0 | H31: 0 | I31: 0 | J31: 0 | K31: 0
A32: Net Income | B32: 630587 | C32: 614000 | D32: 1666000 | E32: 3047000 | F32: 4141000 | G32: 2796000 | H32: 4332000 | I32: 9752000 | J32: 4368000 | K32: 29760000
A33: Preference Dividends & Similar | B33: 0 | C33: 0 | D33: 0 | E33: 0 | F33: 0 | G33: 0 | H33: 0 | I33: 0 | J33: 0 | K33: 0
A34: Net Income to Common | B34: 630587 | C34: 614000 | D34: 1666000 | E34: 3047000 | F34: 4141000 | G34: 2796000 | H34: 4332000 | I34: 9752000 | J34: 4368000 | K34: 29760000
... A41: Shares Outstanding | B41: 21796520 | C41: 21560000 | D41: 23400000 | E41: 24240000 | F41: 24240000 | G41: 24480000 | H41: 24800000 | I41: 25060000 | J41: 24660000 | K41: 24640000

Sheet Sheet1
A1: Standardized Annual Income Statement
A2: Report Date | B2: =standardized!B11 -> 01/25/2015 | C2: =standardized!C11 -> 01/31/2016 | D2: =standardized!D11 -> 01/29/2017 | E2: =standardized!E11 -> 01/28/2018 | F2: =standardized!F11 -> 01/27/2019 | G2: =standardized!G11 -> 01/26/2020 | H2: =standardized!H11 -> 01/31/2021 | I2: =standardized!I11 -> 01/30/2022 | ... K2: =standardized!K11 -> 01/28/2024
A3: Sales Revenue
A4: Revenue Growth | C4: =standardized!C17/standardized!B17-1 -> 0.070168217 | D4: =standardized!D17/standardized!C17-1 -> 0.37924152 | E4: =standardized!E17/standardized!D17-1 -> 0.40578871 | F4: =standardized!F17/standardized!E17-1 -> 0.2060943 | G4: =standardized!G17/standardized!F17-1 -> -0.068111984 | H4: =standardized!H17/standardized!G17-1 -> 0.52729438 | I4: =standardized!I17/standardized!H17-1 -> 0.61403298 | J4: =standardized!J17/standardized!I17-1 -> 0.002229323 | K4: =standardized!K17/standardized!J17-1 -> 1.2585453
A5: Direct Costs
A6: Gross Margin | B6: =standardized!B19/standardized!B17 -> 0.555265 | C6: =standardized!C19/standardized!C17 -> 0.56107784 | D6: =standardized!D19/standardized!D17 -> 0.58798842 | E6: =standardized!E19/standardized!E17 -> 0.59934116 | F6: =standardized!F19/standardized!F17 -> 0.61206897 | G6: =standardized!G19/standardized!G17 -> 0.61989375 | H6: =standardized!H19/standardized!H17 -> 0.62344828 | I6: =standardized!I19/standardized!I17 -> 0.64929033 | ... K6: =standardized!K19/standardized!K17 -> 0.72717573
A7: Research & Development margin | B7: =standardized!B21/standardized!B21 -> 1 | C7: =(standardized!C21-standardized!B21)/standardized!B21 -> -0.021125595 | D7: =(standardized!D21-standardized!C21)/standardized!C21 -> 0.099173554 | E7: =(standardized!E21-standardized!D21)/standardized!D21 -> 0.22829802 | F7: =(standardized!F21-standardized!E21)/standardized!E21 -> 0.32220367 | G7: =(standardized!G21-standardized!F21)/standardized!F21 -> 0.19065657 | H7: =(standardized!H21-standardized!G21)/standardized!G21 -> 0.38706257 | I7: =(standardized!I21-standardized!H21)/standardized!H21 -> 0.34250765 | J7: =(standardized!J21-standardized!I21)/standardized!I21 -> 0.39312832 | K7: =(standardized!K21-standardized!J21)/standardized!J21 -> 0.18204115
A8: Operating Income | B8: =standardized!B24/standardized!B22 -> #VALUE! | C8: =(standardized!C24-standardized!B24)/standardized!B24 -> -0.015796013 | D8: =(standardized!D24-standardized!C24)/standardized!C24 -> 1.5890228 | E8: =(standardized!E24-standardized!D24)/standardized!D24 -> 0.65977249 | F8: =(standardized!F24-standardized!E24)/standardized!E24 -> 0.18504673 | G8: =(standardized!G24-standardized!F24)/standardized!F24 -> -0.25184017 | H8: =(standardized!H24-standardized!G24)/standardized!G24 -> 0.5924104 | I8: =(standardized!I24-standardized!H24)/standardized!H24 -> 1.2155781 | J8: =(standardized!J24-standardized!I24)/standardized!I24 -> -0.57932477 | K8: =(standardized!K24-standardized!J24)/standardized!J24 -> 6.8058712
A9: Interest Income
A10: Total Non-Operating Income
A11: Earnings Before Tax
A12: Taxation
A13: Accounting Changes
A14: Net Income
A15: Preference Dividends & Similar
A16: Net Income to Common
A17: Average Shares Basic
A18: EPS Net Basic
A19: EPS Continuing Basic
A20: Average Shares Diluted
... A23: Shares Outstanding

Sheet Sheet2
A1: Standardized Annual Income Statement
A2: Report Date | B2: =standardized!B11 -> 01/25/2015 | C2: =standardized!C11 -> 01/31/2016 | D2: =standardized!D11 -> 01/29/2017 | E2: =standardized!E11 -> 01/28/2018 | F2: =standardized!F11 -> 01/27/2019 | G2: =standardized!G11 -> 01/26/2020 | H2: =standardized!H11 -> 01/31/2021 | I2: =standardized!I11 -> 01/30/2022 | ... K2: =standardized!K11 -> 01/28/2024
A3: Sales Revenue
A4: Revenue Growth | B4: =standardized!B17/standardized!B$17 -> 1 | C4: =standardized!C17/standardized!C$17 -> 1 | D4: =standardized!D17/standardized!D$17 -> 1 | E4: =standardized!E17/standardized!E$17 -> 1 | F4: =standardized!F17/standardized!F$17 -> 1 | G4: =standardized!G17/standardized!G$17 -> 1 | H4: =standardized!H17/standardized!H$17 -> 1 | I4: =standardized!I17/standardized!I$17 -> 1 | ... K4: =standardized!K17/standardized!K$17 -> 1
A5: Direct Costs | B5: =standardized!B18/standardized!B$17 -> 0.444735 | C5: =standardized!C18/standardized!C$17 -> 0.43892216 | D5: =standardized!D18/standardized!D$17 -> 0.41201158 | E5: =standardized!E18/standardized!E$17 -> 0.40065884 | F5: =standardized!F18/standardized!F$17 -> 0.38793103 | G5: =standardized!G18/standardized!G$17 -> 0.38010625 | H5: =standardized!H18/standardized!H$17 -> 0.37655172 | I5: =standardized!I18/standardized!I$17 -> 0.35070967 | ... K5: =standardized!K18/standardized!K$17 -> 0.27282427
A6: Gross Profit | B6: =standardized!B19/standardized!B$17 -> 0.555265 | C6: =standardized!C19/standardized!C$17 -> 0.56107784 | D6: =standardized!D19/standardized!D$17 -> 0.58798842 | E6: =standardized!E19/standardized!E$17 -> 0.59934116 | F6: =standardized!F19/standardized!F$17 -> 0.61206897 | G6: =standardized!G19/standardized!G$17 -> 0.61989375 | H6: =standardized!H19/standardized!H$17 -> 0.62344828 | I6: =standardized!I19/standardized!I$17 -> 0.64929033 | ... K6: =standardized!K19/standardized!K$17 -> 0.72717573
A7: Selling General & Admin | B7: =standardized!B20/standardized!B$17 -> 0.10269407 | C7: =standardized!C20/standardized!C$17 -> 0.12015968 | D7: =standardized!D20/standardized!D$17 -> 0.095947902 | E7: =standardized!E20/standardized!E$17 -> 0.083899526 | F7: =standardized!F20/standardized!F$17 -> 0.084585183 | G7: =standardized!G20/standardized!G$17 -> 0.10010991 | H7: =standardized!H20/standardized!H$17 -> 0.11634183 | I7: =standardized!I20/standardized!I$17 -> 0.080478561 | ... K7: =standardized!K20/standardized!K$17 -> 0.043563901
A8: Research & Development | B8: =standardized!B21/standardized!B$17 -> 0.290446 | C8: =standardized!C21/standardized!C$17 -> 0.26566866 | D8: =standardized!D21/standardized!D$17 -> 0.21172214 | E8: =standardized!E21/standardized!E$17 -> 0.18499074 | F8: =standardized!F21/standardized!F$17 -> 0.20279959 | G8: =standardized!G21/standardized!G$17 -> 0.25911339 | H8: =standardized!H21/standardized!H$17 -> 0.23532234 | I8: =standardized!I21/standardized!I$17 -> 0.19573456 | ... K8: =standardized!K21/standardized!K$17 -> 0.14239519
A9: Total Indirect Operating Costs | B9: =standardized!B23/standardized!B$17 -> 0.39314007 | C9: =standardized!C23/standardized!C$17 -> 0.41197605 | D9: =standardized!D23/standardized!D$17 -> 0.3081042 | E9: =standardized!E23/standardized!E$17 -> 0.26889026 | F9: =standardized!F23/standardized!F$17 -> 0.28738477 | G9: =standardized!G23/standardized!G$17 -> 0.3592233 | H9: =standardized!H23/standardized!H$17 -> 0.35166417 | I9: =standardized!I23/standardized!I$17 -> 0.27621312 | ... K9: =standardized!K23/standardized!K$17 -> 0.1859591
A10: Operating Income | B10: =standardized!B24/standardized!B$17 -> 0.16212493 | C10: =standardized!C24/standardized!C$17 -> 0.1491018 | D10: =standardized!D24/standardized!D$17 -> 0.27988423 | E10: =standardized!E24/standardized!E$17 -> 0.3304509 | F10: =standardized!F24/standardized!F$17 -> 0.32468419 | G10: =standardized!G24/standardized!G$17 -> 0.26067045 | H10: =standardized!H24/standardized!H$17 -> 0.27178411 | I10: =standardized!I24/standardized!I$17 -> 0.37307721 | ... K10: =standardized!K24/standardized!K$17 -> 0.54121664
A11: Interest Income | B11: =standardized!B25/standardized!B$17 -> -0.0038541008 | C11: =standardized!C25/standardized!C$17 -> -0.0015968064 | D11: =standardized!D25/standardized!D$17 -> -0.0005788712 | E11: =standardized!E25/standardized!E$17 -> 0.00082355363 | F11: =standardized!F25/standardized!F$17 -> 0.0066575623 | G11: =standardized!G25/standardized!G$17 -> 0.011540575 | H11: =standardized!H25/standardized!H$17 -> -0.0076161919 | I11: =standardized!I25/standardized!I$17 -> -0.0076911644 | ... K11: =standardized!K25/standardized!K$17 -> 0.0099963888
A12: Total Non-Operating Income | B12: =standardized!B26/standardized!B$17 -> 0.0029669933 | C12: =standardized!C26/standardized!C$17 -> 0.00079840319 | D12: =standardized!D26/standardized!D$17 -> -0.003617945 | E12: =standardized!E26/standardized!E$17 -> -0.0022647725 | F12: =standardized!F26/standardized!F$17 -> 0.0011949471 | G12: =standardized!G26/standardized!G$17 -> -0.00018318373 | H12: =standardized!H26/standardized!H$17 -> 0.00023988006 | I12: =standardized!I26/standardized!I$17 -> 0.0039756261 | ... K12: =standardized!K26/standardized!K$17 -> 0.0038902203
A13: Earnings Before Tax | B13: =standardized!B27/standardized!B$17 -> -0.00088710751 | C13: =standardized!C27/standardized!C$17 -> -0.00079840319 | D13: =standardized!D27/standardized!D$17 -> -0.0041968162 | E13: =standardized!E27/standardized!E$17 -> -0.0014412189 | F13: =standardized!F27/standardized!F$17 -> 0.0078525094 | G13: =standardized!G27/standardized!G$17 -> 0.011357391 | H13: =standardized!H27/standardized!H$17 -> -0.0073763118 | I13: =standardized!I27/standardized!I$17 -> -0.0037155384 | ... K13: =standardized!K27/standardized!K$17 -> 0.013886609
A14: Taxation | B14: =standardized!B28/standardized!B$17 -> 0.16123782 | C14: =standardized!C28/standardized!C$17 -> 0.14830339 | D14: =standardized!D28/standardized!D$17 -> 0.27568741 | E14: =standardized!E28/standardized!E$17 -> 0.32900968 | F14: =standardized!F28/standardized!F$17 -> 0.3325367 | G14: =standardized!G28/standardized!G$17 -> 0.27202784 | H14: =standardized!H28/standardized!H$17 -> 0.2644078 | I14: =standardized!I28/standardized!I$17 -> 0.36936167 | ... K14: =standardized!K28/standardized!K$17 -> 0.55510325
A15: Extraordinary Items | B15: =standardized!B29/standardized!B$17 -> 0.026540385 | C15: =standardized!C29/standardized!C$17 -> 0.025748503 | D15: =standardized!D29/standardized!D$17 -> 0.034587554 | E15: =standardized!E29/standardized!E$17 -> 0.015338686 | F15: =standardized!F29/standardized!F$17 -> -0.020911574 | G15: =standardized!G29/standardized!G$17 -> 0.015936985 | H15: =standardized!H29/standardized!H$17 -> 0.0046176912 | I15: =standardized!I29/standardized!I$17 -> 0.0070223675 | ... K15: =standardized!K29/standardized!K$17 -> 0.066609763
A16: Accounting Changes | B16: =standardized!B30/standardized!B$17 -> 0 | C16: =standardized!C30/standardized!C$17 -> 0 | D16: =standardized!D30/standardized!D$17 -> 0 | E16: =standardized!E30/standardized!E$17 -> 0 | F16: =standardized!F30/standardized!F$17 -> 0 | G16: =standardized!G30/standardized!G$17 -> 0 | H16: =standardized!H30/standardized!H$17 -> 0 | I16: =standardized!I30/standardized!I$17 -> 0 | ... K16: =standardized!K30/standardized!K$17 -> 0
A17: Net Income | B17: =standardized!B31/standardized!B$17 -> 0 | C17: =standardized!C31/standardized!C$17 -> 0 | D17: =standardized!D31/standardized!D$17 -> 0 | E17: =standardized!E31/standardized!E$17 -> 0 | F17: =standardized!F31/standardized!F$17 -> 0 | G17: =standardized!G31/standardized!G$17 -> 0 | H17: =standardized!H31/standardized!H$17 -> 0 | I17: =standardized!I31/standardized!I$17 -> 0 | ... K17: =standardized!K31/standardized!K$17 -> 0
A18: Preference Dividends & Similar | B18: =standardized!B32/standardized!B$17 -> 0.13469744 | C18: =standardized!C32/standardized!C$17 -> 0.12255489 | D18: =standardized!D32/standardized!D$17 -> 0.24109986 | E18: =standardized!E32/standardized!E$17 -> 0.31367099 | F18: =standardized!F32/standardized!F$17 -> 0.35344828 | G18: =standardized!G32/standardized!G$17 -> 0.25609086 | H18: =standardized!H32/standardized!H$17 -> 0.2597901 | I18: =standardized!I32/standardized!I$17 -> 0.3623393 | ... K18: =standardized!K32/standardized!K$17 -> 0.48849348
A19: Net Income to Common | B19: =standardized!B33/standardized!B$17 -> 0 | C19: =standardized!C33/standardized!C$17 -> 0 | D19: =standardized!D33/standardized!D$17 -> 0 | E19: =standardized!E33/standardized!E$17 -> 0 | F19: =standardized!F33/standardized!F$17 -> 0 | G19: =standardized!G33/standardized!G$17 -> 0 | H19: =standardized!H33/standardized!H$17 -> 0 | I19: =standardized!I33/standardized!I$17 -> 0 | ... K19: =standardized!K33/standardized!K$17 -> 0
A20: Average Shares Basic | B20: =standardized!B34/standardized!B$17 -> 0.13469744 | C20: =standardized!C34/standardized!C$17 -> 0.12255489 | D20: =standardized!D34/standardized!D$17 -> 0.24109986 | E20: =standardized!E34/standardized!E$17 -> 0.31367099 | F20: =standardized!F34/standardized!F$17 -> 0.35344828 | G20: =standardized!G34/standardized!G$17 -> 0.25609086 | H20: =standardized!H34/standardized!H$17 -> 0.2597901 | I20: =standardized!I34/standardized!I$17 -> 0.3623393 | ... K20: =standardized!K34/standardized!K$17 -> 0.48849348
... A26: Shares Outstanding | B26: =standardized!B40/standardized!B$17 -> 6.4081929e-09 | C26: =standardized!C40/standardized!C$17 -> 5.988024e-09 | D26: =standardized!D40/standardized!D$17 -> 8.683068e-09 | E26: =standardized!E40/standardized!E$17 -> 1.2353305e-08 | F26: =standardized!F40/standardized!F$17 -> 1.4510072e-08 | G26: =standardized!G40/standardized!G$17 -> 1.0075105e-08 | H26: =standardized!H40/standardized!H$17 -> 1.0194903e-08 | I26: =standardized!I40/standardized!I$17 -> 1.44906e-08 | ... K26: =standardized!K40/standardized!K$17 -> 1.9533174e-08
