Workbook

Sheet Stock Price
C2: Max Points: | D2: 2 | F2: Total Max Quiz Points | H2: =D2+'Income Statement'!C2+'Common Size IS'!C2+Ratios!C2+Valuation!D2 -> 15
C3: Points | F3: Total Points | H3: =D3+'[1]Income Statement'!C3+'[1]Common Size IS'!D3+[1]Ratios!C3+[1]Valuation!D3 -> 0
A5: Below are historic monthly stock prices for Nike stock for 6-1-2014 to 7-1-2024
A7: Please graph the historic stock price of Nike stock and provide a brief comment on the general stock performance of Nike
A8: Please compute monthly returns of the stock of Nike for the period of June 2014 to July 2024
A10: Date | B10: Price
A11: 41791 | B11: 34.54
A12: 41821 | B12: 34.35
A13: 41852 | B13: 34.98
A14: 41883 | B14: 39.84
A15: 41913 | B15: 41.53
A16: 41944 | B16: 44.35
A17: 41974 | B17: 42.95
A18: 42005 | B18: 41.32
A19: 42036 | B19: 43.51
A20: 42064 | B20: 45.07
A21: 42095 | B21: 44.4
A22: 42125 | B22: 45.68
... A132: 45474 | B132: 74.53

Sheet Income Statement
B2: Max Points | C2: 3
B3: Points
A4: Powered by Clearbit
A5: NIKE Inc (NYS: NKE)
A7: Throughout the test, where appropriate, please provide your commentary and visuals
A10: Standardized Annual Income Statement
A11: Report Date | B11: 05/31/2015 | C11: 05/31/2016 | D11: 05/31/2017 | E11: 05/31/2018 | F11: 05/31/2019 | G11: 05/31/2020 | H11: 05/31/2021 | I11: 05/31/2022 | J11: 05/31/2023 | K11: 05/31/2024
A12: Currency | B12: USD | C12: USD | D12: USD | E12: USD | F12: USD | G12: USD | H12: USD | I12: USD | J12: USD | K12: USD
A13: Audit Status | B13: Not Qualified | C13: Not Qualified | D13: Not Qualified | E13: Not Qualified | F13: Not Qualified | G13: Not Qualified | H13: Not Qualified | I13: Not Qualified | J13: Not Qualified | K13: Not Qualified
A14: Consolidated | B14: Yes | C14: Yes | D14: Yes | E14: Yes | F14: Yes | G14: Yes | H14: Yes | I14: Yes | J14: Yes | K14: Yes
A15: Scale | B15: Thousands | C15: Thousands | D15: Thousands | E15: Thousands | F15: Thousands | G15: Thousands | H15: Thousands | I15: Thousands | J15: Thousands | K15: Thousands
A16: Total Revenue | B16: 30601000 | C16: 32376000 | D16: 34350000 | E16: 36397000 | F16: 39117000 | G16: 37403000 | H16: 44538000 | I16: 46710000 | J16: 51217000 | K16: 51362000
A17: Direct Costs | B17: 16534000 | C17: 17405000 | D17: 19038000 | E17: 20441000 | F17: 21643000 | G17: 21162000 | H17: 24576000 | I17: 25231000 | J17: 28925000 | K17: 28475000
A18: Gross Profit | B18: 14067000 | C18: 14971000 | D18: 15312000 | E18: 15956000 | F18: 17474000 | G18: 16241000 | H18: 19962000 | I18: 21479000 | J18: 22292000 | K18: 22887000
A19: Selling General & Admin | B19: 9892000 | C19: 10469000 | D19: 10563000 | E19: 11511000 | F19: 12702000 | G19: 13126000 | H19: 13025000 | I19: 14804000 | J19: 16377000 | K19: 16576000
A20: Other Operating Expense | B20: -58000 | C20: -140000 | D20: -196000 | E20: 66000 | F20: -78000 | G20: 139000 | H20: 14000 | I20: -181000 | J20: -280000 | K20: 0
A21: Total Indirect Operating Costs | B21: 9834000 | C21: 10329000 | D21: 10367000 | E21: 11577000 | F21: 12624000 | G21: 13265000 | H21: 13039000 | I21: 14623000 | J21: 16097000 | K21: 16576000
A22: Operating Income | B22: 4233000 | C22: 4642000 | D22: 4945000 | E22: 4379000 | F22: 4850000 | G22: 2976000 | H22: 6923000 | I22: 6856000 | J22: 6195000 | K22: 6311000
A23: Interest Income | B23: -28000 | C23: -19000 | D23: -59000 | E23: -54000 | F23: -49000 | G23: -89000 | H23: -262000 | I23: -205000 | J23: 6000 | K23: 161000
A24: Other Non-Operating Income | B24: 0 | C24: 0 | D24: 0 | E24: 0 | F24: 0 | G24: 0 | H24: 0 | I24: 0 | J24: 0 | K24: 228000
A25: Total Non-Operating Income | B25: -28000 | C25: -19000 | D25: -59000 | E25: -54000 | F25: -49000 | G25: -89000 | H25: -262000 | I25: -205000 | J25: 6000 | K25: 389000
A26: Earnings Before Tax | B26: 4205000 | C26: 4623000 | D26: 4886000 | E26: 4325000 | F26: 4801000 | G26: 2887000 | H26: 6661000 | I26: 6651000 | J26: 6201000 | K26: 6700000
A27: Taxation | B27: 932000 | C27: 863000 | D27: 646000 | E27: 2392000 | F27: 772000 | G27: 348000 | H27: 934000 | I27: 605000 | J27: 1131000 | K27: 1000000
... A33: Please compute the following: | B33: 2015 | C33: 2016 | D33: 2017 | E33: 2018 | F33: 2019 | G33: 2020 | H33: 2021 | I33: 2022 | J33: 2023 | K33: 2024
A35: Average Stock Price (for the year - June to May for each year)
A37: Year over Year return based on above average prices for the year
A39: Average Market Cap (for the year June to May)
A41: Earnings Per Share
A42: Price to Earnings (Year Avg.)
A44: Please compute the annual sales growth of Nike for 2015-2024
A46: Please graph the level of sales and net income using a bar chart, make sure to proparly label the axis. Provide a comment regarding your obeservations. Feel free to provide additional visuals if needed.

Sheet Common Size IS
B2: Max Points: | C2: 2
B3: Points
A4: Powered by Clearbit
A5: NIKE Inc (NYS: NKE)
A7: Please create a common size Income Statement
A10: Report Date | B10: ='Income Statement'!B11 -> 05/31/2015 | C10: ='Income Statement'!C11 -> 05/31/2016 | D10: ='Income Statement'!D11 -> 05/31/2017 | E10: ='Income Statement'!E11 -> 05/31/2018 | F10: ='Income Statement'!F11 -> 05/31/2019 | G10: ='Income Statement'!G11 -> 05/31/2020 | H10: ='Income Statement'!H11 -> 05/31/2021 | I10: ='Income Statement'!I11 -> 05/31/2022 | ... K10: ='Income Statement'!K11 -> 05/31/2024
A12: Total Revenue
A13: Direct Costs
A14: Gross Profit
A15: Selling General & Admin
A16: Other Operating Expense
A17: Total Indirect Operating Costs
A18: Operating Income
A19: Interest Income
A20: Other Non-Operating Income
A21: Total Non-Operating Income
A22: Earnings Before Tax
A23: Taxation
... A27: Please Comment as to the historic dynamics of the direct cost and selling general and administrative expenses of Nike. Feel free to inlcude visuals.

Sheet Balance Sheet
A4: Powered by Clearbit
A5: NIKE Inc (NYS: NKE)
A7: Exchange rate used is that of the Year End reported date
A10: Standardized Annual Balance Sheet
A11: Report Date | B11: 05/31/2015 | C11: 05/31/2016 | D11: 05/31/2017 | E11: 05/31/2018 | F11: 05/31/2019 | G11: 05/31/2020 | H11: 05/31/2021 | I11: 05/31/2022 | J11: 05/31/2023 | K11: 05/31/2024
A12: Currency | B12: USD | C12: USD | D12: USD | E12: USD | F12: USD | G12: USD | H12: USD | I12: USD | J12: USD | K12: USD
A13: Audit Status | B13: Not Qualified | C13: Not Qualified | D13: Not Qualified | E13: Not Qualified | F13: Not Qualified | G13: Not Qualified | H13: Not Qualified | I13: Not Qualified | J13: Not Qualified | K13: Not Qualified
A14: Consolidated | B14: Yes | C14: Yes | D14: Yes | E14: Yes | F14: Yes | G14: Yes | H14: Yes | I14: Yes | J14: Yes | K14: Yes
A15: Scale | B15: Thousands | C15: Thousands | D15: Thousands | E15: Thousands | F15: Thousands | G15: Thousands | H15: Thousands | I15: Thousands | J15: Thousands | K15: Thousands
A16: Cash & Equivalents | B16: 3852000 | C16: 3138000 | D16: 3808000 | E16: 4249000 | F16: 4466000 | G16: 8348000 | H16: 9889000 | I16: 8574000 | J16: 7441000 | K16: 9860000
A17: Short Term Investments | B17: 2072000 | C17: 2319000 | D17: 2371000 | E17: 996000 | F17: 197000 | G17: 439000 | H17: 3587000 | I17: 4423000 | J17: 3234000 | K17: 1722000
A18: Cash & Equivs & ST Investments | B18: 5924000 | C18: 5457000 | D18: 6179000 | E18: 5245000 | F18: 4663000 | G18: 8787000 | H18: 13476000 | I18: 12997000 | J18: 10675000 | K18: 11582000
A19: Receivables (ST) | B19: 3358000 | C19: 3241000 | D19: 3677000 | E19: 3498000 | F19: 4272000 | G19: 2749000 | H19: 4463000 | I19: 4667000 | J19: 4131000 | K19: 4427000
A20: Inventories | B20: 4337000 | C20: 4838000 | D20: 5055000 | E20: 5261000 | F20: 5622000 | G20: 7367000 | H20: 6854000 | I20: 8420000 | J20: 8454000 | K20: 7519000
A21: Current Tax Assets | B21: 389000 | C21: - | D21: - | E21: - | F21: - | G21: - | H21: - | I21: - | J21: - | K21: -
A22: Prepayments (ST) | B22: - | C22: - | D22: - | E22: - | F22: - | G22: - | H22: - | I22: - | J22: - | K22: 1854000
A23: Other Current Assets | B23: 1968000 | C23: 1489000 | D23: 1150000 | E23: 1130000 | F23: 1968000 | G23: 1653000 | H23: 1498000 | I23: 2129000 | J23: 1942000 | K23: 0
A24: Total Current Assets | B24: 15976000 | C24: 15025000 | D24: 16061000 | E24: 15134000 | F24: 16525000 | G24: 20556000 | H24: 26291000 | I24: 28213000 | J24: 25202000 | K24: 25382000
A25: Gross Property Plant & Equip | B25: 6352000 | C25: 7038000 | D25: 7958000 | E25: 8891000 | F25: 9469000 | G25: 9661000 | H25: 10061000 | I25: 10097000 | J25: 10715000 | K25: 10914000
A26: Accumulated Depreciation | B26: 3341000 | C26: 3518000 | D26: 3969000 | E26: 4437000 | F26: 4725000 | G26: 4795000 | H26: 5157000 | I26: 5306000 | J26: 5634000 | K26: 5914000
A27: Net Property Plant & Equip | B27: 3011000 | C27: 3520000 | D27: 3989000 | E27: 4454000 | F27: 4744000 | G27: 4866000 | H27: 4904000 | I27: 4791000 | J27: 5081000 | K27: 5000000
A28: Intangible Assets | B28: 412000 | C28: 412000 | D28: 422000 | E28: 439000 | F28: 437000 | G28: 497000 | H28: 511000 | I28: 570000 | J28: 555000 | K28: 499000
A29: Other Assets | B29: 2201000 | C29: 2439000 | D29: 2787000 | E29: 2509000 | F29: 2011000 | G29: 5423000 | H29: 6034000 | I29: 6747000 | J29: 6693000 | K29: 7229000
A30: Total Assets | B30: 21600000 | C30: 21396000 | D30: 23259000 | E30: 22536000 | F30: 23717000 | G30: 31342000 | H30: 37740000 | I30: 40321000 | J30: 37531000 | K30: 38110000
A31: Accounts Payable & Accrued Exps | B31: 6082000 | C31: 5228000 | D31: 5059000 | E31: 5548000 | F31: 7622000 | G31: 7432000 | H31: 8899000 | I31: 9578000 | J31: 8585000 | K31: 8576000
A32: Accounts Payable | B32: 2131000 | C32: 2191000 | D32: 2048000 | E32: 2279000 | F32: 2612000 | G32: 2248000 | H32: 2836000 | I32: 3358000 | J32: 2862000 | K32: 2851000
A33: Accrued Expenses | B33: 3951000 | C33: 3037000 | D33: 3011000 | E33: 3269000 | F33: 5010000 | G33: 5184000 | H33: 6063000 | I33: 6220000 | J33: 5723000 | K33: 5725000
A34: Current Debt | B34: 181000 | C34: 45000 | D34: 331000 | E34: 342000 | F34: 15000 | G34: 251000 | H34: 2000 | I34: 510000 | J34: 6000 | K34: 1006000
... A37: LT Debt & Leases | B37: 1079000 | C37: 2010000 | D37: 3471000 | E37: 3468000 | F37: 3464000 | G37: 9406000 | H37: 9413000 | I37: 8920000 | J37: 8927000 | K37: 7903000
A38: Deferred LT Liabilities | B38: - | C38: - | D38: - | E38: - | F38: - | G38: - | H38: - | I38: - | J38: - | K38: 2618000
A39: Other Liabilities | B39: 1480000 | C39: 1770000 | D39: 1907000 | E39: 3216000 | F39: 3347000 | G39: 5597000 | H39: 5886000 | I39: 5390000 | J39: 5344000 | K39: 2566000
A40: Total Liabilities | B40: 8893000 | C40: 9138000 | D40: 10852000 | E40: 12724000 | F40: 14677000 | G40: 23287000 | H40: 24973000 | I40: 25040000 | J40: 23527000 | K40: 23680000
A41: Common Share Capital | B41: 3000 | C41: 3000 | D41: 3000 | E41: 3000 | F41: 3000 | G41: 3000 | H41: 3000 | I41: 3000 | J41: 3000 | K41: 3000
A42: Additional Paid-In Capital | B42: 6773000 | C42: 7786000 | D42: 8638000 | E42: 6384000 | F42: 7163000 | G42: 8299000 | H42: 9965000 | I42: 11484000 | J42: 12412000 | K42: 13409000
A43: Retained Earnings | B43: 4685000 | C43: 4151000 | D43: 3979000 | E43: 3517000 | F43: 1643000 | G43: -191000 | H43: 3179000 | I43: 3476000 | J43: 1358000 | K43: 965000
A44: Accum Other Comprehensive Income | B44: 1246000 | C44: 318000 | D44: -213000 | E44: -92000 | F44: 231000 | G44: -56000 | H44: -380000 | I44: 318000 | J44: 231000 | K44: 53000
A45: For Curr Trans (BS) | B45: -11000 | C45: -207000 | D45: -191000 | E45: -173000 | F45: -346000 | G45: -494000 | H45: 2000 | I45: -520000 | J45: -253000 | K45: -256000
A46: Other Equity | B46: 11000 | C46: 207000 | D46: 191000 | E46: 173000 | F46: 346000 | G46: 494000 | H46: -2000 | I46: 520000 | J46: 253000 | K46: 256000
A47: Total Equity | B47: 12707000 | C47: 12258000 | D47: 12407000 | E47: 9812000 | F47: 9040000 | G47: 8055000 | H47: 12767000 | I47: 15281000 | J47: 14004000 | K47: 14430000
A48: Total Liabilities & Equity | B48: 21600000 | C48: 21396000 | D48: 23259000 | E48: 22536000 | F48: 23717000 | G48: 31342000 | H48: 37740000 | I48: 40321000 | J48: 37531000 | K48: 38110000

Sheet Ratios
B2: Max Points | C2: 4
B3: Points
A4: Powered by Clearbit
A5: NIKE Inc (NYS: NKE)
A8: Report Date | B8: ='Income Statement'!B11 -> 05/31/2015 | C8: ='Income Statement'!C11 -> 05/31/2016 | D8: ='Income Statement'!D11 -> 05/31/2017 | E8: ='Income Statement'!E11 -> 05/31/2018 | F8: ='Income Statement'!F11 -> 05/31/2019 | G8: ='Income Statement'!G11 -> 05/31/2020 | H8: ='Income Statement'!H11 -> 05/31/2021 | I8: ='Income Statement'!I11 -> 05/31/2022 | ... K8: ='Income Statement'!K11 -> 05/31/2024
A10: Please compute at least two short-term solvency ratios and comment on the short-term financial position of Nike during the period.
A14: Please compute at least two long-term solvency ratios and comment on the long-term financial position of Nike's duringthe period
A18: Please compute at least two profitability ratios and comment on the profitability of Nike during the period
A22: Please compute the Total Asset Turnover ratio and comment on what this ratio represents and what your results indicate
A26: Please compute the Inventory Turnover and the Days in Inventory ratios and comment on what these ratios represent and what your results indicate.
A30: Feel free to use visuals if/where appropriate

Sheet Valuation
C2: Max Points | D2: 4
C3: Points
B5: Assume that the Net Income of Nike represents the dividends that Nike pays. In other words, assume that Net Income = Dividend | C5: note that this is an assumption for the purposes of this question only, it is not actualy true for Nike.
B7: 1. Assume that Nike's 2025 net income (dividend) will be 4% higher than its 2024 net income. For the purposes of this question, assume that the year ending May 31, 2024 is the full year 2024 of Nike.
B9: 2. Assume that you are conducting this analysis on June 1, 2024 and that the dividends are paid on May 31 of each year;
B11: 3. Assume that the net income (dividend) of Nike will grow at a rate of 5% in 2026, at a rate of 7% in 2027, at a rate of 8% in 2028, at a rate of 5% in 2029, and at a rate of 4% thereafter and forever into the future
B13: 4. Assume that you are considering investing in Nike and that you want to make a 13% annual return on your investment. Based on your analysis, would you be willing to invest in Nike? Why? Please provide both a mathematical solution and a written explanation.
B15: Please look up today's stock price:
B16: Please use the Number of Shares Outstanding from the 2024 statements provided in this file for the calculations:
B18: Bonus Question - 1 extra point
B19: At what rate of return (approximatelly) would you be indifferent about buying or not buying the stock of Nike under above assumptions?
