Workbook

Sheet standardized
A4: Powered by Clearbit
A5: Johnson & Johnson (NYS: JNJ)
A7: Exchange rate used is that of the Year End reported date
A10: Standardized Annual Income Statement
A11: Report Date | B11: 12/28/2014 | C11: 01/03/2016 | D11: 01/01/2017 | E11: 12/31/2017 | F11: 12/30/2018 | G11: 12/29/2019 | H11: 01/03/2021 | I11: 01/02/2022 | J11: 01/01/2023 | K11: 12/31/2023
A12: Currency | B12: USD | C12: USD | D12: USD | E12: USD | F12: USD | G12: USD | H12: USD | I12: USD | J12: USD | K12: USD
A13: Audit Status | B13: Not Qualified | C13: Not Qualified | D13: Not Qualified | E13: Not Qualified | F13: Not Qualified | G13: Not Qualified | H13: Not Qualified | I13: Not Qualified | J13: Not Qualified | K13: Not Qualified
A14: Consolidated | B14: Yes | C14: Yes | D14: Yes | E14: Yes | F14: Yes | G14: Yes | H14: Yes | I14: Yes | J14: Yes | K14: Yes
A15: Sales Growth | C15: =C18/B18-1 -> -0.057270856 | D15: =D18/C18-1 -> 0.025915461 | E15: =E18/D18-1 -> 0.063430241 | F15: =F18/E18-1 -> 0.067115762 | G15: =G18/F18-1 -> 0.0058592074 | H15: =H18/G18-1 -> 0.0063978357 | I15: =I18/H18-1 -> 0.13551051 | J15: =J18/I18-1 -> 0.012455345 | K15: =K18/J18-1 -> -0.1030513 | L15: =AVERAGE(C15:K15) -> 0.017373578
A16: Scale | B16: Millions | C16: Millions | D16: Millions | E16: Millions | F16: Millions | G16: Millions | H16: Millions | I16: Millions | J16: Millions | K16: Millions
B17: 74331 | C17: 70074 | D17: 71890 | E17: 76450 | F17: 81581 | G17: 82059 | H17: 82584 | I17: 93775 | J17: 94943 | K17: 85159
A18: Total Revenue | B18: 74331 | C18: 70074 | D18: 71890 | E18: 76450 | F18: 81581 | G18: 82059 | H18: 82584 | I18: 93775 | J18: 94943 | K18: 85159
A19: Direct Costs | B19: 22746 | C19: 21536 | D19: 21685 | E19: 25354 | F19: 27091 | G19: 27556 | H19: 28427 | I19: 29855 | J19: 31089 | K19: 26553
A20: Gross Profit | B20: 51585 | C20: 48538 | D20: 50205 | E20: 51096 | F20: 54490 | G20: 54503 | H20: 54157 | I20: 63920 | J20: 63854 | K20: 58606
A21: Selling General & Admin | B21: 21954 | C21: 21203 | D21: 19945 | E21: 21420 | F21: 22540 | G21: 22178 | H21: 22084 | I21: 24659 | J21: 24765 | K21: 21512
A22: Research & Development | B22: 8672 | C22: 9270 | D22: 9124 | E22: 10962 | F22: 11901 | G22: 12245 | H22: 12340 | I22: 15614 | J22: 15386 | K22: 15398
A23: Restruct Remediation & Impair | B23: - | C23: 509 | D23: 491 | E23: 309 | F23: 251 | G23: 266 | H23: 247 | I23: 252 | J23: 321 | K23: 489
A24: Other Operating Expense | B24: 0 | C24: 0 | D24: 0 | E24: 0 | F24: 0 | G24: 0 | H24: 0 | I24: 0 | J24: 0 | K24: 6634
A25: Total Indirect Operating Costs | B25: 30626 | C25: 30982 | D25: 29560 | E25: 32691 | F25: 34692 | G25: 34689 | H25: 34671 | I25: 40525 | J25: 40472 | K25: 44033
A26: Operating Income | B26: 20959 | C26: 17556 | D26: 20645 | E26: 18405 | F26: 19798 | G26: 19814 | H26: 19486 | I26: 23395 | J26: 23382 | K26: 14573
A27: Interest Income | B27: -466 | C27: -424 | D27: -358 | E27: -549 | F27: -394 | G27: 39 | H27: -90 | I27: -130 | J27: 214 | K27: 489
A28: Other Non-Operating Income | B28: 70 | C28: 2064 | D28: -484 | E28: -183 | F28: -1405 | G28: -2525 | H28: -2899 | I28: -489 | J28: -1871 | K28: 0
A29: Total Non-Operating Income | B29: -396 | C29: 1640 | D29: -842 | E29: -732 | F29: -1799 | G29: -2486 | H29: -2989 | I29: -619 | J29: -1657 | K29: 489
A30: Earnings Before Tax | B30: 20563 | C30: 19196 | D30: 19803 | E30: 17673 | F30: 17999 | G30: 17328 | H30: 16497 | I30: 22776 | J30: 21725 | K30: 15062
A31: Taxation | B31: 4240 | C31: 3787 | D31: 3263 | E31: 16373 | F31: 2702 | G31: 2209 | H31: 1783 | I31: 1898 | J31: 3784 | K31: 1736
A32: Discontinued Operations | B32: - | C32: - | D32: - | E32: - | F32: - | G32: - | H32: - | I32: - | J32: - | K32: 21827
A33: Extraordinary Items | B33: 0 | C33: 0 | D33: 0 | E33: 0 | F33: 0 | G33: 0 | H33: 0 | I33: 0 | J33: 0 | K33: 0
A34: Accounting Changes | B34: 0 | C34: 0 | D34: 0 | E34: 0 | F34: 0 | G34: 0 | H34: 0 | I34: 0 | J34: 0 | K34: 0
A35: Net Income | B35: 16323 | C35: 15409 | D35: 16540 | E35: 1300 | F35: 15297 | G35: 15119 | H35: 14714 | I35: 20878 | J35: 17941 | K35: 35153
A36: Preference Dividends & Similar | B36: 0 | C36: 0 | D36: 0 | E36: 0 | F36: 0 | G36: 0 | H36: 0 | I36: 0 | J36: 0 | K36: 0
A37: Net Income to Common | B37: 16323 | C37: 15409 | D37: 16540 | E37: 1300 | F37: 15297 | G37: 15119 | H37: 14714 | I37: 20878 | J37: 17941 | K37: 35153
A38: Average Shares Basic | B38: 2815.2 | C38: 2771.8 | D38: 2737.3 | E38: 2692 | F38: 2681.5 | G38: 2645.1 | H38: 2632.8 | I38: 2632.1 | J38: 2625.2 | K38: 2533.5
A39: EPS Net Basic | B39: 5.8 | C39: 5.56 | D39: 6.04 | E39: 0.48 | F39: 5.7 | G39: 5.72 | H39: 5.59 | I39: 7.93 | J39: 6.83 | K39: 13.88
A40: EPS Continuing Basic | B40: 5.8 | C40: 5.56 | D40: 6.04 | E40: 0.48 | F40: 5.7 | G40: 5.72 | H40: 5.59 | I40: 7.93 | J40: 6.83 | K40: 5.26
A41: Average Shares Diluted | B41: 2863.9 | C41: 2812.9 | D41: 2788.9 | E41: 2745.3 | F41: 2728.7 | G41: 2684.3 | H41: 2670.7 | I41: 2674 | J41: 2663.9 | K41: 2560.4
A42: EPS Net Diluted | B42: 5.7 | C42: 5.48 | D42: 5.93 | E42: 0.47 | F42: 5.61 | G42: 5.63 | H42: 5.51 | I42: 7.81 | J42: 6.73 | K42: 13.72
A43: EPS Continuing Diluted | B43: 5.7 | C43: 5.48 | D43: 5.93 | E43: 0.47 | F43: 5.61 | G43: 5.63 | H43: 5.51 | I43: 7.81 | J43: 6.73 | K43: 5.2
A44: Shares Outstanding | B44: 2783.223 | C44: 2755.162 | D44: 2706.511 | E44: 2682.525 | F44: 2662.324 | G44: 2632.507 | H44: 2632.512 | I44: 2628.965 | J44: 2613.597 | K44: 2407.078
A48: maybe do macroeconomic factor on the project sales growth

Sheet Sheet1
A3: Johnson & Johnson (NYS: JNJ)
A5: Exchange rate used is that of the Year End reported date
A8: Standardized Annual Income Statement
A9: Report Date | B9: 12/28/2014 | C9: 01/03/2016 | D9: 01/01/2017 | E9: 12/31/2017 | F9: 12/30/2018 | G9: 12/29/2019 | H9: 01/03/2021 | I9: 01/02/2022 | J9: 01/01/2023 | K9: 12/31/2023
A10: Currency
A11: Audit Status
A12: Consolidated
A13: Sales Growth
A14: Scale
A15: Sales Revenue
A16: Total Revenue | B16: =standardized!B18/standardized!B$18 -> 1 | C16: =standardized!C18/standardized!C$18 -> 1 | D16: =standardized!D18/standardized!D$18 -> 1 | E16: =standardized!E18/standardized!E$18 -> 1 | F16: =standardized!F18/standardized!F$18 -> 1 | G16: =standardized!G18/standardized!G$18 -> 1 | H16: =standardized!H18/standardized!H$18 -> 1 | I16: =standardized!I18/standardized!I$18 -> 1 | ... K16: =standardized!K18/standardized!K$18 -> 1
A17: Direct Costs | B17: =standardized!B19/standardized!B$18 -> 0.30600961 | C17: =standardized!C19/standardized!C$18 -> 0.30733225 | D17: =standardized!D19/standardized!D$18 -> 0.3016414 | E17: =standardized!E19/standardized!E$18 -> 0.3316416 | F17: =standardized!F19/standardized!F$18 -> 0.33207487 | G17: =standardized!G19/standardized!G$18 -> 0.33580716 | H17: =standardized!H19/standardized!H$18 -> 0.34421922 | I17: =standardized!I19/standardized!I$18 -> 0.31836844 | ... K17: =standardized!K19/standardized!K$18 -> 0.31180498
A18: Gross Profit | B18: =standardized!B20/standardized!B$18 -> 0.69399039 | C18: =standardized!C20/standardized!C$18 -> 0.69266775 | D18: =standardized!D20/standardized!D$18 -> 0.6983586 | E18: =standardized!E20/standardized!E$18 -> 0.6683584 | F18: =standardized!F20/standardized!F$18 -> 0.66792513 | G18: =standardized!G20/standardized!G$18 -> 0.66419284 | H18: =standardized!H20/standardized!H$18 -> 0.65578078 | I18: =standardized!I20/standardized!I$18 -> 0.68163156 | ... K18: =standardized!K20/standardized!K$18 -> 0.68819502
A19: Selling General & Admin | B19: =standardized!B21/standardized!B$18 -> 0.29535456 | C19: =standardized!C21/standardized!C$18 -> 0.30258013 | D19: =standardized!D21/standardized!D$18 -> 0.27743775 | E19: =standardized!E21/standardized!E$18 -> 0.28018313 | F19: =standardized!F21/standardized!F$18 -> 0.27628982 | G19: =standardized!G21/standardized!G$18 -> 0.27026895 | H19: =standardized!H21/standardized!H$18 -> 0.26741257 | I19: =standardized!I21/standardized!I$18 -> 0.26295921 | ... K19: =standardized!K21/standardized!K$18 -> 0.25260982
A20: Research & Development | B20: =standardized!B22/standardized!B$18 -> 0.11666734 | C20: =standardized!C22/standardized!C$18 -> 0.13228872 | D20: =standardized!D22/standardized!D$18 -> 0.12691612 | E20: =standardized!E22/standardized!E$18 -> 0.14338784 | F20: =standardized!F22/standardized!F$18 -> 0.14587956 | G20: =standardized!G22/standardized!G$18 -> 0.1492219 | H20: =standardized!H22/standardized!H$18 -> 0.14942362 | I20: =standardized!I22/standardized!I$18 -> 0.16650493 | ... K20: =standardized!K22/standardized!K$18 -> 0.18081471
A21: Restruct Remediation & Impair | B21: =standardized!B23/standardized!B$18 -> #VALUE! | C21: =standardized!C23/standardized!C$18 -> 0.0072637498 | D21: =standardized!D23/standardized!D$18 -> 0.006829879 | E21: =standardized!E23/standardized!E$18 -> 0.0040418574 | F21: =standardized!F23/standardized!F$18 -> 0.0030766968 | G21: =standardized!G23/standardized!G$18 -> 0.0032415701 | H21: =standardized!H23/standardized!H$18 -> 0.0029908941 | I21: =standardized!I23/standardized!I$18 -> 0.0026872834 | ... K21: =standardized!K23/standardized!K$18 -> 0.0057421999
A22: Other Operating Expense | B22: =standardized!B24/standardized!B$18 -> 0 | C22: =standardized!C24/standardized!C$18 -> 0 | D22: =standardized!D24/standardized!D$18 -> 0 | E22: =standardized!E24/standardized!E$18 -> 0 | F22: =standardized!F24/standardized!F$18 -> 0 | G22: =standardized!G24/standardized!G$18 -> 0 | H22: =standardized!H24/standardized!H$18 -> 0 | I22: =standardized!I24/standardized!I$18 -> 0 | ... K22: =standardized!K24/standardized!K$18 -> 0.077901337
A23: Total Indirect Operating Costs | B23: =standardized!B25/standardized!B$18 -> 0.4120219 | C23: =standardized!C25/standardized!C$18 -> 0.4421326 | D23: =standardized!D25/standardized!D$18 -> 0.41118375 | E23: =standardized!E25/standardized!E$18 -> 0.42761282 | F23: =standardized!F25/standardized!F$18 -> 0.42524607 | G23: =standardized!G25/standardized!G$18 -> 0.42273242 | H23: =standardized!H25/standardized!H$18 -> 0.41982709 | I23: =standardized!I25/standardized!I$18 -> 0.43215143 | ... K23: =standardized!K25/standardized!K$18 -> 0.51706807
A24: Operating Income | B24: =standardized!B26/standardized!B$18 -> 0.28196849 | C24: =standardized!C26/standardized!C$18 -> 0.25053515 | D24: =standardized!D26/standardized!D$18 -> 0.28717485 | E24: =standardized!E26/standardized!E$18 -> 0.24074559 | F24: =standardized!F26/standardized!F$18 -> 0.24267906 | G24: =standardized!G26/standardized!G$18 -> 0.24146041 | H24: =standardized!H26/standardized!H$18 -> 0.2359537 | I24: =standardized!I26/standardized!I$18 -> 0.24948014 | ... K24: =standardized!K26/standardized!K$18 -> 0.17112695
A25: Interest Income | B25: =standardized!B27/standardized!B$18 -> -0.0062692551 | C25: =standardized!C27/standardized!C$18 -> -0.0060507464 | D25: =standardized!D27/standardized!D$18 -> -0.0049798303 | E25: =standardized!E27/standardized!E$18 -> -0.0071811642 | F25: =standardized!F27/standardized!F$18 -> -0.0048295559 | G25: =standardized!G27/standardized!G$18 -> 0.0004752678 | H25: =standardized!H27/standardized!H$18 -> -0.0010897995 | I25: =standardized!I27/standardized!I$18 -> -0.001386297 | ... K25: =standardized!K27/standardized!K$18 -> 0.0057421999
A26: Other Non-Operating Income | B26: =standardized!B28/standardized!B$18 -> 0.0009417336 | C26: =standardized!C28/standardized!C$18 -> 0.029454577 | D26: =standardized!D28/standardized!D$18 -> -0.006732508 | E26: =standardized!E28/standardized!E$18 -> -0.0023937214 | F26: =standardized!F28/standardized!F$18 -> -0.017222147 | G26: =standardized!G28/standardized!G$18 -> -0.030770543 | H26: =standardized!H28/standardized!H$18 -> -0.035103652 | I26: =standardized!I28/standardized!I$18 -> -0.0052146094 | ... K26: =standardized!K28/standardized!K$18 -> 0
A27: Total Non-Operating Income | B27: =standardized!B29/standardized!B$18 -> -0.0053275215 | C27: =standardized!C29/standardized!C$18 -> 0.02340383 | D27: =standardized!D29/standardized!D$18 -> -0.011712338 | E27: =standardized!E29/standardized!E$18 -> -0.0095748855 | F27: =standardized!F29/standardized!F$18 -> -0.022051703 | G27: =standardized!G29/standardized!G$18 -> -0.030295275 | H27: =standardized!H29/standardized!H$18 -> -0.036193452 | I27: =standardized!I29/standardized!I$18 -> -0.0066009064 | ... K27: =standardized!K29/standardized!K$18 -> 0.0057421999
... A33: Net Income | B33: =standardized!B35/standardized!B$18 -> 0.21959882 | C33: =standardized!C35/standardized!C$18 -> 0.21989611 | D33: =standardized!D35/standardized!D$18 -> 0.23007372 | E33: =standardized!E35/standardized!E$18 -> 0.017004578 | F33: =standardized!F35/standardized!F$18 -> 0.18750689 | G33: =standardized!G35/standardized!G$18 -> 0.18424548 | H33: =standardized!H35/standardized!H$18 -> 0.17817011 | I33: =standardized!I35/standardized!I$18 -> 0.2226393 | ... K33: =standardized!K35/standardized!K$18 -> 0.41279254
A34: Preference Dividends & Similar
A35: Net Income to Common
A36: Average Shares Basic
A37: EPS Net Basic
A38: EPS Continuing Basic
A39: Average Shares Diluted
A40: EPS Net Diluted
A41: EPS Continuing Diluted
A42: Shares Outstanding

Sheet balancesheet
A1: Johnson & Johnson (NYS: JNJ)
A3: Exchange rate used is that of the Year End reported date
A6: Standardized Annual Balance Sheet
A7: Report Date | B7: 12/28/2014 | C7: 01/03/2016 | D7: 01/01/2017 | E7: 12/31/2017 | F7: 12/30/2018 | G7: 12/29/2019 | H7: 01/03/2021 | I7: 01/02/2022 | J7: 01/01/2023 | K7: 12/31/2023
A8: Currency | B8: USD | C8: USD | D8: USD | E8: USD | F8: USD | G8: USD | H8: USD | I8: USD | J8: USD | K8: USD
A9: Audit Status | B9: Not Qualified | C9: Not Qualified | D9: Not Qualified | E9: Not Qualified | F9: Not Qualified | G9: Not Qualified | H9: Not Qualified | I9: Not Qualified | J9: Not Qualified | K9: Not Qualified
A10: Consolidated | B10: Yes | C10: Yes | D10: Yes | E10: Yes | F10: Yes | G10: Yes | H10: Yes | I10: Yes | J10: Yes | K10: Yes
A11: Scale | B11: Millions | C11: Millions | D11: Millions | E11: Millions | F11: Millions | G11: Millions | H11: Millions | I11: Millions | J11: Millions | K11: Millions
A12: Cash & Equivalents | B12: 14523 | C12: 13732 | D12: 18972 | E12: 17824 | F12: 18107 | G12: 17305 | H12: 13985 | I12: 14487 | J12: 14127 | K12: 21859
A13: Short Term Investments | B13: 18566 | C13: 24644 | D13: 22935 | E13: 472 | F13: 1580 | G13: 1982 | H13: 11200 | I13: 17121 | J13: 9392 | K13: 1068
A14: Cash & Equivs & ST Investments | B14: 33089 | C14: 38376 | D14: 41907 | E14: 18296 | F14: 19687 | G14: 19287 | H14: 25185 | I14: 31608 | J14: 23519 | K14: 22927
A15: Receivables (ST) | B15: 10985 | C15: 10734 | D15: 11699 | E15: 13490 | F15: 14098 | G15: 14481 | H15: 13576 | I15: 15283 | J15: 16160 | K15: 14873
A16: Inventories | B16: 8184 | C16: 8053 | D16: 8144 | E16: 8765 | F16: 8599 | G16: 9020 | H16: 9344 | I16: 10387 | J16: 12483 | K16: 11181
A17: Current Tax Assets | B17: 3567 | C17: - | D17: - | E17: - | F17: - | G17: - | H17: - | I17: - | J17: - | K17: -
A18: Assets Held for Sale (ST) | B18: - | C18: - | D18: - | E18: - | F18: 950 | G18: 94 | H18: - | I18: - | J18: - | K18: -
A19: Other Current Assets | B19: 3486 | C19: 3047 | D19: 3282 | E19: 2537 | F19: 2699 | G19: 2392 | H19: 3132 | I19: 3701 | J19: 3132 | K19: 4514
A20: Total Current Assets | B20: 59311 | C20: 60210 | D20: 65032 | E20: 43088 | F20: 46033 | G20: 45274 | H20: 51237 | I20: 60979 | J20: 55294 | K20: 53495
A21: Gross Property Plant & Equip | B21: 36685 | C21: 36648 | D21: 37773 | E21: 41466 | F21: 41851 | G21: 43332 | H21: 46804 | I21: 47679 | J21: 49253 | K21: 47776
A22: Accumulated Depreciation | B22: 20559 | C22: 20743 | D22: 21861 | E22: 24461 | F22: 24816 | G22: 25674 | H22: 28038 | I22: 28717 | J22: 29450 | K22: 27878
A23: Net Property Plant & Equip | B23: 16126 | C23: 15905 | D23: 15912 | E23: 17005 | F23: 17035 | G23: 17658 | H23: 18766 | I23: 18962 | J23: 19803 | K23: 19898
A24: Intangible Assets | B24: 49054 | C24: 47393 | D24: 49681 | E24: 85134 | F24: 78064 | G24: 81282 | H24: 89795 | I24: 81638 | J24: 93556 | K24: 70733
A25: Deferred LT Assets | B25: 3396 | C25: 5490 | D25: 6148 | E25: 7105 | F25: 7640 | G25: 7819 | H25: 8534 | I25: 10223 | J25: 9123 | K25: 9279
A26: Other Assets | B26: 3232 | C26: 4413 | D26: 4435 | E26: 4971 | F26: 4182 | G26: 5695 | H26: 6562 | I26: 10216 | J26: 9602 | K26: 14153
A27: Total Assets | B27: 131119 | C27: 133411 | D27: 141208 | E27: 157303 | F27: 152954 | G27: 157728 | H27: 174894 | I27: 182018 | J27: 187378 | K27: 167558
A28: Accounts Payable & Accrued Exps | B28: 21447 | C28: 20743 | D28: 21603 | E28: 26631 | F28: 28434 | G28: 34762 | H28: 39862 | I28: 41460 | J28: 43031 | K28: 42831
A29: Accounts Payable | B29: 7633 | C29: 6668 | D29: 6918 | E29: 7310 | F29: 7537 | G29: 8544 | H29: 9505 | I29: 11055 | J29: 11703 | K29: 9632
A30: Accrued Expenses | B30: 13814 | C30: 14075 | D30: 14685 | E30: 19321 | F30: 20897 | G30: 26218 | H30: 30357 | I30: 30405 | J30: 31328 | K30: 33199
... A47: Total Liabilities & Equity | B47: 131119 | C47: 133411 | D47: 141208 | E47: 157303 | F47: 152954 | G47: 157728 | H47: 174894 | I47: 182018 | J47: 187378 | K47: 167558

Sheet Sheet3
A3: Standardized Annual Balance Sheet
A4: Report Date | D4: 12/28/2014 | E4: 01/03/2016 | F4: 01/01/2017 | G4: 12/31/2017 | H4: 12/30/2018 | I4: 12/29/2019 | J4: 01/03/2021 | K4: 01/02/2022 | L4: 01/01/2023 | M4: 12/31/2023
A5: Currency
A6: Audit Status
A7: Consolidated
A8: Scale
A9: Cash & Equivalents | D9: =balancesheet!B12/balancesheet!B$27 -> 0.11076198 | E9: =balancesheet!C12/balancesheet!C$27 -> 0.10293004 | F9: =balancesheet!D12/balancesheet!D$27 -> 0.13435499 | G9: =balancesheet!E12/balancesheet!E$27 -> 0.11330998 | H9: =balancesheet!F12/balancesheet!F$27 -> 0.118382 | I9: =balancesheet!G12/balancesheet!G$27 -> 0.10971419 | J9: =balancesheet!H12/balancesheet!H$27 -> 0.07996272 | K9: =balancesheet!I12/balancesheet!I$27 -> 0.079591029
A10: Short Term Investments | D10: =balancesheet!B13/balancesheet!B$27 -> 0.14159656 | E10: =balancesheet!C13/balancesheet!C$27 -> 0.1847224 | F10: =balancesheet!D13/balancesheet!D$27 -> 0.16241998 | G10: =balancesheet!E13/balancesheet!E$27 -> 0.0030005785 | H10: =balancesheet!F13/balancesheet!F$27 -> 0.010329903 | I10: =balancesheet!G13/balancesheet!G$27 -> 0.012565936 | J10: =balancesheet!H13/balancesheet!H$27 -> 0.064038789 | K10: =balancesheet!I13/balancesheet!I$27 -> 0.094062126
A11: Cash & Equivs & ST Investments | D11: =balancesheet!B14/balancesheet!B$27 -> 0.25235854 | E11: =balancesheet!C14/balancesheet!C$27 -> 0.28765244 | F11: =balancesheet!D14/balancesheet!D$27 -> 0.29677497 | G11: =balancesheet!E14/balancesheet!E$27 -> 0.11631056 | H11: =balancesheet!F14/balancesheet!F$27 -> 0.1287119 | I11: =balancesheet!G14/balancesheet!G$27 -> 0.12228013 | J11: =balancesheet!H14/balancesheet!H$27 -> 0.14400151 | K11: =balancesheet!I14/balancesheet!I$27 -> 0.17365316
A12: Receivables (ST) | D12: =balancesheet!B15/balancesheet!B$27 -> 0.083778857 | E12: =balancesheet!C15/balancesheet!C$27 -> 0.080458133 | F12: =balancesheet!D15/balancesheet!D$27 -> 0.082849414 | G12: =balancesheet!E15/balancesheet!E$27 -> 0.085758059 | H12: =balancesheet!F15/balancesheet!F$27 -> 0.092171503 | I12: =balancesheet!G15/balancesheet!G$27 -> 0.091809951 | J12: =balancesheet!H15/balancesheet!H$27 -> 0.077624161 | K12: =balancesheet!I15/balancesheet!I$27 -> 0.083964223
A13: Inventories | D13: =balancesheet!B16/balancesheet!B$27 -> 0.062416583 | E13: =balancesheet!C16/balancesheet!C$27 -> 0.060362339 | F13: =balancesheet!D16/balancesheet!D$27 -> 0.057673786 | G13: =balancesheet!E16/balancesheet!E$27 -> 0.055720488 | H13: =balancesheet!F16/balancesheet!F$27 -> 0.056219517 | I13: =balancesheet!G16/balancesheet!G$27 -> 0.057187056 | J13: =balancesheet!H16/balancesheet!H$27 -> 0.053426647 | K13: =balancesheet!I16/balancesheet!I$27 -> 0.057065785
A14: Current Tax Assets | D14: =balancesheet!B17/balancesheet!B$27 -> 0.027204295 | E14: =balancesheet!C17/balancesheet!C$27 -> #VALUE! | F14: =balancesheet!D17/balancesheet!D$27 -> #VALUE! | G14: =balancesheet!E17/balancesheet!E$27 -> #VALUE! | H14: =balancesheet!F17/balancesheet!F$27 -> #VALUE! | I14: =balancesheet!G17/balancesheet!G$27 -> #VALUE! | J14: =balancesheet!H17/balancesheet!H$27 -> #VALUE! | K14: =balancesheet!I17/balancesheet!I$27 -> #VALUE!
A15: Assets Held for Sale (ST) | D15: =balancesheet!B18/balancesheet!B$27 -> #VALUE! | E15: =balancesheet!C18/balancesheet!C$27 -> #VALUE! | F15: =balancesheet!D18/balancesheet!D$27 -> #VALUE! | G15: =balancesheet!E18/balancesheet!E$27 -> #VALUE! | H15: =balancesheet!F18/balancesheet!F$27 -> 0.0062110177 | I15: =balancesheet!G18/balancesheet!G$27 -> 0.00059596267 | J15: =balancesheet!H18/balancesheet!H$27 -> #VALUE! | K15: =balancesheet!I18/balancesheet!I$27 -> #VALUE!
A16: Other Current Assets | D16: =balancesheet!B19/balancesheet!B$27 -> 0.026586536 | E16: =balancesheet!C19/balancesheet!C$27 -> 0.022839196 | F16: =balancesheet!D19/balancesheet!D$27 -> 0.023242309 | G16: =balancesheet!E19/balancesheet!E$27 -> 0.016128109 | H16: =balancesheet!F19/balancesheet!F$27 -> 0.017645828 | I16: =balancesheet!G19/balancesheet!G$27 -> 0.015165348 | J16: =balancesheet!H19/balancesheet!H$27 -> 0.01790799 | K16: =balancesheet!I19/balancesheet!I$27 -> 0.020333154
A17: Total Current Assets | D17: =balancesheet!B20/balancesheet!B$27 -> 0.45234482 | E17: =balancesheet!C20/balancesheet!C$27 -> 0.45131211 | F17: =balancesheet!D20/balancesheet!D$27 -> 0.46054048 | G17: =balancesheet!E20/balancesheet!E$27 -> 0.27391722 | H17: =balancesheet!F20/balancesheet!F$27 -> 0.30095977 | I17: =balancesheet!G20/balancesheet!G$27 -> 0.28703845 | J17: =balancesheet!H20/balancesheet!H$27 -> 0.29296031 | K17: =balancesheet!I20/balancesheet!I$27 -> 0.33501632
A18: Gross Property Plant & Equip | D18: =balancesheet!B21/balancesheet!B$27 -> 0.27978401 | E18: =balancesheet!C21/balancesheet!C$27 -> 0.27469999 | F18: =balancesheet!D21/balancesheet!D$27 -> 0.26749901 | G18: =balancesheet!E21/balancesheet!E$27 -> 0.26360591 | H18: =balancesheet!F21/balancesheet!F$27 -> 0.27361821 | I18: =balancesheet!G21/balancesheet!G$27 -> 0.27472611 | J18: =balancesheet!H21/balancesheet!H$27 -> 0.26761353 | K18: =balancesheet!I21/balancesheet!I$27 -> 0.26194662
A19: Accumulated Depreciation | D19: =balancesheet!B22/balancesheet!B$27 -> 0.1567965 | E19: =balancesheet!C22/balancesheet!C$27 -> 0.15548193 | F19: =balancesheet!D22/balancesheet!D$27 -> 0.15481417 | G19: =balancesheet!E22/balancesheet!E$27 -> 0.15550244 | H19: =balancesheet!F22/balancesheet!F$27 -> 0.16224486 | I19: =balancesheet!G22/balancesheet!G$27 -> 0.16277389 | J19: =balancesheet!H22/balancesheet!H$27 -> 0.16031425 | K19: =balancesheet!I22/balancesheet!I$27 -> 0.15777011
A20: Net Property Plant & Equip | D20: =balancesheet!B23/balancesheet!B$27 -> 0.12298752 | E20: =balancesheet!C23/balancesheet!C$27 -> 0.11921806 | F20: =balancesheet!D23/balancesheet!D$27 -> 0.11268483 | G20: =balancesheet!E23/balancesheet!E$27 -> 0.10810347 | H20: =balancesheet!F23/balancesheet!F$27 -> 0.11137335 | I20: =balancesheet!G23/balancesheet!G$27 -> 0.11195222 | J20: =balancesheet!H23/balancesheet!H$27 -> 0.10729928 | K20: =balancesheet!I23/balancesheet!I$27 -> 0.10417651
... A44: Total Liabilities & Equity | D44: =balancesheet!B47/balancesheet!B$27 -> 1 | E44: =balancesheet!C47/balancesheet!C$27 -> 1 | F44: =balancesheet!D47/balancesheet!D$27 -> 1 | G44: =balancesheet!E47/balancesheet!E$27 -> 1 | H44: =balancesheet!F47/balancesheet!F$27 -> 1 | I44: =balancesheet!G47/balancesheet!G$27 -> 1 | J44: =balancesheet!H47/balancesheet!H$27 -> 1 | K44: =balancesheet!I47/balancesheet!I$27 -> 1

Sheet Sheet4
A3: Standardized Annual Balance Sheet
A4: Report Date | C4: 12/28/2014 | D4: 01/03/2016 | E4: 01/01/2017 | F4: 12/31/2017 | G4: 12/30/2018 | H4: 12/29/2019 | I4: 01/03/2021 | J4: 01/02/2022 | K4: 01/01/2023 | L4: 12/31/2023
A5: Currency
A6: Audit Status
A7: Consolidated
A8: Scale
A9: Cash & Equivalents | C9: =balancesheet!B12/standardized!B$18 -> 0.19538281 | D9: =balancesheet!C12/standardized!B$18 -> 0.18474123 | E9: =balancesheet!D12/standardized!B$18 -> 0.25523671 | F9: =balancesheet!E12/standardized!B$18 -> 0.23979228 | G9: =balancesheet!F12/standardized!B$18 -> 0.24359957 | H9: =balancesheet!G12/standardized!B$18 -> 0.23281 | I9: =balancesheet!H12/standardized!B$18 -> 0.18814492 | J9: =balancesheet!I12/standardized!B$18 -> 0.19489849 | K9: =balancesheet!J12/standardized!B$18 -> 0.19005529 | L9: =balancesheet!K12/standardized!B$18 -> 0.2940765
A10: Short Term Investments | C10: =balancesheet!B13/standardized!B$18 -> 0.24977466 | D10: =balancesheet!C13/standardized!B$18 -> 0.33154404 | E10: =balancesheet!D13/standardized!B$18 -> 0.30855229 | F10: =balancesheet!E13/standardized!B$18 -> 0.0063499751 | G10: =balancesheet!F13/standardized!B$18 -> 0.021256273 | H10: =balancesheet!G13/standardized!B$18 -> 0.026664514 | I10: =balancesheet!H13/standardized!B$18 -> 0.15067738 | J10: =balancesheet!I13/standardized!B$18 -> 0.23033458 | K10: =balancesheet!J13/standardized!B$18 -> 0.12635374 | L10: =balancesheet!K13/standardized!B$18 -> 0.014368164
A11: Cash & Equivs & ST Investments | C11: =balancesheet!B14/standardized!B$18 -> 0.44515747 | D11: =balancesheet!C14/standardized!B$18 -> 0.51628526 | E11: =balancesheet!D14/standardized!B$18 -> 0.563789 | F11: =balancesheet!E14/standardized!B$18 -> 0.24614226 | G11: =balancesheet!F14/standardized!B$18 -> 0.26485585 | H11: =balancesheet!G14/standardized!B$18 -> 0.25947451 | I11: =balancesheet!H14/standardized!B$18 -> 0.33882229 | J11: =balancesheet!I14/standardized!B$18 -> 0.42523308 | K11: =balancesheet!J14/standardized!B$18 -> 0.31640904 | L11: =balancesheet!K14/standardized!B$18 -> 0.30844466
A12: Receivables (ST) | C12: =balancesheet!B15/standardized!B$18 -> 0.14778491 | D12: =balancesheet!C15/standardized!B$18 -> 0.14440812 | E12: =balancesheet!D15/standardized!B$18 -> 0.15739059 | F12: =balancesheet!E15/standardized!B$18 -> 0.18148552 | G12: =balancesheet!F15/standardized!B$18 -> 0.18966515 | H12: =balancesheet!G15/standardized!B$18 -> 0.19481777 | I12: =balancesheet!H15/standardized!B$18 -> 0.1826425 | J12: =balancesheet!I15/standardized!B$18 -> 0.20560735 | K12: =balancesheet!J15/standardized!B$18 -> 0.21740593 | L12: =balancesheet!K15/standardized!B$18 -> 0.20009148
A13: Inventories | C13: =balancesheet!B16/standardized!B$18 -> 0.11010211 | D13: =balancesheet!C16/standardized!B$18 -> 0.10833972 | E13: =balancesheet!D16/standardized!B$18 -> 0.10956398 | F13: =balancesheet!E16/standardized!B$18 -> 0.1179185 | G13: =balancesheet!F16/standardized!B$18 -> 0.11568525 | H13: =balancesheet!G16/standardized!B$18 -> 0.1213491 | I13: =balancesheet!H16/standardized!B$18 -> 0.12570798 | J13: =balancesheet!I16/standardized!B$18 -> 0.13973981 | K13: =balancesheet!J16/standardized!B$18 -> 0.16793801 | L13: =balancesheet!K16/standardized!B$18 -> 0.15042176
A14: Current Tax Assets | C14: =balancesheet!B17/standardized!B$18 -> 0.047988053 | D14: =balancesheet!C17/standardized!B$18 -> #VALUE! | E14: =balancesheet!D17/standardized!B$18 -> #VALUE! | F14: =balancesheet!E17/standardized!B$18 -> #VALUE! | G14: =balancesheet!F17/standardized!B$18 -> #VALUE! | H14: =balancesheet!G17/standardized!B$18 -> #VALUE! | I14: =balancesheet!H17/standardized!B$18 -> #VALUE! | J14: =balancesheet!I17/standardized!B$18 -> #VALUE! | K14: =balancesheet!J17/standardized!B$18 -> #VALUE! | L14: =balancesheet!K17/standardized!B$18 -> #VALUE!
A15: Assets Held for Sale (ST) | C15: =balancesheet!B18/standardized!B$18 -> #VALUE! | D15: =balancesheet!C18/standardized!B$18 -> #VALUE! | E15: =balancesheet!D18/standardized!B$18 -> #VALUE! | F15: =balancesheet!E18/standardized!B$18 -> #VALUE! | G15: =balancesheet!F18/standardized!B$18 -> 0.01278067 | H15: =balancesheet!G18/standardized!B$18 -> 0.0012646137 | I15: =balancesheet!H18/standardized!B$18 -> #VALUE! | J15: =balancesheet!I18/standardized!B$18 -> #VALUE! | K15: =balancesheet!J18/standardized!B$18 -> #VALUE! | L15: =balancesheet!K18/standardized!B$18 -> #VALUE!
A16: Other Current Assets | C16: =balancesheet!B19/standardized!B$18 -> 0.046898333 | D16: =balancesheet!C19/standardized!B$18 -> 0.040992318 | E16: =balancesheet!D19/standardized!B$18 -> 0.044153852 | F16: =balancesheet!E19/standardized!B$18 -> 0.034131116 | G16: =balancesheet!F19/standardized!B$18 -> 0.036310557 | H16: =balancesheet!G19/standardized!B$18 -> 0.032180382 | I16: =balancesheet!H19/standardized!B$18 -> 0.042135852 | J16: =balancesheet!I19/standardized!B$18 -> 0.049790801 | K16: =balancesheet!J19/standardized!B$18 -> 0.042135852 | L16: =balancesheet!K19/standardized!B$18 -> 0.060728364
A17: Total Current Assets | C17: =balancesheet!B20/standardized!B$18 -> 0.79793088 | D17: =balancesheet!C20/standardized!B$18 -> 0.81002543 | E17: =balancesheet!D20/standardized!B$18 -> 0.87489742 | F17: =balancesheet!E20/standardized!B$18 -> 0.57967739 | G17: =balancesheet!F20/standardized!B$18 -> 0.61929747 | H17: =balancesheet!G20/standardized!B$18 -> 0.60908638 | I17: =balancesheet!H20/standardized!B$18 -> 0.68930863 | J17: =balancesheet!I20/standardized!B$18 -> 0.82037104 | K17: =balancesheet!J20/standardized!B$18 -> 0.74388882 | L17: =balancesheet!K20/standardized!B$18 -> 0.71968627
A18: Gross Property Plant & Equip | C18: =balancesheet!B21/standardized!B$18 -> 0.49353567 | D18: =balancesheet!C21/standardized!B$18 -> 0.4930379 | E18: =balancesheet!D21/standardized!B$18 -> 0.5081729 | F18: =balancesheet!E21/standardized!B$18 -> 0.55785608 | G18: =balancesheet!F21/standardized!B$18 -> 0.56303561 | H18: =balancesheet!G21/standardized!B$18 -> 0.58296 | I18: =balancesheet!H21/standardized!B$18 -> 0.62966999 | J18: =balancesheet!I21/standardized!B$18 -> 0.64144166 | K18: =balancesheet!J21/standardized!B$18 -> 0.66261721 | L18: =balancesheet!K21/standardized!B$18 -> 0.64274663
A19: Accumulated Depreciation | C19: =balancesheet!B22/standardized!B$18 -> 0.27658716 | D19: =balancesheet!C22/standardized!B$18 -> 0.27906257 | E19: =balancesheet!D22/standardized!B$18 -> 0.2941034 | F19: =balancesheet!E22/standardized!B$18 -> 0.32908208 | G19: =balancesheet!F22/standardized!B$18 -> 0.33385801 | H19: =balancesheet!G22/standardized!B$18 -> 0.34540098 | I19: =balancesheet!H22/standardized!B$18 -> 0.37720467 | J19: =balancesheet!I22/standardized!B$18 -> 0.38633948 | K19: =balancesheet!J22/standardized!B$18 -> 0.39620078 | L19: =balancesheet!K22/standardized!B$18 -> 0.37505213
A20: Net Property Plant & Equip | C20: =balancesheet!B23/standardized!B$18 -> 0.21694851 | D20: =balancesheet!C23/standardized!B$18 -> 0.21397533 | E20: =balancesheet!D23/standardized!B$18 -> 0.2140695 | F20: =balancesheet!E23/standardized!B$18 -> 0.228774 | G20: =balancesheet!F23/standardized!B$18 -> 0.2291776 | H20: =balancesheet!G23/standardized!B$18 -> 0.23755903 | I20: =balancesheet!H23/standardized!B$18 -> 0.25246532 | J20: =balancesheet!I23/standardized!B$18 -> 0.25510218 | K20: =balancesheet!J23/standardized!B$18 -> 0.26641643 | L20: =balancesheet!K23/standardized!B$18 -> 0.2676945
... A43: Total Equity | C43: =balancesheet!B46/standardized!B$18 -> 0.93839717 | D43: =balancesheet!C46/standardized!B$18 -> 0.95720493 | E43: =balancesheet!D46/standardized!B$18 -> 0.94735709 | F43: =balancesheet!E46/standardized!B$18 -> 0.80935276 | G43: =balancesheet!F46/standardized!B$18 -> 0.8038638 | H43: =balancesheet!G46/standardized!B$18 -> 0.80008341 | I43: =balancesheet!H46/standardized!B$18 -> 0.85130027 | J43: =balancesheet!I46/standardized!B$18 -> 0.99585637 | K43: =balancesheet!J46/standardized!B$18 -> 1.0332701 | L43: =balancesheet!K46/standardized!B$18 -> 0.92523981
A44: Total Liabilities & Equity | C44: =balancesheet!B47/standardized!B$18 -> 1.7639881 | D44: =balancesheet!C47/standardized!B$18 -> 1.7948232 | E44: =balancesheet!D47/standardized!B$18 -> 1.8997188 | F44: =balancesheet!E47/standardized!B$18 -> 2.1162503 | G44: =balancesheet!F47/standardized!F$18 -> 1.8748728 | H44: =balancesheet!G47/standardized!B$18 -> 2.121968 | I44: =balancesheet!H47/standardized!B$18 -> 2.3529079 | J44: =balancesheet!I47/standardized!B$18 -> 2.4487495 | K44: =balancesheet!J47/standardized!B$18 -> 2.5208594 | L44: =balancesheet!K47/standardized!B$18 -> 2.2542143
